package com.chartboost.sdk.impl;

import android.os.Handler;

class j$d
  implements Runnable
{
  private j.a b;
  
  public j$d(j paramj, j.a parama)
  {
    this.b = parama;
  }
  
  private void a(boolean paramBoolean, String paramString)
  {
    j.d(this.a).post(new j.d.1(this, paramBoolean, paramString));
  }
  
  /* Error */
  public void run()
  {
    // Byte code:
    //   0: aload_0
    //   1: getfield 19	com/chartboost/sdk/impl/j$d:b	Lcom/chartboost/sdk/impl/j$a;
    //   4: invokestatic 46	com/chartboost/sdk/impl/j$a:a	(Lcom/chartboost/sdk/impl/j$a;)Lcom/chartboost/sdk/impl/k;
    //   7: astore_1
    //   8: new 48	org/apache/http/client/methods/HttpPost
    //   11: dup
    //   12: new 50	java/lang/StringBuilder
    //   15: dup
    //   16: aload_0
    //   17: getfield 14	com/chartboost/sdk/impl/j$d:a	Lcom/chartboost/sdk/impl/j;
    //   20: invokestatic 53	com/chartboost/sdk/impl/j:b	(Lcom/chartboost/sdk/impl/j;)Ljava/lang/String;
    //   23: invokestatic 59	java/lang/String:valueOf	(Ljava/lang/Object;)Ljava/lang/String;
    //   26: invokespecial 62	java/lang/StringBuilder:<init>	(Ljava/lang/String;)V
    //   29: aload_1
    //   30: invokevirtual 67	com/chartboost/sdk/impl/k:a	()Ljava/lang/String;
    //   33: invokevirtual 71	java/lang/StringBuilder:append	(Ljava/lang/String;)Ljava/lang/StringBuilder;
    //   36: invokevirtual 74	java/lang/StringBuilder:toString	()Ljava/lang/String;
    //   39: invokespecial 75	org/apache/http/client/methods/HttpPost:<init>	(Ljava/lang/String;)V
    //   42: astore_2
    //   43: aload_2
    //   44: ldc 77
    //   46: ldc 79
    //   48: invokevirtual 83	org/apache/http/client/methods/HttpPost:setHeader	(Ljava/lang/String;Ljava/lang/String;)V
    //   51: aload_2
    //   52: ldc 85
    //   54: ldc 79
    //   56: invokevirtual 83	org/apache/http/client/methods/HttpPost:setHeader	(Ljava/lang/String;Ljava/lang/String;)V
    //   59: aload_2
    //   60: ldc 87
    //   62: ldc 89
    //   64: invokevirtual 83	org/apache/http/client/methods/HttpPost:setHeader	(Ljava/lang/String;Ljava/lang/String;)V
    //   67: aload_2
    //   68: ldc 91
    //   70: ldc 93
    //   72: invokevirtual 83	org/apache/http/client/methods/HttpPost:setHeader	(Ljava/lang/String;Ljava/lang/String;)V
    //   75: aload_1
    //   76: invokevirtual 97	com/chartboost/sdk/impl/k:e	()Ljava/util/Map;
    //   79: astore_3
    //   80: aload_3
    //   81: ifnull +26 -> 107
    //   84: aload_3
    //   85: invokeinterface 103 1 0
    //   90: invokeinterface 109 1 0
    //   95: astore 30
    //   97: aload 30
    //   99: invokeinterface 115 1 0
    //   104: ifne +330 -> 434
    //   107: aload_0
    //   108: getfield 14	com/chartboost/sdk/impl/j$d:a	Lcom/chartboost/sdk/impl/j;
    //   111: astore 4
    //   113: aload 4
    //   115: monitorenter
    //   116: iconst_1
    //   117: invokestatic 118	com/chartboost/sdk/impl/j:b	()I
    //   120: iadd
    //   121: istore 6
    //   123: iload 6
    //   125: invokestatic 121	com/chartboost/sdk/impl/j:a	(I)V
    //   128: aload 4
    //   130: monitorexit
    //   131: aload_1
    //   132: invokevirtual 124	com/chartboost/sdk/impl/k:d	()Lorg/json/JSONObject;
    //   135: ifnull +346 -> 481
    //   138: new 126	org/apache/http/entity/StringEntity
    //   141: dup
    //   142: aload_1
    //   143: invokevirtual 124	com/chartboost/sdk/impl/k:d	()Lorg/json/JSONObject;
    //   146: invokevirtual 129	org/json/JSONObject:toString	()Ljava/lang/String;
    //   149: invokespecial 130	org/apache/http/entity/StringEntity:<init>	(Ljava/lang/String;)V
    //   152: astore 12
    //   154: aload 12
    //   156: new 132	org/apache/http/message/BasicHeader
    //   159: dup
    //   160: ldc 77
    //   162: ldc 134
    //   164: invokespecial 136	org/apache/http/message/BasicHeader:<init>	(Ljava/lang/String;Ljava/lang/String;)V
    //   167: invokevirtual 140	org/apache/http/entity/StringEntity:setContentType	(Lorg/apache/http/Header;)V
    //   170: aload_2
    //   171: aload 12
    //   173: invokevirtual 144	org/apache/http/client/methods/HttpPost:setEntity	(Lorg/apache/http/HttpEntity;)V
    //   176: invokestatic 149	com/chartboost/sdk/impl/l:b	()Lorg/apache/http/client/HttpClient;
    //   179: aload_2
    //   180: invokeinterface 155 2 0
    //   185: astore 13
    //   187: aload 13
    //   189: astore 9
    //   191: aload 9
    //   193: invokeinterface 161 1 0
    //   198: invokeinterface 166 1 0
    //   203: istore 14
    //   205: aload 9
    //   207: invokeinterface 170 1 0
    //   212: astore 15
    //   214: aload 15
    //   216: invokeinterface 176 1 0
    //   221: astore 23
    //   223: new 178	java/io/BufferedReader
    //   226: dup
    //   227: new 180	java/io/InputStreamReader
    //   230: dup
    //   231: aload 23
    //   233: ldc 182
    //   235: invokespecial 185	java/io/InputStreamReader:<init>	(Ljava/io/InputStream;Ljava/lang/String;)V
    //   238: sipush 2048
    //   241: invokespecial 188	java/io/BufferedReader:<init>	(Ljava/io/Reader;I)V
    //   244: astore 24
    //   246: new 50	java/lang/StringBuilder
    //   249: dup
    //   250: aload 23
    //   252: invokevirtual 193	java/io/InputStream:available	()I
    //   255: invokespecial 195	java/lang/StringBuilder:<init>	(I)V
    //   258: astore 25
    //   260: aload 24
    //   262: invokevirtual 198	java/io/BufferedReader:readLine	()Ljava/lang/String;
    //   265: astore 26
    //   267: aload 26
    //   269: ifnonnull +303 -> 572
    //   272: aload 24
    //   274: invokevirtual 201	java/io/BufferedReader:close	()V
    //   277: aload 25
    //   279: invokevirtual 74	java/lang/StringBuilder:toString	()Ljava/lang/String;
    //   282: astore 27
    //   284: aload 27
    //   286: astore 17
    //   288: iload 14
    //   290: sipush 300
    //   293: if_icmpge +323 -> 616
    //   296: iload 14
    //   298: sipush 200
    //   301: if_icmplt +315 -> 616
    //   304: aload 17
    //   306: ifnull +414 -> 720
    //   309: new 128	org/json/JSONObject
    //   312: dup
    //   313: new 203	org/json/JSONTokener
    //   316: dup
    //   317: aload 17
    //   319: invokespecial 204	org/json/JSONTokener:<init>	(Ljava/lang/String;)V
    //   322: invokespecial 207	org/json/JSONObject:<init>	(Lorg/json/JSONTokener;)V
    //   325: astore 20
    //   327: aload_0
    //   328: getfield 19	com/chartboost/sdk/impl/j$d:b	Lcom/chartboost/sdk/impl/j$a;
    //   331: invokestatic 46	com/chartboost/sdk/impl/j$a:a	(Lcom/chartboost/sdk/impl/j$a;)Lcom/chartboost/sdk/impl/k;
    //   334: invokevirtual 211	com/chartboost/sdk/impl/k:g	()Lcom/chartboost/sdk/Libraries/d$a;
    //   337: astore 21
    //   339: new 50	java/lang/StringBuilder
    //   342: dup
    //   343: invokespecial 212	java/lang/StringBuilder:<init>	()V
    //   346: astore 22
    //   348: aload 21
    //   350: ifnull +251 -> 601
    //   353: aload 21
    //   355: aload 20
    //   357: aload 22
    //   359: invokevirtual 217	com/chartboost/sdk/Libraries/d$a:a	(Ljava/lang/Object;Ljava/lang/StringBuilder;)Z
    //   362: ifne +239 -> 601
    //   365: new 50	java/lang/StringBuilder
    //   368: dup
    //   369: ldc 219
    //   371: invokespecial 62	java/lang/StringBuilder:<init>	(Ljava/lang/String;)V
    //   374: aload 22
    //   376: invokevirtual 74	java/lang/StringBuilder:toString	()Ljava/lang/String;
    //   379: invokevirtual 71	java/lang/StringBuilder:append	(Ljava/lang/String;)Ljava/lang/StringBuilder;
    //   382: invokevirtual 74	java/lang/StringBuilder:toString	()Ljava/lang/String;
    //   385: astore 10
    //   387: aload 15
    //   389: invokestatic 223	com/chartboost/sdk/Libraries/CBUtility:a	(Lorg/apache/http/HttpEntity;)V
    //   392: aload_0
    //   393: getfield 14	com/chartboost/sdk/impl/j$d:a	Lcom/chartboost/sdk/impl/j;
    //   396: invokestatic 227	com/chartboost/sdk/impl/j:c	(Lcom/chartboost/sdk/impl/j;)Landroid/util/SparseArray;
    //   399: aload_0
    //   400: getfield 19	com/chartboost/sdk/impl/j$d:b	Lcom/chartboost/sdk/impl/j$a;
    //   403: invokestatic 230	com/chartboost/sdk/impl/j$a:b	(Lcom/chartboost/sdk/impl/j$a;)Ljava/lang/Integer;
    //   406: invokevirtual 235	java/lang/Integer:intValue	()I
    //   409: invokevirtual 240	android/util/SparseArray:remove	(I)V
    //   412: aload_0
    //   413: getfield 19	com/chartboost/sdk/impl/j$d:b	Lcom/chartboost/sdk/impl/j$a;
    //   416: invokestatic 243	com/chartboost/sdk/impl/j$a:c	(Lcom/chartboost/sdk/impl/j$a;)Lorg/json/JSONObject;
    //   419: ifnull +290 -> 709
    //   422: iconst_1
    //   423: istore 11
    //   425: aload_0
    //   426: iload 11
    //   428: aload 10
    //   430: invokespecial 245	com/chartboost/sdk/impl/j$d:a	(ZLjava/lang/String;)V
    //   433: return
    //   434: aload 30
    //   436: invokeinterface 249 1 0
    //   441: checkcast 251	java/util/Map$Entry
    //   444: astore 31
    //   446: aload_2
    //   447: aload 31
    //   449: invokeinterface 254 1 0
    //   454: checkcast 55	java/lang/String
    //   457: aload 31
    //   459: invokeinterface 257 1 0
    //   464: invokevirtual 258	java/lang/Object:toString	()Ljava/lang/String;
    //   467: invokevirtual 83	org/apache/http/client/methods/HttpPost:setHeader	(Ljava/lang/String;Ljava/lang/String;)V
    //   470: goto -373 -> 97
    //   473: astore 5
    //   475: aload 4
    //   477: monitorexit
    //   478: aload 5
    //   480: athrow
    //   481: new 50	java/lang/StringBuilder
    //   484: dup
    //   485: ldc_w 260
    //   488: invokespecial 62	java/lang/StringBuilder:<init>	(Ljava/lang/String;)V
    //   491: iload 6
    //   493: invokevirtual 263	java/lang/StringBuilder:append	(I)Ljava/lang/StringBuilder;
    //   496: ldc_w 265
    //   499: invokevirtual 71	java/lang/StringBuilder:append	(Ljava/lang/String;)Ljava/lang/StringBuilder;
    //   502: aload_1
    //   503: invokevirtual 267	com/chartboost/sdk/impl/k:c	()Ljava/lang/String;
    //   506: invokevirtual 71	java/lang/StringBuilder:append	(Ljava/lang/String;)Ljava/lang/StringBuilder;
    //   509: invokevirtual 74	java/lang/StringBuilder:toString	()Ljava/lang/String;
    //   512: pop
    //   513: goto -337 -> 176
    //   516: astore 8
    //   518: aconst_null
    //   519: astore 9
    //   521: new 50	java/lang/StringBuilder
    //   524: dup
    //   525: ldc_w 269
    //   528: invokespecial 62	java/lang/StringBuilder:<init>	(Ljava/lang/String;)V
    //   531: aload 8
    //   533: invokevirtual 272	java/lang/Exception:getLocalizedMessage	()Ljava/lang/String;
    //   536: invokevirtual 71	java/lang/StringBuilder:append	(Ljava/lang/String;)Ljava/lang/StringBuilder;
    //   539: invokevirtual 74	java/lang/StringBuilder:toString	()Ljava/lang/String;
    //   542: astore 10
    //   544: aload 9
    //   546: invokestatic 275	com/chartboost/sdk/Libraries/CBUtility:a	(Lorg/apache/http/HttpResponse;)V
    //   549: aload_0
    //   550: getfield 14	com/chartboost/sdk/impl/j$d:a	Lcom/chartboost/sdk/impl/j;
    //   553: invokestatic 227	com/chartboost/sdk/impl/j:c	(Lcom/chartboost/sdk/impl/j;)Landroid/util/SparseArray;
    //   556: aload_0
    //   557: getfield 19	com/chartboost/sdk/impl/j$d:b	Lcom/chartboost/sdk/impl/j$a;
    //   560: invokestatic 230	com/chartboost/sdk/impl/j$a:b	(Lcom/chartboost/sdk/impl/j$a;)Ljava/lang/Integer;
    //   563: invokevirtual 235	java/lang/Integer:intValue	()I
    //   566: invokevirtual 240	android/util/SparseArray:remove	(I)V
    //   569: goto -157 -> 412
    //   572: aload 25
    //   574: aload 26
    //   576: invokevirtual 71	java/lang/StringBuilder:append	(Ljava/lang/String;)Ljava/lang/StringBuilder;
    //   579: ldc_w 277
    //   582: invokevirtual 71	java/lang/StringBuilder:append	(Ljava/lang/String;)Ljava/lang/StringBuilder;
    //   585: pop
    //   586: goto -326 -> 260
    //   589: astore 16
    //   591: aload 9
    //   593: invokevirtual 258	java/lang/Object:toString	()Ljava/lang/String;
    //   596: astore 17
    //   598: goto -310 -> 288
    //   601: aload_0
    //   602: getfield 19	com/chartboost/sdk/impl/j$d:b	Lcom/chartboost/sdk/impl/j$a;
    //   605: aload 20
    //   607: invokestatic 280	com/chartboost/sdk/impl/j$a:a	(Lcom/chartboost/sdk/impl/j$a;Lorg/json/JSONObject;)V
    //   610: aconst_null
    //   611: astore 10
    //   613: goto -226 -> 387
    //   616: new 50	java/lang/StringBuilder
    //   619: dup
    //   620: ldc_w 282
    //   623: invokespecial 62	java/lang/StringBuilder:<init>	(Ljava/lang/String;)V
    //   626: iload 14
    //   628: invokevirtual 263	java/lang/StringBuilder:append	(I)Ljava/lang/StringBuilder;
    //   631: ldc_w 284
    //   634: invokevirtual 71	java/lang/StringBuilder:append	(Ljava/lang/String;)Ljava/lang/StringBuilder;
    //   637: aload 17
    //   639: invokevirtual 71	java/lang/StringBuilder:append	(Ljava/lang/String;)Ljava/lang/StringBuilder;
    //   642: invokevirtual 74	java/lang/StringBuilder:toString	()Ljava/lang/String;
    //   645: pop
    //   646: aload 15
    //   648: invokestatic 223	com/chartboost/sdk/Libraries/CBUtility:a	(Lorg/apache/http/HttpEntity;)V
    //   651: new 50	java/lang/StringBuilder
    //   654: dup
    //   655: ldc_w 282
    //   658: invokespecial 62	java/lang/StringBuilder:<init>	(Ljava/lang/String;)V
    //   661: iload 14
    //   663: invokevirtual 263	java/lang/StringBuilder:append	(I)Ljava/lang/StringBuilder;
    //   666: ldc_w 286
    //   669: invokevirtual 71	java/lang/StringBuilder:append	(Ljava/lang/String;)Ljava/lang/StringBuilder;
    //   672: invokevirtual 74	java/lang/StringBuilder:toString	()Ljava/lang/String;
    //   675: astore 19
    //   677: aload 19
    //   679: astore 10
    //   681: goto -289 -> 392
    //   684: astore 7
    //   686: aload_0
    //   687: getfield 14	com/chartboost/sdk/impl/j$d:a	Lcom/chartboost/sdk/impl/j;
    //   690: invokestatic 227	com/chartboost/sdk/impl/j:c	(Lcom/chartboost/sdk/impl/j;)Landroid/util/SparseArray;
    //   693: aload_0
    //   694: getfield 19	com/chartboost/sdk/impl/j$d:b	Lcom/chartboost/sdk/impl/j$a;
    //   697: invokestatic 230	com/chartboost/sdk/impl/j$a:b	(Lcom/chartboost/sdk/impl/j$a;)Ljava/lang/Integer;
    //   700: invokevirtual 235	java/lang/Integer:intValue	()I
    //   703: invokevirtual 240	android/util/SparseArray:remove	(I)V
    //   706: aload 7
    //   708: athrow
    //   709: iconst_0
    //   710: istore 11
    //   712: goto -287 -> 425
    //   715: astore 8
    //   717: goto -196 -> 521
    //   720: ldc_w 288
    //   723: astore 10
    //   725: goto -338 -> 387
    // Local variable table:
    //   start	length	slot	name	signature
    //   0	728	0	this	d
    //   7	496	1	localk	k
    //   42	405	2	localHttpPost	org.apache.http.client.methods.HttpPost
    //   79	6	3	localMap	java.util.Map
    //   111	365	4	localj	j
    //   473	6	5	localObject1	Object
    //   121	371	6	i	int
    //   684	23	7	localObject2	Object
    //   516	16	8	localException1	java.lang.Exception
    //   715	1	8	localException2	java.lang.Exception
    //   189	403	9	localHttpResponse1	org.apache.http.HttpResponse
    //   385	339	10	localObject3	Object
    //   423	288	11	bool	boolean
    //   152	20	12	localStringEntity	org.apache.http.entity.StringEntity
    //   185	3	13	localHttpResponse2	org.apache.http.HttpResponse
    //   203	459	14	j	int
    //   212	435	15	localHttpEntity	org.apache.http.HttpEntity
    //   589	1	16	localException3	java.lang.Exception
    //   286	352	17	str1	String
    //   675	3	19	str2	String
    //   325	281	20	localJSONObject	org.json.JSONObject
    //   337	17	21	locala	com.chartboost.sdk.Libraries.d.a
    //   346	29	22	localStringBuilder1	java.lang.StringBuilder
    //   221	30	23	localInputStream	java.io.InputStream
    //   244	29	24	localBufferedReader	java.io.BufferedReader
    //   258	315	25	localStringBuilder2	java.lang.StringBuilder
    //   265	310	26	str3	String
    //   282	3	27	str4	String
    //   95	340	30	localIterator	java.util.Iterator
    //   444	14	31	localEntry	java.util.Map.Entry
    // Exception table:
    //   from	to	target	type
    //   116	131	473	finally
    //   131	176	516	java/lang/Exception
    //   176	187	516	java/lang/Exception
    //   481	513	516	java/lang/Exception
    //   214	260	589	java/lang/Exception
    //   260	267	589	java/lang/Exception
    //   272	284	589	java/lang/Exception
    //   572	586	589	java/lang/Exception
    //   131	176	684	finally
    //   176	187	684	finally
    //   191	214	684	finally
    //   214	260	684	finally
    //   260	267	684	finally
    //   272	284	684	finally
    //   309	348	684	finally
    //   353	387	684	finally
    //   387	392	684	finally
    //   481	513	684	finally
    //   521	549	684	finally
    //   572	586	684	finally
    //   591	598	684	finally
    //   601	610	684	finally
    //   616	677	684	finally
    //   191	214	715	java/lang/Exception
    //   309	348	715	java/lang/Exception
    //   353	387	715	java/lang/Exception
    //   387	392	715	java/lang/Exception
    //   591	598	715	java/lang/Exception
    //   601	610	715	java/lang/Exception
    //   616	677	715	java/lang/Exception
  }
}


/* Location:           C:\Users\vishnu\Desktop\New folder (3)\classes_dex2jar.jar
 * Qualified Name:     com.chartboost.sdk.impl.j.d
 * JD-Core Version:    0.7.0.1
 */