package com.jirbo.adcolony;

final class cl
  extends Thread
{
  Runnable a;
  
  /* Error */
  public final void run()
  {
    // Byte code:
    //   0: aload_0
    //   1: getfield 17	com/jirbo/adcolony/cl:a	Ljava/lang/Runnable;
    //   4: ifnull +17 -> 21
    //   7: aload_0
    //   8: getfield 17	com/jirbo/adcolony/cl:a	Ljava/lang/Runnable;
    //   11: invokeinterface 21 1 0
    //   16: aload_0
    //   17: aconst_null
    //   18: putfield 17	com/jirbo/adcolony/cl:a	Ljava/lang/Runnable;
    //   21: getstatic 27	com/jirbo/adcolony/ck:f	Z
    //   24: ifeq +36 -> 60
    //   27: return
    //   28: astore 6
    //   30: invokestatic 32	com/jirbo/adcolony/a:i	()V
    //   33: new 34	java/lang/StringBuilder
    //   36: dup
    //   37: invokespecial 35	java/lang/StringBuilder:<init>	()V
    //   40: aload 6
    //   42: invokevirtual 39	java/lang/StringBuilder:append	(Ljava/lang/Object;)Ljava/lang/StringBuilder;
    //   45: invokevirtual 43	java/lang/StringBuilder:toString	()Ljava/lang/String;
    //   48: pop
    //   49: invokestatic 32	com/jirbo/adcolony/a:i	()V
    //   52: aload 6
    //   54: invokevirtual 46	java/lang/RuntimeException:printStackTrace	()V
    //   57: goto -41 -> 16
    //   60: aload_0
    //   61: monitorenter
    //   62: getstatic 49	com/jirbo/adcolony/ck:a	Ljava/lang/String;
    //   65: astore_2
    //   66: aload_2
    //   67: monitorenter
    //   68: getstatic 53	com/jirbo/adcolony/ck:b	Ljava/util/ArrayList;
    //   71: aload_0
    //   72: invokevirtual 59	java/util/ArrayList:add	(Ljava/lang/Object;)Z
    //   75: pop
    //   76: aload_2
    //   77: monitorexit
    //   78: aload_0
    //   79: invokevirtual 64	java/lang/Object:wait	()V
    //   82: aload_0
    //   83: monitorexit
    //   84: goto -84 -> 0
    //   87: astore_1
    //   88: aload_0
    //   89: monitorexit
    //   90: aload_1
    //   91: athrow
    //   92: astore_3
    //   93: aload_2
    //   94: monitorexit
    //   95: aload_3
    //   96: athrow
    //   97: astore 5
    //   99: goto -17 -> 82
    // Local variable table:
    //   start	length	slot	name	signature
    //   0	102	0	this	cl
    //   87	4	1	localObject1	java.lang.Object
    //   92	4	3	localObject2	java.lang.Object
    //   97	1	5	localInterruptedException	java.lang.InterruptedException
    //   28	25	6	localRuntimeException	java.lang.RuntimeException
    // Exception table:
    //   from	to	target	type
    //   7	16	28	java/lang/RuntimeException
    //   62	68	87	finally
    //   78	82	87	finally
    //   82	84	87	finally
    //   93	97	87	finally
    //   68	78	92	finally
    //   78	82	97	java/lang/InterruptedException
  }
}


/* Location:           C:\Users\vishnu\Desktop\New folder (3)\classes_dex2jar.jar
 * Qualified Name:     com.jirbo.adcolony.cl
 * JD-Core Version:    0.7.0.1
 */