package com.jirbo.adcolony;

final class ec
{
  private static String a = null;
  
  /* Error */
  public static String a(android.content.Context paramContext)
  {
    // Byte code:
    //   0: ldc 2
    //   2: monitorenter
    //   3: getstatic 10	com/jirbo/adcolony/ec:a	Ljava/lang/String;
    //   6: ifnonnull +99 -> 105
    //   9: new 15	java/io/File
    //   12: dup
    //   13: aload_0
    //   14: invokevirtual 21	android/content/Context:getFilesDir	()Ljava/io/File;
    //   17: ldc 23
    //   19: invokespecial 27	java/io/File:<init>	(Ljava/io/File;Ljava/lang/String;)V
    //   22: astore_2
    //   23: aload_2
    //   24: invokevirtual 31	java/io/File:exists	()Z
    //   27: ifne +32 -> 59
    //   30: new 33	java/io/FileOutputStream
    //   33: dup
    //   34: aload_2
    //   35: invokespecial 36	java/io/FileOutputStream:<init>	(Ljava/io/File;)V
    //   38: astore 4
    //   40: aload 4
    //   42: invokestatic 42	java/util/UUID:randomUUID	()Ljava/util/UUID;
    //   45: invokevirtual 46	java/util/UUID:toString	()Ljava/lang/String;
    //   48: invokevirtual 52	java/lang/String:getBytes	()[B
    //   51: invokevirtual 56	java/io/FileOutputStream:write	([B)V
    //   54: aload 4
    //   56: invokevirtual 59	java/io/FileOutputStream:close	()V
    //   59: new 61	java/io/RandomAccessFile
    //   62: dup
    //   63: aload_2
    //   64: ldc 63
    //   66: invokespecial 64	java/io/RandomAccessFile:<init>	(Ljava/io/File;Ljava/lang/String;)V
    //   69: astore 5
    //   71: aload 5
    //   73: invokevirtual 68	java/io/RandomAccessFile:length	()J
    //   76: l2i
    //   77: newarray byte
    //   79: astore 6
    //   81: aload 5
    //   83: aload 6
    //   85: invokevirtual 71	java/io/RandomAccessFile:readFully	([B)V
    //   88: aload 5
    //   90: invokevirtual 72	java/io/RandomAccessFile:close	()V
    //   93: new 48	java/lang/String
    //   96: dup
    //   97: aload 6
    //   99: invokespecial 74	java/lang/String:<init>	([B)V
    //   102: putstatic 10	com/jirbo/adcolony/ec:a	Ljava/lang/String;
    //   105: getstatic 10	com/jirbo/adcolony/ec:a	Ljava/lang/String;
    //   108: astore 7
    //   110: ldc 2
    //   112: monitorexit
    //   113: aload 7
    //   115: areturn
    //   116: astore_3
    //   117: new 76	com/jirbo/adcolony/dv
    //   120: dup
    //   121: aload_3
    //   122: invokevirtual 77	java/lang/Exception:toString	()Ljava/lang/String;
    //   125: invokespecial 80	com/jirbo/adcolony/dv:<init>	(Ljava/lang/String;)V
    //   128: athrow
    //   129: astore_1
    //   130: ldc 2
    //   132: monitorexit
    //   133: aload_1
    //   134: athrow
    // Local variable table:
    //   start	length	slot	name	signature
    //   0	135	0	paramContext	android.content.Context
    //   129	5	1	localObject	Object
    //   22	42	2	localFile	java.io.File
    //   116	6	3	localException	java.lang.Exception
    //   38	17	4	localFileOutputStream	java.io.FileOutputStream
    //   69	20	5	localRandomAccessFile	java.io.RandomAccessFile
    //   79	19	6	arrayOfByte	byte[]
    //   108	6	7	str	String
    // Exception table:
    //   from	to	target	type
    //   23	59	116	java/lang/Exception
    //   59	105	116	java/lang/Exception
    //   3	23	129	finally
    //   23	59	129	finally
    //   59	105	129	finally
    //   105	110	129	finally
    //   117	129	129	finally
  }
}


/* Location:           C:\Users\vishnu\Desktop\New folder (3)\classes_dex2jar.jar
 * Qualified Name:     com.jirbo.adcolony.ec
 * JD-Core Version:    0.7.0.1
 */