package com.jirbo.adcolony;

import android.app.Activity;
import android.content.Intent;
import java.util.ArrayList;

public final class g
{
  f a = new f(this);
  d b = new d(this);
  bu c = new bu(this);
  cc d = new cc(this);
  ce e = new ce(this);
  cg f = new cg(this);
  dk g = new dk(this);
  ca h = new ca(this);
  ArrayList<an> i = new ArrayList();
  ArrayList<an> j = new ArrayList();
  volatile boolean k;
  boolean l;
  cn m = new cn();
  
  private void b(dx paramdx)
  {
    try
    {
      this.a.c(paramdx.b);
      return;
    }
    finally
    {
      localObject = finally;
      throw localObject;
    }
  }
  
  private void b(dz paramdz)
  {
    try
    {
      this.a.b(paramdz.b);
      return;
    }
    finally
    {
      localObject = finally;
      throw localObject;
    }
  }
  
  private boolean g()
  {
    boolean bool = false;
    for (;;)
    {
      try
      {
        bq localbq = this.a.k;
        if (localbq.b <= 1)
        {
          n = 0;
          if (n != 0)
          {
            a.u.a = 3;
            return bool;
          }
        }
        else
        {
          a.c.g.b = true;
          dj localdj = localbq.k;
          int i1 = localdj.b;
          localdj.b = (i1 + 1);
          if (i1 == 0)
          {
            n = 0;
            continue;
          }
          if (localbq.k.b < localbq.b) {
            break label185;
          }
          localbq.k.b = 0;
          break label185;
        }
        c();
        ADCVideo.a();
        if (a.d)
        {
          aq.a.b("Launching AdColonyOverlay");
          a.a().startActivity(new Intent(a.a(), AdColonyOverlay.class));
        }
        else
        {
          aq.a.b("Launching AdColonyFullscreen");
          a.a().startActivity(new Intent(a.a(), AdColonyFullscreen.class));
        }
      }
      finally {}
      label185:
      int n = 1;
      continue;
      bool = true;
    }
  }
  
  final int a(String paramString)
  {
    try
    {
      int i1 = this.a.h.e(paramString);
      n = i1;
    }
    catch (RuntimeException localRuntimeException)
    {
      for (;;)
      {
        a.a(localRuntimeException);
        int n = 0;
      }
    }
    finally {}
    return n;
  }
  
  final void a()
  {
    this.k = true;
    new h(this, this);
  }
  
  final void a(double paramDouble)
  {
    new l(this, this, paramDouble);
  }
  
  final void a(an paraman)
  {
    synchronized (this.i)
    {
      if (!a.c()) {
        return;
      }
      this.i.add(paraman);
      if (!this.k) {
        f();
      }
      return;
    }
  }
  
  final void a(String paramString1, String paramString2)
  {
    new n(this, this, paramString1, paramString2);
  }
  
  final void a(String paramString1, String paramString2, String[] paramArrayOfString)
  {
    try
    {
      a.a(a.e);
      aq.c.a("==== Configuring AdColony ").a(this.a.b).b(" ====");
      aq.a.a("package name: ").b(cm.c());
      this.a.i = paramString2;
      this.a.j = paramArrayOfString;
      this.a.a(paramString1);
      this.m.a = System.currentTimeMillis();
      return;
    }
    catch (RuntimeException localRuntimeException)
    {
      for (;;)
      {
        a.a(localRuntimeException);
      }
    }
    finally {}
  }
  
  /* Error */
  final void a(boolean paramBoolean)
  {
    // Byte code:
    //   0: iconst_1
    //   1: istore_2
    //   2: aload_0
    //   3: monitorenter
    //   4: aload_0
    //   5: dconst_1
    //   6: invokevirtual 253	com/jirbo/adcolony/g:a	(D)V
    //   9: iload_1
    //   10: ifne +182 -> 192
    //   13: getstatic 117	com/jirbo/adcolony/a:u	Lcom/jirbo/adcolony/dn;
    //   16: invokevirtual 254	com/jirbo/adcolony/dn:c	()Z
    //   19: ifeq +173 -> 192
    //   22: getstatic 117	com/jirbo/adcolony/a:u	Lcom/jirbo/adcolony/dn;
    //   25: astore 4
    //   27: aload 4
    //   29: getfield 256	com/jirbo/adcolony/dn:c	Lcom/jirbo/adcolony/bq;
    //   32: invokevirtual 258	com/jirbo/adcolony/bq:b	()V
    //   35: aload_0
    //   36: getfield 75	com/jirbo/adcolony/g:h	Lcom/jirbo/adcolony/ca;
    //   39: aload 4
    //   41: getfield 259	com/jirbo/adcolony/dn:b	Ljava/lang/String;
    //   44: aload 4
    //   46: getfield 262	com/jirbo/adcolony/dn:d	Lcom/jirbo/adcolony/au;
    //   49: getfield 266	com/jirbo/adcolony/au:d	I
    //   52: invokevirtual 269	com/jirbo/adcolony/ca:a	(Ljava/lang/String;I)V
    //   55: getstatic 117	com/jirbo/adcolony/a:u	Lcom/jirbo/adcolony/dn;
    //   58: checkcast 90	com/jirbo/adcolony/dx
    //   61: astore 5
    //   63: aload 5
    //   65: invokevirtual 271	com/jirbo/adcolony/dx:e	()Ljava/lang/String;
    //   68: astore 6
    //   70: aload 5
    //   72: invokevirtual 274	com/jirbo/adcolony/dx:f	()I
    //   75: istore 7
    //   77: aload 5
    //   79: invokevirtual 276	com/jirbo/adcolony/dx:g	()I
    //   82: istore 8
    //   84: iload 8
    //   86: iload_2
    //   87: if_icmple +64 -> 151
    //   90: iconst_1
    //   91: aload_0
    //   92: getfield 75	com/jirbo/adcolony/g:h	Lcom/jirbo/adcolony/ca;
    //   95: aload 5
    //   97: invokevirtual 271	com/jirbo/adcolony/dx:e	()Ljava/lang/String;
    //   100: invokevirtual 278	com/jirbo/adcolony/ca:b	(Ljava/lang/String;)I
    //   103: iadd
    //   104: istore 9
    //   106: iconst_0
    //   107: istore 10
    //   109: iload 9
    //   111: iload 8
    //   113: if_icmplt +82 -> 195
    //   116: aload_0
    //   117: getfield 75	com/jirbo/adcolony/g:h	Lcom/jirbo/adcolony/ca;
    //   120: astore 11
    //   122: aload 5
    //   124: invokevirtual 271	com/jirbo/adcolony/dx:e	()Ljava/lang/String;
    //   127: astore 12
    //   129: aload 11
    //   131: getfield 281	com/jirbo/adcolony/ca:d	Ljava/util/HashMap;
    //   134: aload 12
    //   136: iload 10
    //   138: invokestatic 287	java/lang/Integer:valueOf	(I)Ljava/lang/Integer;
    //   141: invokevirtual 293	java/util/HashMap:put	(Ljava/lang/Object;Ljava/lang/Object;)Ljava/lang/Object;
    //   144: pop
    //   145: aload 11
    //   147: iconst_1
    //   148: putfield 295	com/jirbo/adcolony/ca:e	Z
    //   151: iload_2
    //   152: ifeq +40 -> 192
    //   155: aload 5
    //   157: getfield 296	com/jirbo/adcolony/dx:c	Lcom/jirbo/adcolony/bq;
    //   160: getfield 299	com/jirbo/adcolony/bq:j	Lcom/jirbo/adcolony/bs;
    //   163: getfield 302	com/jirbo/adcolony/bs:e	Z
    //   166: ifeq +12 -> 178
    //   169: aload_0
    //   170: iconst_1
    //   171: aload 6
    //   173: iload 7
    //   175: invokevirtual 305	com/jirbo/adcolony/g:a	(ZLjava/lang/String;I)V
    //   178: new 307	com/jirbo/adcolony/m
    //   181: dup
    //   182: aload_0
    //   183: aload_0
    //   184: aload 6
    //   186: iload 7
    //   188: invokespecial 310	com/jirbo/adcolony/m:<init>	(Lcom/jirbo/adcolony/g;Lcom/jirbo/adcolony/g;Ljava/lang/String;I)V
    //   191: pop
    //   192: aload_0
    //   193: monitorexit
    //   194: return
    //   195: iload 9
    //   197: istore 10
    //   199: iconst_0
    //   200: istore_2
    //   201: goto -85 -> 116
    //   204: astore_3
    //   205: aload_0
    //   206: monitorexit
    //   207: aload_3
    //   208: athrow
    // Local variable table:
    //   start	length	slot	name	signature
    //   0	209	0	this	g
    //   0	209	1	paramBoolean	boolean
    //   1	200	2	n	int
    //   204	4	3	localObject	Object
    //   25	20	4	localdn	dn
    //   61	95	5	localdx	dx
    //   68	117	6	str1	String
    //   75	112	7	i1	int
    //   82	32	8	i2	int
    //   104	92	9	i3	int
    //   107	91	10	i4	int
    //   120	26	11	localca	ca
    //   127	8	12	str2	String
    // Exception table:
    //   from	to	target	type
    //   4	9	204	finally
    //   13	84	204	finally
    //   90	106	204	finally
    //   116	151	204	finally
    //   155	178	204	finally
    //   178	192	204	finally
  }
  
  final void a(boolean paramBoolean, String paramString, int paramInt)
  {
    try
    {
      a.y.a(paramBoolean, paramString, paramInt);
      return;
    }
    finally
    {
      localObject = finally;
      throw localObject;
    }
  }
  
  final boolean a(dx paramdx)
  {
    for (;;)
    {
      try
      {
        a.u = paramdx;
        str = paramdx.b;
        boolean bool2 = f(str);
        bool1 = false;
        if (bool2) {
          continue;
        }
      }
      catch (RuntimeException localRuntimeException)
      {
        String str;
        boolean bool3;
        a.a(localRuntimeException);
        boolean bool1 = false;
        continue;
      }
      finally {}
      return bool1;
      aq.a.a("Showing v4vc for zone ").b(str);
      b(paramdx);
      bool3 = g();
      bool1 = bool3;
    }
  }
  
  public final boolean a(dz paramdz)
  {
    for (;;)
    {
      try
      {
        a.u = paramdz;
        str = paramdz.b;
        boolean bool2 = e(str);
        bool1 = false;
        if (bool2) {
          continue;
        }
      }
      catch (RuntimeException localRuntimeException)
      {
        String str;
        boolean bool3;
        a.a(localRuntimeException);
        boolean bool1 = false;
        continue;
      }
      finally {}
      return bool1;
      aq.a.a("Showing ad for zone ").b(str);
      b(paramdz);
      bool3 = g();
      bool1 = bool3;
    }
  }
  
  final boolean a(String paramString, boolean paramBoolean1, boolean paramBoolean2)
  {
    for (;;)
    {
      try
      {
        boolean bool2 = a.c();
        bool1 = false;
        if (bool2) {
          continue;
        }
      }
      catch (RuntimeException localRuntimeException)
      {
        boolean bool3;
        boolean bool4;
        a.a(localRuntimeException);
        boolean bool1 = false;
        continue;
      }
      finally {}
      return bool1;
      bool3 = this.b.a(paramString, paramBoolean1);
      bool1 = false;
      if (bool3)
      {
        bool4 = this.b.j.n.a(paramString).a(paramBoolean2);
        bool1 = bool4;
      }
    }
  }
  
  final void b()
  {
    this.k = false;
    new i(this, this);
  }
  
  final boolean b(String paramString)
  {
    try
    {
      boolean bool2 = this.a.h.a(paramString, false);
      bool1 = bool2;
    }
    catch (RuntimeException localRuntimeException)
    {
      for (;;)
      {
        a.a(localRuntimeException);
        boolean bool1 = false;
      }
    }
    finally {}
    return bool1;
  }
  
  final boolean b(String paramString, boolean paramBoolean1, boolean paramBoolean2)
  {
    for (;;)
    {
      try
      {
        boolean bool2 = a.c();
        bool1 = false;
        if (bool2) {
          continue;
        }
      }
      catch (RuntimeException localRuntimeException)
      {
        boolean bool3;
        boolean bool4;
        a.a(localRuntimeException);
        boolean bool1 = false;
        continue;
      }
      finally {}
      return bool1;
      bool3 = this.b.a(paramString, paramBoolean1);
      bool1 = false;
      if (bool3)
      {
        bool4 = this.b.j.n.a(paramString).b(paramBoolean2);
        bool1 = bool4;
      }
    }
  }
  
  final String c(String paramString)
  {
    try
    {
      String str2 = this.a.h.a(paramString, "");
      str1 = str2;
    }
    catch (RuntimeException localRuntimeException)
    {
      for (;;)
      {
        a.a(localRuntimeException);
        String str1 = null;
      }
    }
    finally {}
    return str1;
  }
  
  final void c()
  {
    try
    {
      this.a.m = 0.0D;
      aq.a.b("Tracking ad event - start");
      dn localdn = a.u;
      dj localdj = localdn.c.k;
      localdj.d = (1 + localdj.d);
      if (!a.u.c())
      {
        localdn.c.b();
        this.h.a(localdn.b, localdn.d.d);
      }
      new k(this, this, localdn);
      return;
    }
    finally {}
  }
  
  final int d(String paramString)
  {
    try
    {
      int n = this.h.b(paramString);
      return n;
    }
    finally
    {
      localObject = finally;
      throw localObject;
    }
  }
  
  /* Error */
  final String d()
  {
    // Byte code:
    //   0: aload_0
    //   1: monitorenter
    //   2: aload_0
    //   3: getfield 45	com/jirbo/adcolony/g:b	Lcom/jirbo/adcolony/d;
    //   6: astore_2
    //   7: aload_2
    //   8: getfield 379	com/jirbo/adcolony/d:b	Z
    //   11: istore_3
    //   12: aconst_null
    //   13: astore 4
    //   15: iconst_0
    //   16: istore 5
    //   18: iload_3
    //   19: ifne +11 -> 30
    //   22: aload_0
    //   23: monitorexit
    //   24: aload 4
    //   26: areturn
    //   27: iinc 5 1
    //   30: iload 5
    //   32: aload_2
    //   33: getfield 341	com/jirbo/adcolony/d:j	Lcom/jirbo/adcolony/ay;
    //   36: getfield 347	com/jirbo/adcolony/ay:n	Lcom/jirbo/adcolony/bt;
    //   39: getfield 381	com/jirbo/adcolony/bt:a	Ljava/util/ArrayList;
    //   42: invokevirtual 384	java/util/ArrayList:size	()I
    //   45: if_icmpge -23 -> 22
    //   48: aload_2
    //   49: getfield 341	com/jirbo/adcolony/d:j	Lcom/jirbo/adcolony/ay;
    //   52: getfield 347	com/jirbo/adcolony/ay:n	Lcom/jirbo/adcolony/bt;
    //   55: iload 5
    //   57: invokevirtual 387	com/jirbo/adcolony/bt:a	(I)Lcom/jirbo/adcolony/bq;
    //   60: astore 6
    //   62: aload 6
    //   64: iconst_1
    //   65: invokevirtual 355	com/jirbo/adcolony/bq:a	(Z)Z
    //   68: ifeq -41 -> 27
    //   71: aload 6
    //   73: getfield 389	com/jirbo/adcolony/bq:a	Ljava/lang/String;
    //   76: astore 4
    //   78: aload 6
    //   80: iconst_0
    //   81: iconst_1
    //   82: invokevirtual 392	com/jirbo/adcolony/bq:a	(ZZ)Z
    //   85: ifeq -58 -> 27
    //   88: aload 6
    //   90: getfield 389	com/jirbo/adcolony/bq:a	Ljava/lang/String;
    //   93: astore 4
    //   95: goto -73 -> 22
    //   98: astore_1
    //   99: aload_0
    //   100: monitorexit
    //   101: aload_1
    //   102: athrow
    // Local variable table:
    //   start	length	slot	name	signature
    //   0	103	0	this	g
    //   98	4	1	localObject	Object
    //   6	43	2	locald	d
    //   11	8	3	bool	boolean
    //   13	81	4	str	String
    //   16	40	5	n	int
    //   60	29	6	localbq	bq
    // Exception table:
    //   from	to	target	type
    //   2	12	98	finally
    //   30	95	98	finally
  }
  
  /* Error */
  final String e()
  {
    // Byte code:
    //   0: aload_0
    //   1: monitorenter
    //   2: aload_0
    //   3: getfield 45	com/jirbo/adcolony/g:b	Lcom/jirbo/adcolony/d;
    //   6: astore_2
    //   7: aload_2
    //   8: getfield 379	com/jirbo/adcolony/d:b	Z
    //   11: istore_3
    //   12: aconst_null
    //   13: astore 4
    //   15: iconst_0
    //   16: istore 5
    //   18: iload_3
    //   19: ifne +11 -> 30
    //   22: aload_0
    //   23: monitorexit
    //   24: aload 4
    //   26: areturn
    //   27: iinc 5 1
    //   30: iload 5
    //   32: aload_2
    //   33: getfield 341	com/jirbo/adcolony/d:j	Lcom/jirbo/adcolony/ay;
    //   36: getfield 347	com/jirbo/adcolony/ay:n	Lcom/jirbo/adcolony/bt;
    //   39: getfield 381	com/jirbo/adcolony/bt:a	Ljava/util/ArrayList;
    //   42: invokevirtual 384	java/util/ArrayList:size	()I
    //   45: if_icmpge -23 -> 22
    //   48: aload_2
    //   49: getfield 341	com/jirbo/adcolony/d:j	Lcom/jirbo/adcolony/ay;
    //   52: getfield 347	com/jirbo/adcolony/ay:n	Lcom/jirbo/adcolony/bt;
    //   55: iload 5
    //   57: invokevirtual 387	com/jirbo/adcolony/bt:a	(I)Lcom/jirbo/adcolony/bq;
    //   60: astore 6
    //   62: aload 6
    //   64: iconst_1
    //   65: invokevirtual 361	com/jirbo/adcolony/bq:b	(Z)Z
    //   68: ifeq -41 -> 27
    //   71: aload 6
    //   73: getfield 389	com/jirbo/adcolony/bq:a	Ljava/lang/String;
    //   76: astore 4
    //   78: aload 6
    //   80: iconst_0
    //   81: iconst_1
    //   82: invokevirtual 392	com/jirbo/adcolony/bq:a	(ZZ)Z
    //   85: ifeq -58 -> 27
    //   88: aload 6
    //   90: getfield 389	com/jirbo/adcolony/bq:a	Ljava/lang/String;
    //   93: astore 4
    //   95: goto -73 -> 22
    //   98: astore_1
    //   99: aload_0
    //   100: monitorexit
    //   101: aload_1
    //   102: athrow
    // Local variable table:
    //   start	length	slot	name	signature
    //   0	103	0	this	g
    //   98	4	1	localObject	Object
    //   6	43	2	locald	d
    //   11	8	3	bool	boolean
    //   13	81	4	str	String
    //   16	40	5	n	int
    //   60	29	6	localbq	bq
    // Exception table:
    //   from	to	target	type
    //   2	12	98	finally
    //   30	95	98	finally
  }
  
  final boolean e(String paramString)
  {
    try
    {
      boolean bool = a(paramString, false, true);
      return bool;
    }
    finally
    {
      localObject = finally;
      throw localObject;
    }
  }
  
  /* Error */
  final void f()
  {
    // Byte code:
    //   0: iconst_1
    //   1: istore_1
    //   2: aload_0
    //   3: monitorenter
    //   4: invokestatic 396	com/jirbo/adcolony/a:b	()Z
    //   7: istore_3
    //   8: iload_3
    //   9: ifeq +6 -> 15
    //   12: aload_0
    //   13: monitorexit
    //   14: return
    //   15: aload_0
    //   16: getfield 398	com/jirbo/adcolony/g:l	Z
    //   19: ifne +142 -> 161
    //   22: invokestatic 199	com/jirbo/adcolony/a:c	()Z
    //   25: istore 38
    //   27: iload 38
    //   29: ifeq +132 -> 161
    //   32: aload_0
    //   33: getfield 398	com/jirbo/adcolony/g:l	Z
    //   36: ifeq +20 -> 56
    //   39: aload_0
    //   40: getfield 185	com/jirbo/adcolony/g:k	Z
    //   43: ifne +513 -> 556
    //   46: aload_0
    //   47: getfield 80	com/jirbo/adcolony/g:i	Ljava/util/ArrayList;
    //   50: invokevirtual 384	java/util/ArrayList:size	()I
    //   53: ifle +503 -> 556
    //   56: aload_0
    //   57: iconst_1
    //   58: putfield 398	com/jirbo/adcolony/g:l	Z
    //   61: aload_0
    //   62: getfield 82	com/jirbo/adcolony/g:j	Ljava/util/ArrayList;
    //   65: aload_0
    //   66: getfield 80	com/jirbo/adcolony/g:i	Ljava/util/ArrayList;
    //   69: invokevirtual 402	java/util/ArrayList:addAll	(Ljava/util/Collection;)Z
    //   72: pop
    //   73: aload_0
    //   74: getfield 80	com/jirbo/adcolony/g:i	Ljava/util/ArrayList;
    //   77: invokevirtual 405	java/util/ArrayList:clear	()V
    //   80: iconst_0
    //   81: istore 41
    //   83: iload 41
    //   85: aload_0
    //   86: getfield 82	com/jirbo/adcolony/g:j	Ljava/util/ArrayList;
    //   89: invokevirtual 384	java/util/ArrayList:size	()I
    //   92: if_icmpge +33 -> 125
    //   95: aload_0
    //   96: getfield 82	com/jirbo/adcolony/g:j	Ljava/util/ArrayList;
    //   99: iload 41
    //   101: invokevirtual 409	java/util/ArrayList:get	(I)Ljava/lang/Object;
    //   104: ifnull +1114 -> 1218
    //   107: aload_0
    //   108: getfield 82	com/jirbo/adcolony/g:j	Ljava/util/ArrayList;
    //   111: iload 41
    //   113: invokevirtual 409	java/util/ArrayList:get	(I)Ljava/lang/Object;
    //   116: checkcast 411	com/jirbo/adcolony/an
    //   119: invokevirtual 412	com/jirbo/adcolony/an:a	()V
    //   122: goto +1096 -> 1218
    //   125: aload_0
    //   126: getfield 82	com/jirbo/adcolony/g:j	Ljava/util/ArrayList;
    //   129: invokevirtual 405	java/util/ArrayList:clear	()V
    //   132: goto -100 -> 32
    //   135: astore 39
    //   137: aload_0
    //   138: iconst_0
    //   139: putfield 398	com/jirbo/adcolony/g:l	Z
    //   142: aload_0
    //   143: getfield 82	com/jirbo/adcolony/g:j	Ljava/util/ArrayList;
    //   146: invokevirtual 405	java/util/ArrayList:clear	()V
    //   149: aload_0
    //   150: getfield 80	com/jirbo/adcolony/g:i	Ljava/util/ArrayList;
    //   153: invokevirtual 405	java/util/ArrayList:clear	()V
    //   156: aload 39
    //   158: invokestatic 183	com/jirbo/adcolony/a:a	(Ljava/lang/RuntimeException;)V
    //   161: getstatic 414	com/jirbo/adcolony/a:g	Z
    //   164: ifne +18 -> 182
    //   167: aload_0
    //   168: getfield 40	com/jirbo/adcolony/g:a	Lcom/jirbo/adcolony/f;
    //   171: invokevirtual 415	com/jirbo/adcolony/f:a	()V
    //   174: iconst_1
    //   175: putstatic 414	com/jirbo/adcolony/a:g	Z
    //   178: iconst_1
    //   179: putstatic 417	com/jirbo/adcolony/a:i	Z
    //   182: aload_0
    //   183: getfield 45	com/jirbo/adcolony/g:b	Lcom/jirbo/adcolony/d;
    //   186: astore 5
    //   188: invokestatic 420	com/jirbo/adcolony/cm:b	()D
    //   191: aload 5
    //   193: getfield 422	com/jirbo/adcolony/d:g	D
    //   196: dcmpl
    //   197: iflt +9 -> 206
    //   200: aload 5
    //   202: iconst_1
    //   203: putfield 424	com/jirbo/adcolony/d:c	Z
    //   206: aload 5
    //   208: getfield 424	com/jirbo/adcolony/d:c	Z
    //   211: ifeq +171 -> 382
    //   214: aload 5
    //   216: iconst_0
    //   217: putfield 424	com/jirbo/adcolony/d:c	Z
    //   220: invokestatic 428	com/jirbo/adcolony/ah:a	()I
    //   223: bipush 32
    //   225: if_icmplt +157 -> 382
    //   228: aload 5
    //   230: ldc2_w 429
    //   233: invokestatic 420	com/jirbo/adcolony/cm:b	()D
    //   236: dadd
    //   237: putfield 422	com/jirbo/adcolony/d:g	D
    //   240: iconst_1
    //   241: putstatic 417	com/jirbo/adcolony/a:i	Z
    //   244: getstatic 432	com/jirbo/adcolony/aq:b	Lcom/jirbo/adcolony/aq;
    //   247: ldc_w 434
    //   250: invokevirtual 150	com/jirbo/adcolony/aq:b	(Ljava/lang/Object;)Lcom/jirbo/adcolony/aq;
    //   253: pop
    //   254: invokestatic 437	com/jirbo/adcolony/by:c	()Z
    //   257: ifne +346 -> 603
    //   260: getstatic 432	com/jirbo/adcolony/aq:b	Lcom/jirbo/adcolony/aq;
    //   263: ldc_w 439
    //   266: invokevirtual 150	com/jirbo/adcolony/aq:b	(Ljava/lang/Object;)Lcom/jirbo/adcolony/aq;
    //   269: pop
    //   270: getstatic 145	com/jirbo/adcolony/aq:a	Lcom/jirbo/adcolony/aq;
    //   273: ldc_w 441
    //   276: invokevirtual 224	com/jirbo/adcolony/aq:a	(Ljava/lang/String;)Lcom/jirbo/adcolony/aq;
    //   279: aload 5
    //   281: getfield 442	com/jirbo/adcolony/d:d	Z
    //   284: invokevirtual 445	com/jirbo/adcolony/aq:a	(Z)Lcom/jirbo/adcolony/aq;
    //   287: ldc_w 447
    //   290: invokevirtual 224	com/jirbo/adcolony/aq:a	(Ljava/lang/String;)Lcom/jirbo/adcolony/aq;
    //   293: aload 5
    //   295: getfield 379	com/jirbo/adcolony/d:b	Z
    //   298: invokevirtual 449	com/jirbo/adcolony/aq:b	(Z)Lcom/jirbo/adcolony/aq;
    //   301: pop
    //   302: aload 5
    //   304: getfield 442	com/jirbo/adcolony/d:d	Z
    //   307: ifne +75 -> 382
    //   310: aload 5
    //   312: iconst_1
    //   313: putfield 442	com/jirbo/adcolony/d:d	Z
    //   316: aload 5
    //   318: getfield 379	com/jirbo/adcolony/d:b	Z
    //   321: ifne +61 -> 382
    //   324: getstatic 432	com/jirbo/adcolony/aq:b	Lcom/jirbo/adcolony/aq;
    //   327: ldc_w 451
    //   330: invokevirtual 150	com/jirbo/adcolony/aq:b	(Ljava/lang/Object;)Lcom/jirbo/adcolony/aq;
    //   333: pop
    //   334: new 453	com/jirbo/adcolony/ag
    //   337: dup
    //   338: ldc_w 455
    //   341: invokespecial 457	com/jirbo/adcolony/ag:<init>	(Ljava/lang/String;)V
    //   344: astore 35
    //   346: aload 35
    //   348: invokestatic 462	com/jirbo/adcolony/ap:a	(Lcom/jirbo/adcolony/ag;)Lcom/jirbo/adcolony/ad;
    //   351: astore 36
    //   353: aload 36
    //   355: ifnull +27 -> 382
    //   358: aload 5
    //   360: aload 36
    //   362: invokevirtual 465	com/jirbo/adcolony/d:a	(Lcom/jirbo/adcolony/ad;)Z
    //   365: ifeq +204 -> 569
    //   368: aload 5
    //   370: iconst_1
    //   371: putfield 379	com/jirbo/adcolony/d:b	Z
    //   374: aload 5
    //   376: getfield 341	com/jirbo/adcolony/d:j	Lcom/jirbo/adcolony/ay;
    //   379: invokevirtual 466	com/jirbo/adcolony/ay:a	()V
    //   382: invokestatic 437	com/jirbo/adcolony/by:c	()Z
    //   385: ifne +519 -> 904
    //   388: getstatic 469	com/jirbo/adcolony/a:r	Z
    //   391: ifeq +6 -> 397
    //   394: invokestatic 471	com/jirbo/adcolony/a:j	()V
    //   397: iconst_0
    //   398: putstatic 469	com/jirbo/adcolony/a:r	Z
    //   401: aload_0
    //   402: getfield 50	com/jirbo/adcolony/g:c	Lcom/jirbo/adcolony/bu;
    //   405: astore 6
    //   407: aload 6
    //   409: invokevirtual 472	com/jirbo/adcolony/bu:c	()V
    //   412: aload 6
    //   414: getfield 473	com/jirbo/adcolony/bu:i	Z
    //   417: ifeq +639 -> 1056
    //   420: aload 6
    //   422: getfield 476	com/jirbo/adcolony/bu:e	Lcom/jirbo/adcolony/co;
    //   425: invokevirtual 480	com/jirbo/adcolony/co:a	()Z
    //   428: ifeq +628 -> 1056
    //   431: aload 6
    //   433: getfield 482	com/jirbo/adcolony/bu:a	Lcom/jirbo/adcolony/g;
    //   436: getfield 45	com/jirbo/adcolony/g:b	Lcom/jirbo/adcolony/d;
    //   439: getfield 341	com/jirbo/adcolony/d:j	Lcom/jirbo/adcolony/ay;
    //   442: getfield 483	com/jirbo/adcolony/ay:g	D
    //   445: dstore 11
    //   447: dload 11
    //   449: dconst_0
    //   450: dcmpl
    //   451: ifeq +600 -> 1051
    //   454: aload 6
    //   456: getfield 485	com/jirbo/adcolony/bu:j	D
    //   459: aload 6
    //   461: getfield 482	com/jirbo/adcolony/bu:a	Lcom/jirbo/adcolony/g;
    //   464: getfield 45	com/jirbo/adcolony/g:b	Lcom/jirbo/adcolony/d;
    //   467: getfield 341	com/jirbo/adcolony/d:j	Lcom/jirbo/adcolony/ay;
    //   470: getfield 483	com/jirbo/adcolony/ay:g	D
    //   473: dcmpl
    //   474: ifle +577 -> 1051
    //   477: iconst_0
    //   478: istore 13
    //   480: aconst_null
    //   481: astore 14
    //   483: iload 13
    //   485: aload 6
    //   487: getfield 487	com/jirbo/adcolony/bu:b	Ljava/util/ArrayList;
    //   490: invokevirtual 384	java/util/ArrayList:size	()I
    //   493: if_icmpge +427 -> 920
    //   496: aload 6
    //   498: getfield 487	com/jirbo/adcolony/bu:b	Ljava/util/ArrayList;
    //   501: iload 13
    //   503: invokevirtual 409	java/util/ArrayList:get	(I)Ljava/lang/Object;
    //   506: checkcast 489	com/jirbo/adcolony/bv
    //   509: astore 18
    //   511: aload 18
    //   513: getfield 490	com/jirbo/adcolony/bv:e	Z
    //   516: ifeq +695 -> 1211
    //   519: aload 14
    //   521: ifnull +25 -> 546
    //   524: aload 18
    //   526: getfield 492	com/jirbo/adcolony/bv:h	D
    //   529: dstore 19
    //   531: aload 14
    //   533: getfield 492	com/jirbo/adcolony/bv:h	D
    //   536: dstore 21
    //   538: dload 19
    //   540: dload 21
    //   542: dcmpg
    //   543: ifge +668 -> 1211
    //   546: iinc 13 1
    //   549: aload 18
    //   551: astore 14
    //   553: goto -70 -> 483
    //   556: aload_0
    //   557: iconst_0
    //   558: putfield 398	com/jirbo/adcolony/g:l	Z
    //   561: goto -400 -> 161
    //   564: astore_2
    //   565: aload_0
    //   566: monitorexit
    //   567: aload_2
    //   568: athrow
    //   569: getstatic 432	com/jirbo/adcolony/aq:b	Lcom/jirbo/adcolony/aq;
    //   572: ldc_w 494
    //   575: invokevirtual 150	com/jirbo/adcolony/aq:b	(Ljava/lang/Object;)Lcom/jirbo/adcolony/aq;
    //   578: pop
    //   579: aload 35
    //   581: invokevirtual 495	com/jirbo/adcolony/ag:c	()V
    //   584: aload 5
    //   586: iconst_0
    //   587: putfield 379	com/jirbo/adcolony/d:b	Z
    //   590: goto -208 -> 382
    //   593: astore 4
    //   595: aload 4
    //   597: invokestatic 183	com/jirbo/adcolony/a:a	(Ljava/lang/RuntimeException;)V
    //   600: goto -588 -> 12
    //   603: new 497	com/jirbo/adcolony/cj
    //   606: dup
    //   607: invokespecial 498	com/jirbo/adcolony/cj:<init>	()V
    //   610: astore 24
    //   612: aload 5
    //   614: getfield 499	com/jirbo/adcolony/d:a	Lcom/jirbo/adcolony/g;
    //   617: getfield 40	com/jirbo/adcolony/g:a	Lcom/jirbo/adcolony/f;
    //   620: pop
    //   621: aload 24
    //   623: getstatic 501	com/jirbo/adcolony/f:c	Ljava/lang/String;
    //   626: invokevirtual 502	com/jirbo/adcolony/cj:a	(Ljava/lang/String;)V
    //   629: aload 24
    //   631: ldc_w 504
    //   634: invokevirtual 502	com/jirbo/adcolony/cj:a	(Ljava/lang/String;)V
    //   637: aload 24
    //   639: aload 5
    //   641: getfield 499	com/jirbo/adcolony/d:a	Lcom/jirbo/adcolony/g;
    //   644: getfield 40	com/jirbo/adcolony/g:a	Lcom/jirbo/adcolony/f;
    //   647: getfield 236	com/jirbo/adcolony/f:i	Ljava/lang/String;
    //   650: invokevirtual 502	com/jirbo/adcolony/cj:a	(Ljava/lang/String;)V
    //   653: aload 24
    //   655: ldc_w 506
    //   658: invokevirtual 502	com/jirbo/adcolony/cj:a	(Ljava/lang/String;)V
    //   661: aload 5
    //   663: getfield 499	com/jirbo/adcolony/d:a	Lcom/jirbo/adcolony/g;
    //   666: getfield 40	com/jirbo/adcolony/g:a	Lcom/jirbo/adcolony/f;
    //   669: getfield 239	com/jirbo/adcolony/f:j	[Ljava/lang/String;
    //   672: ifnull +68 -> 740
    //   675: aload 5
    //   677: getfield 499	com/jirbo/adcolony/d:a	Lcom/jirbo/adcolony/g;
    //   680: getfield 40	com/jirbo/adcolony/g:a	Lcom/jirbo/adcolony/f;
    //   683: getfield 239	com/jirbo/adcolony/f:j	[Ljava/lang/String;
    //   686: astore 28
    //   688: aload 28
    //   690: arraylength
    //   691: istore 29
    //   693: iconst_0
    //   694: istore 30
    //   696: iload 30
    //   698: iload 29
    //   700: if_icmpge +40 -> 740
    //   703: aload 28
    //   705: iload 30
    //   707: aaload
    //   708: astore 31
    //   710: iload_1
    //   711: ifeq +18 -> 729
    //   714: iconst_0
    //   715: istore_1
    //   716: aload 24
    //   718: aload 31
    //   720: invokevirtual 502	com/jirbo/adcolony/cj:a	(Ljava/lang/String;)V
    //   723: iinc 30 1
    //   726: goto -30 -> 696
    //   729: aload 24
    //   731: ldc_w 508
    //   734: invokevirtual 502	com/jirbo/adcolony/cj:a	(Ljava/lang/String;)V
    //   737: goto -21 -> 716
    //   740: aload 24
    //   742: aload 5
    //   744: getfield 499	com/jirbo/adcolony/d:a	Lcom/jirbo/adcolony/g;
    //   747: getfield 40	com/jirbo/adcolony/g:a	Lcom/jirbo/adcolony/f;
    //   750: getfield 510	com/jirbo/adcolony/f:g	Ljava/lang/String;
    //   753: invokevirtual 502	com/jirbo/adcolony/cj:a	(Ljava/lang/String;)V
    //   756: aload 24
    //   758: ldc_w 512
    //   761: invokevirtual 502	com/jirbo/adcolony/cj:a	(Ljava/lang/String;)V
    //   764: aload 24
    //   766: aload 5
    //   768: getfield 499	com/jirbo/adcolony/d:a	Lcom/jirbo/adcolony/g;
    //   771: getfield 40	com/jirbo/adcolony/g:a	Lcom/jirbo/adcolony/f;
    //   774: getfield 515	com/jirbo/adcolony/f:v	Ljava/lang/String;
    //   777: invokestatic 517	com/jirbo/adcolony/by:a	(Ljava/lang/String;)Ljava/lang/String;
    //   780: invokevirtual 502	com/jirbo/adcolony/cj:a	(Ljava/lang/String;)V
    //   783: aload 24
    //   785: ldc_w 519
    //   788: invokevirtual 502	com/jirbo/adcolony/cj:a	(Ljava/lang/String;)V
    //   791: invokestatic 520	com/jirbo/adcolony/by:a	()Z
    //   794: ifeq +82 -> 876
    //   797: aload 24
    //   799: ldc_w 522
    //   802: invokevirtual 502	com/jirbo/adcolony/cj:a	(Ljava/lang/String;)V
    //   805: aload 24
    //   807: ldc_w 524
    //   810: invokevirtual 502	com/jirbo/adcolony/cj:a	(Ljava/lang/String;)V
    //   813: aload 24
    //   815: aload 5
    //   817: getfield 499	com/jirbo/adcolony/d:a	Lcom/jirbo/adcolony/g;
    //   820: getfield 40	com/jirbo/adcolony/g:a	Lcom/jirbo/adcolony/f;
    //   823: getfield 527	com/jirbo/adcolony/f:w	Ljava/lang/String;
    //   826: invokestatic 517	com/jirbo/adcolony/by:a	(Ljava/lang/String;)Ljava/lang/String;
    //   829: invokevirtual 502	com/jirbo/adcolony/cj:a	(Ljava/lang/String;)V
    //   832: getstatic 432	com/jirbo/adcolony/aq:b	Lcom/jirbo/adcolony/aq;
    //   835: ldc_w 529
    //   838: invokevirtual 150	com/jirbo/adcolony/aq:b	(Ljava/lang/Object;)Lcom/jirbo/adcolony/aq;
    //   841: pop
    //   842: getstatic 432	com/jirbo/adcolony/aq:b	Lcom/jirbo/adcolony/aq;
    //   845: aload 24
    //   847: invokevirtual 150	com/jirbo/adcolony/aq:b	(Ljava/lang/Object;)Lcom/jirbo/adcolony/aq;
    //   850: pop
    //   851: new 531	com/jirbo/adcolony/aj
    //   854: dup
    //   855: aload 5
    //   857: getfield 499	com/jirbo/adcolony/d:a	Lcom/jirbo/adcolony/g;
    //   860: aload 24
    //   862: invokevirtual 534	com/jirbo/adcolony/cj:toString	()Ljava/lang/String;
    //   865: aload 5
    //   867: invokespecial 537	com/jirbo/adcolony/aj:<init>	(Lcom/jirbo/adcolony/g;Ljava/lang/String;Lcom/jirbo/adcolony/am;)V
    //   870: invokevirtual 538	com/jirbo/adcolony/aj:b	()V
    //   873: goto -491 -> 382
    //   876: invokestatic 539	com/jirbo/adcolony/by:b	()Z
    //   879: ifeq +14 -> 893
    //   882: aload 24
    //   884: ldc_w 541
    //   887: invokevirtual 502	com/jirbo/adcolony/cj:a	(Ljava/lang/String;)V
    //   890: goto -85 -> 805
    //   893: aload 24
    //   895: ldc_w 543
    //   898: invokevirtual 502	com/jirbo/adcolony/cj:a	(Ljava/lang/String;)V
    //   901: goto -96 -> 805
    //   904: getstatic 469	com/jirbo/adcolony/a:r	Z
    //   907: ifne +6 -> 913
    //   910: invokestatic 471	com/jirbo/adcolony/a:j	()V
    //   913: iconst_1
    //   914: putstatic 469	com/jirbo/adcolony/a:r	Z
    //   917: goto -516 -> 401
    //   920: aload 14
    //   922: ifnull +129 -> 1051
    //   925: getstatic 432	com/jirbo/adcolony/aq:b	Lcom/jirbo/adcolony/aq;
    //   928: ldc_w 545
    //   931: invokevirtual 224	com/jirbo/adcolony/aq:a	(Ljava/lang/String;)Lcom/jirbo/adcolony/aq;
    //   934: aload 14
    //   936: getfield 546	com/jirbo/adcolony/bv:b	Ljava/lang/String;
    //   939: invokevirtual 150	com/jirbo/adcolony/aq:b	(Ljava/lang/Object;)Lcom/jirbo/adcolony/aq;
    //   942: pop
    //   943: aload 14
    //   945: iconst_0
    //   946: putfield 490	com/jirbo/adcolony/bv:e	Z
    //   949: new 548	java/io/File
    //   952: dup
    //   953: aload 14
    //   955: getfield 546	com/jirbo/adcolony/bv:b	Ljava/lang/String;
    //   958: invokespecial 549	java/io/File:<init>	(Ljava/lang/String;)V
    //   961: invokevirtual 552	java/io/File:delete	()Z
    //   964: pop
    //   965: aload 14
    //   967: aconst_null
    //   968: putfield 546	com/jirbo/adcolony/bv:b	Ljava/lang/String;
    //   971: aload 6
    //   973: aload 6
    //   975: getfield 485	com/jirbo/adcolony/bu:j	D
    //   978: aload 14
    //   980: getfield 554	com/jirbo/adcolony/bv:g	I
    //   983: i2d
    //   984: dsub
    //   985: putfield 485	com/jirbo/adcolony/bu:j	D
    //   988: getstatic 432	com/jirbo/adcolony/aq:b	Lcom/jirbo/adcolony/aq;
    //   991: ldc_w 556
    //   994: invokevirtual 224	com/jirbo/adcolony/aq:a	(Ljava/lang/String;)Lcom/jirbo/adcolony/aq;
    //   997: aload 6
    //   999: getfield 485	com/jirbo/adcolony/bu:j	D
    //   1002: ldc2_w 557
    //   1005: ddiv
    //   1006: invokevirtual 561	com/jirbo/adcolony/aq:a	(D)Lcom/jirbo/adcolony/aq;
    //   1009: ldc_w 563
    //   1012: invokevirtual 224	com/jirbo/adcolony/aq:a	(Ljava/lang/String;)Lcom/jirbo/adcolony/aq;
    //   1015: dload 11
    //   1017: ldc2_w 557
    //   1020: ddiv
    //   1021: invokevirtual 561	com/jirbo/adcolony/aq:a	(D)Lcom/jirbo/adcolony/aq;
    //   1024: ldc_w 565
    //   1027: invokevirtual 150	com/jirbo/adcolony/aq:b	(Ljava/lang/Object;)Lcom/jirbo/adcolony/aq;
    //   1030: pop
    //   1031: aload 6
    //   1033: iconst_1
    //   1034: putfield 473	com/jirbo/adcolony/bu:i	Z
    //   1037: aload 6
    //   1039: getfield 476	com/jirbo/adcolony/bu:e	Lcom/jirbo/adcolony/co;
    //   1042: ldc2_w 566
    //   1045: invokevirtual 568	com/jirbo/adcolony/co:a	(D)V
    //   1048: goto -594 -> 454
    //   1051: aload 6
    //   1053: invokevirtual 569	com/jirbo/adcolony/bu:b	()V
    //   1056: aload_0
    //   1057: getfield 60	com/jirbo/adcolony/g:e	Lcom/jirbo/adcolony/ce;
    //   1060: astore 7
    //   1062: aload 7
    //   1064: getfield 570	com/jirbo/adcolony/ce:a	Lcom/jirbo/adcolony/g;
    //   1067: getfield 45	com/jirbo/adcolony/g:b	Lcom/jirbo/adcolony/d;
    //   1070: getfield 379	com/jirbo/adcolony/d:b	Z
    //   1073: ifeq +61 -> 1134
    //   1076: aload 7
    //   1078: getfield 571	com/jirbo/adcolony/ce:d	Z
    //   1081: ifeq +24 -> 1105
    //   1084: aload 7
    //   1086: iconst_0
    //   1087: putfield 571	com/jirbo/adcolony/ce:d	Z
    //   1090: aload 7
    //   1092: getfield 570	com/jirbo/adcolony/ce:a	Lcom/jirbo/adcolony/g;
    //   1095: getfield 55	com/jirbo/adcolony/g:d	Lcom/jirbo/adcolony/cc;
    //   1098: ldc_w 573
    //   1101: aconst_null
    //   1102: invokevirtual 576	com/jirbo/adcolony/cc:a	(Ljava/lang/String;Lcom/jirbo/adcolony/ad;)V
    //   1105: aload 7
    //   1107: getfield 577	com/jirbo/adcolony/ce:e	Z
    //   1110: ifeq +24 -> 1134
    //   1113: aload 7
    //   1115: iconst_0
    //   1116: putfield 577	com/jirbo/adcolony/ce:e	Z
    //   1119: aload 7
    //   1121: getfield 570	com/jirbo/adcolony/ce:a	Lcom/jirbo/adcolony/g;
    //   1124: getfield 55	com/jirbo/adcolony/g:d	Lcom/jirbo/adcolony/cc;
    //   1127: ldc_w 579
    //   1130: aconst_null
    //   1131: invokevirtual 576	com/jirbo/adcolony/cc:a	(Ljava/lang/String;Lcom/jirbo/adcolony/ad;)V
    //   1134: aload_0
    //   1135: getfield 55	com/jirbo/adcolony/g:d	Lcom/jirbo/adcolony/cc;
    //   1138: astore 8
    //   1140: aload 8
    //   1142: getfield 580	com/jirbo/adcolony/cc:e	Z
    //   1145: ifeq +14 -> 1159
    //   1148: aload 8
    //   1150: iconst_0
    //   1151: putfield 580	com/jirbo/adcolony/cc:e	Z
    //   1154: aload 8
    //   1156: invokevirtual 581	com/jirbo/adcolony/cc:b	()V
    //   1159: aload 8
    //   1161: invokevirtual 582	com/jirbo/adcolony/cc:c	()V
    //   1164: aload_0
    //   1165: getfield 75	com/jirbo/adcolony/g:h	Lcom/jirbo/adcolony/ca;
    //   1168: astore 9
    //   1170: aload 9
    //   1172: getfield 295	com/jirbo/adcolony/ca:e	Z
    //   1175: ifeq +14 -> 1189
    //   1178: aload 9
    //   1180: iconst_0
    //   1181: putfield 295	com/jirbo/adcolony/ca:e	Z
    //   1184: aload 9
    //   1186: invokevirtual 583	com/jirbo/adcolony/ca:b	()V
    //   1189: aload_0
    //   1190: getfield 70	com/jirbo/adcolony/g:g	Lcom/jirbo/adcolony/dk;
    //   1193: astore 10
    //   1195: aload 10
    //   1197: getfield 126	com/jirbo/adcolony/dk:b	Z
    //   1200: ifeq -1188 -> 12
    //   1203: aload 10
    //   1205: invokevirtual 584	com/jirbo/adcolony/dk:a	()V
    //   1208: goto -1196 -> 12
    //   1211: aload 14
    //   1213: astore 18
    //   1215: goto -669 -> 546
    //   1218: iinc 41 1
    //   1221: goto -1138 -> 83
    // Local variable table:
    //   start	length	slot	name	signature
    //   0	1224	0	this	g
    //   1	715	1	n	int
    //   564	4	2	localObject1	Object
    //   7	2	3	bool1	boolean
    //   593	3	4	localRuntimeException1	RuntimeException
    //   186	680	5	locald	d
    //   405	647	6	localbu	bu
    //   1060	60	7	localce	ce
    //   1138	22	8	localcc	cc
    //   1168	17	9	localca	ca
    //   1193	11	10	localdk	dk
    //   445	571	11	d1	double
    //   478	69	13	i1	int
    //   481	731	14	localObject2	Object
    //   509	705	18	localObject3	Object
    //   529	10	19	d2	double
    //   536	5	21	d3	double
    //   610	284	24	localcj	cj
    //   686	18	28	arrayOfString	String[]
    //   691	10	29	i2	int
    //   694	30	30	i3	int
    //   708	11	31	str	String
    //   344	236	35	localag	ag
    //   351	10	36	localad	ad
    //   25	3	38	bool2	boolean
    //   135	22	39	localRuntimeException2	RuntimeException
    //   81	1138	41	i4	int
    // Exception table:
    //   from	to	target	type
    //   32	56	135	java/lang/RuntimeException
    //   56	80	135	java/lang/RuntimeException
    //   83	122	135	java/lang/RuntimeException
    //   125	132	135	java/lang/RuntimeException
    //   556	561	135	java/lang/RuntimeException
    //   4	8	564	finally
    //   15	27	564	finally
    //   32	56	564	finally
    //   56	80	564	finally
    //   83	122	564	finally
    //   125	132	564	finally
    //   137	161	564	finally
    //   161	182	564	finally
    //   182	206	564	finally
    //   206	353	564	finally
    //   358	382	564	finally
    //   382	397	564	finally
    //   397	401	564	finally
    //   401	447	564	finally
    //   454	477	564	finally
    //   483	519	564	finally
    //   524	538	564	finally
    //   556	561	564	finally
    //   569	590	564	finally
    //   595	600	564	finally
    //   603	693	564	finally
    //   703	710	564	finally
    //   716	723	564	finally
    //   729	737	564	finally
    //   740	805	564	finally
    //   805	873	564	finally
    //   876	890	564	finally
    //   893	901	564	finally
    //   904	913	564	finally
    //   913	917	564	finally
    //   925	1048	564	finally
    //   1051	1056	564	finally
    //   1056	1105	564	finally
    //   1105	1134	564	finally
    //   1134	1159	564	finally
    //   1159	1189	564	finally
    //   1189	1208	564	finally
    //   15	27	593	java/lang/RuntimeException
    //   137	161	593	java/lang/RuntimeException
    //   161	182	593	java/lang/RuntimeException
    //   182	206	593	java/lang/RuntimeException
    //   206	353	593	java/lang/RuntimeException
    //   358	382	593	java/lang/RuntimeException
    //   382	397	593	java/lang/RuntimeException
    //   397	401	593	java/lang/RuntimeException
    //   401	447	593	java/lang/RuntimeException
    //   454	477	593	java/lang/RuntimeException
    //   483	519	593	java/lang/RuntimeException
    //   524	538	593	java/lang/RuntimeException
    //   569	590	593	java/lang/RuntimeException
    //   603	693	593	java/lang/RuntimeException
    //   703	710	593	java/lang/RuntimeException
    //   716	723	593	java/lang/RuntimeException
    //   729	737	593	java/lang/RuntimeException
    //   740	805	593	java/lang/RuntimeException
    //   805	873	593	java/lang/RuntimeException
    //   876	890	593	java/lang/RuntimeException
    //   893	901	593	java/lang/RuntimeException
    //   904	913	593	java/lang/RuntimeException
    //   913	917	593	java/lang/RuntimeException
    //   925	1048	593	java/lang/RuntimeException
    //   1051	1056	593	java/lang/RuntimeException
    //   1056	1105	593	java/lang/RuntimeException
    //   1105	1134	593	java/lang/RuntimeException
    //   1134	1159	593	java/lang/RuntimeException
    //   1159	1189	593	java/lang/RuntimeException
    //   1189	1208	593	java/lang/RuntimeException
  }
  
  final boolean f(String paramString)
  {
    try
    {
      boolean bool = b(paramString, false, true);
      return bool;
    }
    finally
    {
      localObject = finally;
      throw localObject;
    }
  }
  
  final bq g(String paramString)
  {
    try
    {
      bq localbq = this.b.j.n.a(paramString);
      return localbq;
    }
    finally
    {
      localObject = finally;
      throw localObject;
    }
  }
}


/* Location:           C:\Users\vishnu\Desktop\New folder (3)\classes_dex2jar.jar
 * Qualified Name:     com.jirbo.adcolony.g
 * JD-Core Version:    0.7.0.1
 */