package com.google.android.gms.internal;

import android.os.IBinder;
import android.os.Parcel;
import com.google.android.gms.common.data.d;

final class dp
  implements dn
{
  private IBinder a;
  
  dp(IBinder paramIBinder)
  {
    this.a = paramIBinder;
  }
  
  public final void a()
  {
    Parcel localParcel1 = Parcel.obtain();
    Parcel localParcel2 = Parcel.obtain();
    try
    {
      localParcel1.writeInterfaceToken("com.google.android.gms.games.internal.IGamesCallbacks");
      this.a.transact(5016, localParcel1, localParcel2, 0);
      localParcel2.readException();
      return;
    }
    finally
    {
      localParcel2.recycle();
      localParcel1.recycle();
    }
  }
  
  public final void a(int paramInt)
  {
    Parcel localParcel1 = Parcel.obtain();
    Parcel localParcel2 = Parcel.obtain();
    try
    {
      localParcel1.writeInterfaceToken("com.google.android.gms.games.internal.IGamesCallbacks");
      localParcel1.writeInt(paramInt);
      this.a.transact(5013, localParcel1, localParcel2, 0);
      localParcel2.readException();
      return;
    }
    finally
    {
      localParcel2.recycle();
      localParcel1.recycle();
    }
  }
  
  public final void a(int paramInt1, int paramInt2, String paramString)
  {
    Parcel localParcel1 = Parcel.obtain();
    Parcel localParcel2 = Parcel.obtain();
    try
    {
      localParcel1.writeInterfaceToken("com.google.android.gms.games.internal.IGamesCallbacks");
      localParcel1.writeInt(paramInt1);
      localParcel1.writeInt(paramInt2);
      localParcel1.writeString(paramString);
      this.a.transact(5033, localParcel1, localParcel2, 0);
      localParcel2.readException();
      return;
    }
    finally
    {
      localParcel2.recycle();
      localParcel1.recycle();
    }
  }
  
  public final void a(int paramInt, String paramString)
  {
    Parcel localParcel1 = Parcel.obtain();
    Parcel localParcel2 = Parcel.obtain();
    try
    {
      localParcel1.writeInterfaceToken("com.google.android.gms.games.internal.IGamesCallbacks");
      localParcel1.writeInt(paramInt);
      localParcel1.writeString(paramString);
      this.a.transact(5001, localParcel1, localParcel2, 0);
      localParcel2.readException();
      return;
    }
    finally
    {
      localParcel2.recycle();
      localParcel1.recycle();
    }
  }
  
  public final void a(int paramInt, String paramString, boolean paramBoolean)
  {
    Parcel localParcel1 = Parcel.obtain();
    Parcel localParcel2 = Parcel.obtain();
    try
    {
      localParcel1.writeInterfaceToken("com.google.android.gms.games.internal.IGamesCallbacks");
      localParcel1.writeInt(paramInt);
      localParcel1.writeString(paramString);
      int i = 0;
      if (paramBoolean) {
        i = 1;
      }
      localParcel1.writeInt(i);
      this.a.transact(5034, localParcel1, localParcel2, 0);
      localParcel2.readException();
      return;
    }
    finally
    {
      localParcel2.recycle();
      localParcel1.recycle();
    }
  }
  
  /* Error */
  public final void a(d paramd)
  {
    // Byte code:
    //   0: invokestatic 21	android/os/Parcel:obtain	()Landroid/os/Parcel;
    //   3: astore_2
    //   4: invokestatic 21	android/os/Parcel:obtain	()Landroid/os/Parcel;
    //   7: astore_3
    //   8: aload_2
    //   9: ldc 23
    //   11: invokevirtual 27	android/os/Parcel:writeInterfaceToken	(Ljava/lang/String;)V
    //   14: aload_1
    //   15: ifnull +43 -> 58
    //   18: aload_2
    //   19: iconst_1
    //   20: invokevirtual 43	android/os/Parcel:writeInt	(I)V
    //   23: aload_1
    //   24: aload_2
    //   25: iconst_0
    //   26: invokevirtual 56	com/google/android/gms/common/data/d:writeToParcel	(Landroid/os/Parcel;I)V
    //   29: aload_0
    //   30: getfield 15	com/google/android/gms/internal/dp:a	Landroid/os/IBinder;
    //   33: sipush 5002
    //   36: aload_2
    //   37: aload_3
    //   38: iconst_0
    //   39: invokeinterface 33 5 0
    //   44: pop
    //   45: aload_3
    //   46: invokevirtual 36	android/os/Parcel:readException	()V
    //   49: aload_3
    //   50: invokevirtual 39	android/os/Parcel:recycle	()V
    //   53: aload_2
    //   54: invokevirtual 39	android/os/Parcel:recycle	()V
    //   57: return
    //   58: aload_2
    //   59: iconst_0
    //   60: invokevirtual 43	android/os/Parcel:writeInt	(I)V
    //   63: goto -34 -> 29
    //   66: astore 4
    //   68: aload_3
    //   69: invokevirtual 39	android/os/Parcel:recycle	()V
    //   72: aload_2
    //   73: invokevirtual 39	android/os/Parcel:recycle	()V
    //   76: aload 4
    //   78: athrow
    // Local variable table:
    //   start	length	slot	name	signature
    //   0	79	0	this	dp
    //   0	79	1	paramd	d
    //   3	70	2	localParcel1	Parcel
    //   7	62	3	localParcel2	Parcel
    //   66	11	4	localObject	Object
    // Exception table:
    //   from	to	target	type
    //   8	14	66	finally
    //   18	29	66	finally
    //   29	49	66	finally
    //   58	63	66	finally
  }
  
  public final void a(d paramd1, d paramd2)
  {
    Parcel localParcel1 = Parcel.obtain();
    Parcel localParcel2 = Parcel.obtain();
    for (;;)
    {
      try
      {
        localParcel1.writeInterfaceToken("com.google.android.gms.games.internal.IGamesCallbacks");
        if (paramd1 != null)
        {
          localParcel1.writeInt(1);
          paramd1.writeToParcel(localParcel1, 0);
          if (paramd2 != null)
          {
            localParcel1.writeInt(1);
            paramd2.writeToParcel(localParcel1, 0);
            this.a.transact(5005, localParcel1, localParcel2, 0);
            localParcel2.readException();
          }
        }
        else
        {
          localParcel1.writeInt(0);
          continue;
        }
        localParcel1.writeInt(0);
      }
      finally
      {
        localParcel2.recycle();
        localParcel1.recycle();
      }
    }
  }
  
  /* Error */
  public final void a(d paramd, String[] paramArrayOfString)
  {
    // Byte code:
    //   0: invokestatic 21	android/os/Parcel:obtain	()Landroid/os/Parcel;
    //   3: astore_3
    //   4: invokestatic 21	android/os/Parcel:obtain	()Landroid/os/Parcel;
    //   7: astore 4
    //   9: aload_3
    //   10: ldc 23
    //   12: invokevirtual 27	android/os/Parcel:writeInterfaceToken	(Ljava/lang/String;)V
    //   15: aload_1
    //   16: ifnull +51 -> 67
    //   19: aload_3
    //   20: iconst_1
    //   21: invokevirtual 43	android/os/Parcel:writeInt	(I)V
    //   24: aload_1
    //   25: aload_3
    //   26: iconst_0
    //   27: invokevirtual 56	com/google/android/gms/common/data/d:writeToParcel	(Landroid/os/Parcel;I)V
    //   30: aload_3
    //   31: aload_2
    //   32: invokevirtual 62	android/os/Parcel:writeStringArray	([Ljava/lang/String;)V
    //   35: aload_0
    //   36: getfield 15	com/google/android/gms/internal/dp:a	Landroid/os/IBinder;
    //   39: sipush 5026
    //   42: aload_3
    //   43: aload 4
    //   45: iconst_0
    //   46: invokeinterface 33 5 0
    //   51: pop
    //   52: aload 4
    //   54: invokevirtual 36	android/os/Parcel:readException	()V
    //   57: aload 4
    //   59: invokevirtual 39	android/os/Parcel:recycle	()V
    //   62: aload_3
    //   63: invokevirtual 39	android/os/Parcel:recycle	()V
    //   66: return
    //   67: aload_3
    //   68: iconst_0
    //   69: invokevirtual 43	android/os/Parcel:writeInt	(I)V
    //   72: goto -42 -> 30
    //   75: astore 5
    //   77: aload 4
    //   79: invokevirtual 39	android/os/Parcel:recycle	()V
    //   82: aload_3
    //   83: invokevirtual 39	android/os/Parcel:recycle	()V
    //   86: aload 5
    //   88: athrow
    // Local variable table:
    //   start	length	slot	name	signature
    //   0	89	0	this	dp
    //   0	89	1	paramd	d
    //   0	89	2	paramArrayOfString	String[]
    //   3	80	3	localParcel1	Parcel
    //   7	71	4	localParcel2	Parcel
    //   75	12	5	localObject	Object
    // Exception table:
    //   from	to	target	type
    //   9	15	75	finally
    //   19	30	75	finally
    //   30	57	75	finally
    //   67	72	75	finally
  }
  
  /* Error */
  public final void a(com.google.android.gms.games.multiplayer.realtime.RealTimeMessage paramRealTimeMessage)
  {
    // Byte code:
    //   0: invokestatic 21	android/os/Parcel:obtain	()Landroid/os/Parcel;
    //   3: astore_2
    //   4: invokestatic 21	android/os/Parcel:obtain	()Landroid/os/Parcel;
    //   7: astore_3
    //   8: aload_2
    //   9: ldc 23
    //   11: invokevirtual 27	android/os/Parcel:writeInterfaceToken	(Ljava/lang/String;)V
    //   14: aload_1
    //   15: ifnull +43 -> 58
    //   18: aload_2
    //   19: iconst_1
    //   20: invokevirtual 43	android/os/Parcel:writeInt	(I)V
    //   23: aload_1
    //   24: aload_2
    //   25: iconst_0
    //   26: invokevirtual 66	com/google/android/gms/games/multiplayer/realtime/RealTimeMessage:writeToParcel	(Landroid/os/Parcel;I)V
    //   29: aload_0
    //   30: getfield 15	com/google/android/gms/internal/dp:a	Landroid/os/IBinder;
    //   33: sipush 5032
    //   36: aload_2
    //   37: aload_3
    //   38: iconst_0
    //   39: invokeinterface 33 5 0
    //   44: pop
    //   45: aload_3
    //   46: invokevirtual 36	android/os/Parcel:readException	()V
    //   49: aload_3
    //   50: invokevirtual 39	android/os/Parcel:recycle	()V
    //   53: aload_2
    //   54: invokevirtual 39	android/os/Parcel:recycle	()V
    //   57: return
    //   58: aload_2
    //   59: iconst_0
    //   60: invokevirtual 43	android/os/Parcel:writeInt	(I)V
    //   63: goto -34 -> 29
    //   66: astore 4
    //   68: aload_3
    //   69: invokevirtual 39	android/os/Parcel:recycle	()V
    //   72: aload_2
    //   73: invokevirtual 39	android/os/Parcel:recycle	()V
    //   76: aload 4
    //   78: athrow
    // Local variable table:
    //   start	length	slot	name	signature
    //   0	79	0	this	dp
    //   0	79	1	paramRealTimeMessage	com.google.android.gms.games.multiplayer.realtime.RealTimeMessage
    //   3	70	2	localParcel1	Parcel
    //   7	62	3	localParcel2	Parcel
    //   66	11	4	localObject	Object
    // Exception table:
    //   from	to	target	type
    //   8	14	66	finally
    //   18	29	66	finally
    //   29	49	66	finally
    //   58	63	66	finally
  }
  
  public final void a(String paramString)
  {
    Parcel localParcel1 = Parcel.obtain();
    Parcel localParcel2 = Parcel.obtain();
    try
    {
      localParcel1.writeInterfaceToken("com.google.android.gms.games.internal.IGamesCallbacks");
      localParcel1.writeString(paramString);
      this.a.transact(6001, localParcel1, localParcel2, 0);
      localParcel2.readException();
      return;
    }
    finally
    {
      localParcel2.recycle();
      localParcel1.recycle();
    }
  }
  
  public final IBinder asBinder()
  {
    return this.a;
  }
  
  public final void b(int paramInt)
  {
    Parcel localParcel1 = Parcel.obtain();
    Parcel localParcel2 = Parcel.obtain();
    try
    {
      localParcel1.writeInterfaceToken("com.google.android.gms.games.internal.IGamesCallbacks");
      localParcel1.writeInt(paramInt);
      this.a.transact(5015, localParcel1, localParcel2, 0);
      localParcel2.readException();
      return;
    }
    finally
    {
      localParcel2.recycle();
      localParcel1.recycle();
    }
  }
  
  public final void b(int paramInt, String paramString)
  {
    Parcel localParcel1 = Parcel.obtain();
    Parcel localParcel2 = Parcel.obtain();
    try
    {
      localParcel1.writeInterfaceToken("com.google.android.gms.games.internal.IGamesCallbacks");
      localParcel1.writeInt(paramInt);
      localParcel1.writeString(paramString);
      this.a.transact(5003, localParcel1, localParcel2, 0);
      localParcel2.readException();
      return;
    }
    finally
    {
      localParcel2.recycle();
      localParcel1.recycle();
    }
  }
  
  /* Error */
  public final void b(d paramd)
  {
    // Byte code:
    //   0: invokestatic 21	android/os/Parcel:obtain	()Landroid/os/Parcel;
    //   3: astore_2
    //   4: invokestatic 21	android/os/Parcel:obtain	()Landroid/os/Parcel;
    //   7: astore_3
    //   8: aload_2
    //   9: ldc 23
    //   11: invokevirtual 27	android/os/Parcel:writeInterfaceToken	(Ljava/lang/String;)V
    //   14: aload_1
    //   15: ifnull +43 -> 58
    //   18: aload_2
    //   19: iconst_1
    //   20: invokevirtual 43	android/os/Parcel:writeInt	(I)V
    //   23: aload_1
    //   24: aload_2
    //   25: iconst_0
    //   26: invokevirtual 56	com/google/android/gms/common/data/d:writeToParcel	(Landroid/os/Parcel;I)V
    //   29: aload_0
    //   30: getfield 15	com/google/android/gms/internal/dp:a	Landroid/os/IBinder;
    //   33: sipush 5004
    //   36: aload_2
    //   37: aload_3
    //   38: iconst_0
    //   39: invokeinterface 33 5 0
    //   44: pop
    //   45: aload_3
    //   46: invokevirtual 36	android/os/Parcel:readException	()V
    //   49: aload_3
    //   50: invokevirtual 39	android/os/Parcel:recycle	()V
    //   53: aload_2
    //   54: invokevirtual 39	android/os/Parcel:recycle	()V
    //   57: return
    //   58: aload_2
    //   59: iconst_0
    //   60: invokevirtual 43	android/os/Parcel:writeInt	(I)V
    //   63: goto -34 -> 29
    //   66: astore 4
    //   68: aload_3
    //   69: invokevirtual 39	android/os/Parcel:recycle	()V
    //   72: aload_2
    //   73: invokevirtual 39	android/os/Parcel:recycle	()V
    //   76: aload 4
    //   78: athrow
    // Local variable table:
    //   start	length	slot	name	signature
    //   0	79	0	this	dp
    //   0	79	1	paramd	d
    //   3	70	2	localParcel1	Parcel
    //   7	62	3	localParcel2	Parcel
    //   66	11	4	localObject	Object
    // Exception table:
    //   from	to	target	type
    //   8	14	66	finally
    //   18	29	66	finally
    //   29	49	66	finally
    //   58	63	66	finally
  }
  
  /* Error */
  public final void b(d paramd, String[] paramArrayOfString)
  {
    // Byte code:
    //   0: invokestatic 21	android/os/Parcel:obtain	()Landroid/os/Parcel;
    //   3: astore_3
    //   4: invokestatic 21	android/os/Parcel:obtain	()Landroid/os/Parcel;
    //   7: astore 4
    //   9: aload_3
    //   10: ldc 23
    //   12: invokevirtual 27	android/os/Parcel:writeInterfaceToken	(Ljava/lang/String;)V
    //   15: aload_1
    //   16: ifnull +51 -> 67
    //   19: aload_3
    //   20: iconst_1
    //   21: invokevirtual 43	android/os/Parcel:writeInt	(I)V
    //   24: aload_1
    //   25: aload_3
    //   26: iconst_0
    //   27: invokevirtual 56	com/google/android/gms/common/data/d:writeToParcel	(Landroid/os/Parcel;I)V
    //   30: aload_3
    //   31: aload_2
    //   32: invokevirtual 62	android/os/Parcel:writeStringArray	([Ljava/lang/String;)V
    //   35: aload_0
    //   36: getfield 15	com/google/android/gms/internal/dp:a	Landroid/os/IBinder;
    //   39: sipush 5027
    //   42: aload_3
    //   43: aload 4
    //   45: iconst_0
    //   46: invokeinterface 33 5 0
    //   51: pop
    //   52: aload 4
    //   54: invokevirtual 36	android/os/Parcel:readException	()V
    //   57: aload 4
    //   59: invokevirtual 39	android/os/Parcel:recycle	()V
    //   62: aload_3
    //   63: invokevirtual 39	android/os/Parcel:recycle	()V
    //   66: return
    //   67: aload_3
    //   68: iconst_0
    //   69: invokevirtual 43	android/os/Parcel:writeInt	(I)V
    //   72: goto -42 -> 30
    //   75: astore 5
    //   77: aload 4
    //   79: invokevirtual 39	android/os/Parcel:recycle	()V
    //   82: aload_3
    //   83: invokevirtual 39	android/os/Parcel:recycle	()V
    //   86: aload 5
    //   88: athrow
    // Local variable table:
    //   start	length	slot	name	signature
    //   0	89	0	this	dp
    //   0	89	1	paramd	d
    //   0	89	2	paramArrayOfString	String[]
    //   3	80	3	localParcel1	Parcel
    //   7	71	4	localParcel2	Parcel
    //   75	12	5	localObject	Object
    // Exception table:
    //   from	to	target	type
    //   9	15	75	finally
    //   19	30	75	finally
    //   30	57	75	finally
    //   67	72	75	finally
  }
  
  public final void b(String paramString)
  {
    Parcel localParcel1 = Parcel.obtain();
    Parcel localParcel2 = Parcel.obtain();
    try
    {
      localParcel1.writeInterfaceToken("com.google.android.gms.games.internal.IGamesCallbacks");
      localParcel1.writeString(paramString);
      this.a.transact(6002, localParcel1, localParcel2, 0);
      localParcel2.readException();
      return;
    }
    finally
    {
      localParcel2.recycle();
      localParcel1.recycle();
    }
  }
  
  public final void c(int paramInt)
  {
    Parcel localParcel1 = Parcel.obtain();
    Parcel localParcel2 = Parcel.obtain();
    try
    {
      localParcel1.writeInterfaceToken("com.google.android.gms.games.internal.IGamesCallbacks");
      localParcel1.writeInt(paramInt);
      this.a.transact(5036, localParcel1, localParcel2, 0);
      localParcel2.readException();
      return;
    }
    finally
    {
      localParcel2.recycle();
      localParcel1.recycle();
    }
  }
  
  public final void c(int paramInt, String paramString)
  {
    Parcel localParcel1 = Parcel.obtain();
    Parcel localParcel2 = Parcel.obtain();
    try
    {
      localParcel1.writeInterfaceToken("com.google.android.gms.games.internal.IGamesCallbacks");
      localParcel1.writeInt(paramInt);
      localParcel1.writeString(paramString);
      this.a.transact(5020, localParcel1, localParcel2, 0);
      localParcel2.readException();
      return;
    }
    finally
    {
      localParcel2.recycle();
      localParcel1.recycle();
    }
  }
  
  /* Error */
  public final void c(d paramd)
  {
    // Byte code:
    //   0: invokestatic 21	android/os/Parcel:obtain	()Landroid/os/Parcel;
    //   3: astore_2
    //   4: invokestatic 21	android/os/Parcel:obtain	()Landroid/os/Parcel;
    //   7: astore_3
    //   8: aload_2
    //   9: ldc 23
    //   11: invokevirtual 27	android/os/Parcel:writeInterfaceToken	(Ljava/lang/String;)V
    //   14: aload_1
    //   15: ifnull +43 -> 58
    //   18: aload_2
    //   19: iconst_1
    //   20: invokevirtual 43	android/os/Parcel:writeInt	(I)V
    //   23: aload_1
    //   24: aload_2
    //   25: iconst_0
    //   26: invokevirtual 56	com/google/android/gms/common/data/d:writeToParcel	(Landroid/os/Parcel;I)V
    //   29: aload_0
    //   30: getfield 15	com/google/android/gms/internal/dp:a	Landroid/os/IBinder;
    //   33: sipush 5006
    //   36: aload_2
    //   37: aload_3
    //   38: iconst_0
    //   39: invokeinterface 33 5 0
    //   44: pop
    //   45: aload_3
    //   46: invokevirtual 36	android/os/Parcel:readException	()V
    //   49: aload_3
    //   50: invokevirtual 39	android/os/Parcel:recycle	()V
    //   53: aload_2
    //   54: invokevirtual 39	android/os/Parcel:recycle	()V
    //   57: return
    //   58: aload_2
    //   59: iconst_0
    //   60: invokevirtual 43	android/os/Parcel:writeInt	(I)V
    //   63: goto -34 -> 29
    //   66: astore 4
    //   68: aload_3
    //   69: invokevirtual 39	android/os/Parcel:recycle	()V
    //   72: aload_2
    //   73: invokevirtual 39	android/os/Parcel:recycle	()V
    //   76: aload 4
    //   78: athrow
    // Local variable table:
    //   start	length	slot	name	signature
    //   0	79	0	this	dp
    //   0	79	1	paramd	d
    //   3	70	2	localParcel1	Parcel
    //   7	62	3	localParcel2	Parcel
    //   66	11	4	localObject	Object
    // Exception table:
    //   from	to	target	type
    //   8	14	66	finally
    //   18	29	66	finally
    //   29	49	66	finally
    //   58	63	66	finally
  }
  
  /* Error */
  public final void c(d paramd, String[] paramArrayOfString)
  {
    // Byte code:
    //   0: invokestatic 21	android/os/Parcel:obtain	()Landroid/os/Parcel;
    //   3: astore_3
    //   4: invokestatic 21	android/os/Parcel:obtain	()Landroid/os/Parcel;
    //   7: astore 4
    //   9: aload_3
    //   10: ldc 23
    //   12: invokevirtual 27	android/os/Parcel:writeInterfaceToken	(Ljava/lang/String;)V
    //   15: aload_1
    //   16: ifnull +51 -> 67
    //   19: aload_3
    //   20: iconst_1
    //   21: invokevirtual 43	android/os/Parcel:writeInt	(I)V
    //   24: aload_1
    //   25: aload_3
    //   26: iconst_0
    //   27: invokevirtual 56	com/google/android/gms/common/data/d:writeToParcel	(Landroid/os/Parcel;I)V
    //   30: aload_3
    //   31: aload_2
    //   32: invokevirtual 62	android/os/Parcel:writeStringArray	([Ljava/lang/String;)V
    //   35: aload_0
    //   36: getfield 15	com/google/android/gms/internal/dp:a	Landroid/os/IBinder;
    //   39: sipush 5028
    //   42: aload_3
    //   43: aload 4
    //   45: iconst_0
    //   46: invokeinterface 33 5 0
    //   51: pop
    //   52: aload 4
    //   54: invokevirtual 36	android/os/Parcel:readException	()V
    //   57: aload 4
    //   59: invokevirtual 39	android/os/Parcel:recycle	()V
    //   62: aload_3
    //   63: invokevirtual 39	android/os/Parcel:recycle	()V
    //   66: return
    //   67: aload_3
    //   68: iconst_0
    //   69: invokevirtual 43	android/os/Parcel:writeInt	(I)V
    //   72: goto -42 -> 30
    //   75: astore 5
    //   77: aload 4
    //   79: invokevirtual 39	android/os/Parcel:recycle	()V
    //   82: aload_3
    //   83: invokevirtual 39	android/os/Parcel:recycle	()V
    //   86: aload 5
    //   88: athrow
    // Local variable table:
    //   start	length	slot	name	signature
    //   0	89	0	this	dp
    //   0	89	1	paramd	d
    //   0	89	2	paramArrayOfString	String[]
    //   3	80	3	localParcel1	Parcel
    //   7	71	4	localParcel2	Parcel
    //   75	12	5	localObject	Object
    // Exception table:
    //   from	to	target	type
    //   9	15	75	finally
    //   19	30	75	finally
    //   30	57	75	finally
    //   67	72	75	finally
  }
  
  public final void d(int paramInt)
  {
    Parcel localParcel1 = Parcel.obtain();
    Parcel localParcel2 = Parcel.obtain();
    try
    {
      localParcel1.writeInterfaceToken("com.google.android.gms.games.internal.IGamesCallbacks");
      localParcel1.writeInt(paramInt);
      this.a.transact(5040, localParcel1, localParcel2, 0);
      localParcel2.readException();
      return;
    }
    finally
    {
      localParcel2.recycle();
      localParcel1.recycle();
    }
  }
  
  /* Error */
  public final void d(d paramd)
  {
    // Byte code:
    //   0: invokestatic 21	android/os/Parcel:obtain	()Landroid/os/Parcel;
    //   3: astore_2
    //   4: invokestatic 21	android/os/Parcel:obtain	()Landroid/os/Parcel;
    //   7: astore_3
    //   8: aload_2
    //   9: ldc 23
    //   11: invokevirtual 27	android/os/Parcel:writeInterfaceToken	(Ljava/lang/String;)V
    //   14: aload_1
    //   15: ifnull +43 -> 58
    //   18: aload_2
    //   19: iconst_1
    //   20: invokevirtual 43	android/os/Parcel:writeInt	(I)V
    //   23: aload_1
    //   24: aload_2
    //   25: iconst_0
    //   26: invokevirtual 56	com/google/android/gms/common/data/d:writeToParcel	(Landroid/os/Parcel;I)V
    //   29: aload_0
    //   30: getfield 15	com/google/android/gms/internal/dp:a	Landroid/os/IBinder;
    //   33: sipush 5007
    //   36: aload_2
    //   37: aload_3
    //   38: iconst_0
    //   39: invokeinterface 33 5 0
    //   44: pop
    //   45: aload_3
    //   46: invokevirtual 36	android/os/Parcel:readException	()V
    //   49: aload_3
    //   50: invokevirtual 39	android/os/Parcel:recycle	()V
    //   53: aload_2
    //   54: invokevirtual 39	android/os/Parcel:recycle	()V
    //   57: return
    //   58: aload_2
    //   59: iconst_0
    //   60: invokevirtual 43	android/os/Parcel:writeInt	(I)V
    //   63: goto -34 -> 29
    //   66: astore 4
    //   68: aload_3
    //   69: invokevirtual 39	android/os/Parcel:recycle	()V
    //   72: aload_2
    //   73: invokevirtual 39	android/os/Parcel:recycle	()V
    //   76: aload 4
    //   78: athrow
    // Local variable table:
    //   start	length	slot	name	signature
    //   0	79	0	this	dp
    //   0	79	1	paramd	d
    //   3	70	2	localParcel1	Parcel
    //   7	62	3	localParcel2	Parcel
    //   66	11	4	localObject	Object
    // Exception table:
    //   from	to	target	type
    //   8	14	66	finally
    //   18	29	66	finally
    //   29	49	66	finally
    //   58	63	66	finally
  }
  
  /* Error */
  public final void d(d paramd, String[] paramArrayOfString)
  {
    // Byte code:
    //   0: invokestatic 21	android/os/Parcel:obtain	()Landroid/os/Parcel;
    //   3: astore_3
    //   4: invokestatic 21	android/os/Parcel:obtain	()Landroid/os/Parcel;
    //   7: astore 4
    //   9: aload_3
    //   10: ldc 23
    //   12: invokevirtual 27	android/os/Parcel:writeInterfaceToken	(Ljava/lang/String;)V
    //   15: aload_1
    //   16: ifnull +51 -> 67
    //   19: aload_3
    //   20: iconst_1
    //   21: invokevirtual 43	android/os/Parcel:writeInt	(I)V
    //   24: aload_1
    //   25: aload_3
    //   26: iconst_0
    //   27: invokevirtual 56	com/google/android/gms/common/data/d:writeToParcel	(Landroid/os/Parcel;I)V
    //   30: aload_3
    //   31: aload_2
    //   32: invokevirtual 62	android/os/Parcel:writeStringArray	([Ljava/lang/String;)V
    //   35: aload_0
    //   36: getfield 15	com/google/android/gms/internal/dp:a	Landroid/os/IBinder;
    //   39: sipush 5029
    //   42: aload_3
    //   43: aload 4
    //   45: iconst_0
    //   46: invokeinterface 33 5 0
    //   51: pop
    //   52: aload 4
    //   54: invokevirtual 36	android/os/Parcel:readException	()V
    //   57: aload 4
    //   59: invokevirtual 39	android/os/Parcel:recycle	()V
    //   62: aload_3
    //   63: invokevirtual 39	android/os/Parcel:recycle	()V
    //   66: return
    //   67: aload_3
    //   68: iconst_0
    //   69: invokevirtual 43	android/os/Parcel:writeInt	(I)V
    //   72: goto -42 -> 30
    //   75: astore 5
    //   77: aload 4
    //   79: invokevirtual 39	android/os/Parcel:recycle	()V
    //   82: aload_3
    //   83: invokevirtual 39	android/os/Parcel:recycle	()V
    //   86: aload 5
    //   88: athrow
    // Local variable table:
    //   start	length	slot	name	signature
    //   0	89	0	this	dp
    //   0	89	1	paramd	d
    //   0	89	2	paramArrayOfString	String[]
    //   3	80	3	localParcel1	Parcel
    //   7	71	4	localParcel2	Parcel
    //   75	12	5	localObject	Object
    // Exception table:
    //   from	to	target	type
    //   9	15	75	finally
    //   19	30	75	finally
    //   30	57	75	finally
    //   67	72	75	finally
  }
  
  /* Error */
  public final void e(d paramd)
  {
    // Byte code:
    //   0: invokestatic 21	android/os/Parcel:obtain	()Landroid/os/Parcel;
    //   3: astore_2
    //   4: invokestatic 21	android/os/Parcel:obtain	()Landroid/os/Parcel;
    //   7: astore_3
    //   8: aload_2
    //   9: ldc 23
    //   11: invokevirtual 27	android/os/Parcel:writeInterfaceToken	(Ljava/lang/String;)V
    //   14: aload_1
    //   15: ifnull +43 -> 58
    //   18: aload_2
    //   19: iconst_1
    //   20: invokevirtual 43	android/os/Parcel:writeInt	(I)V
    //   23: aload_1
    //   24: aload_2
    //   25: iconst_0
    //   26: invokevirtual 56	com/google/android/gms/common/data/d:writeToParcel	(Landroid/os/Parcel;I)V
    //   29: aload_0
    //   30: getfield 15	com/google/android/gms/internal/dp:a	Landroid/os/IBinder;
    //   33: sipush 5008
    //   36: aload_2
    //   37: aload_3
    //   38: iconst_0
    //   39: invokeinterface 33 5 0
    //   44: pop
    //   45: aload_3
    //   46: invokevirtual 36	android/os/Parcel:readException	()V
    //   49: aload_3
    //   50: invokevirtual 39	android/os/Parcel:recycle	()V
    //   53: aload_2
    //   54: invokevirtual 39	android/os/Parcel:recycle	()V
    //   57: return
    //   58: aload_2
    //   59: iconst_0
    //   60: invokevirtual 43	android/os/Parcel:writeInt	(I)V
    //   63: goto -34 -> 29
    //   66: astore 4
    //   68: aload_3
    //   69: invokevirtual 39	android/os/Parcel:recycle	()V
    //   72: aload_2
    //   73: invokevirtual 39	android/os/Parcel:recycle	()V
    //   76: aload 4
    //   78: athrow
    // Local variable table:
    //   start	length	slot	name	signature
    //   0	79	0	this	dp
    //   0	79	1	paramd	d
    //   3	70	2	localParcel1	Parcel
    //   7	62	3	localParcel2	Parcel
    //   66	11	4	localObject	Object
    // Exception table:
    //   from	to	target	type
    //   8	14	66	finally
    //   18	29	66	finally
    //   29	49	66	finally
    //   58	63	66	finally
  }
  
  /* Error */
  public final void e(d paramd, String[] paramArrayOfString)
  {
    // Byte code:
    //   0: invokestatic 21	android/os/Parcel:obtain	()Landroid/os/Parcel;
    //   3: astore_3
    //   4: invokestatic 21	android/os/Parcel:obtain	()Landroid/os/Parcel;
    //   7: astore 4
    //   9: aload_3
    //   10: ldc 23
    //   12: invokevirtual 27	android/os/Parcel:writeInterfaceToken	(Ljava/lang/String;)V
    //   15: aload_1
    //   16: ifnull +51 -> 67
    //   19: aload_3
    //   20: iconst_1
    //   21: invokevirtual 43	android/os/Parcel:writeInt	(I)V
    //   24: aload_1
    //   25: aload_3
    //   26: iconst_0
    //   27: invokevirtual 56	com/google/android/gms/common/data/d:writeToParcel	(Landroid/os/Parcel;I)V
    //   30: aload_3
    //   31: aload_2
    //   32: invokevirtual 62	android/os/Parcel:writeStringArray	([Ljava/lang/String;)V
    //   35: aload_0
    //   36: getfield 15	com/google/android/gms/internal/dp:a	Landroid/os/IBinder;
    //   39: sipush 5030
    //   42: aload_3
    //   43: aload 4
    //   45: iconst_0
    //   46: invokeinterface 33 5 0
    //   51: pop
    //   52: aload 4
    //   54: invokevirtual 36	android/os/Parcel:readException	()V
    //   57: aload 4
    //   59: invokevirtual 39	android/os/Parcel:recycle	()V
    //   62: aload_3
    //   63: invokevirtual 39	android/os/Parcel:recycle	()V
    //   66: return
    //   67: aload_3
    //   68: iconst_0
    //   69: invokevirtual 43	android/os/Parcel:writeInt	(I)V
    //   72: goto -42 -> 30
    //   75: astore 5
    //   77: aload 4
    //   79: invokevirtual 39	android/os/Parcel:recycle	()V
    //   82: aload_3
    //   83: invokevirtual 39	android/os/Parcel:recycle	()V
    //   86: aload 5
    //   88: athrow
    // Local variable table:
    //   start	length	slot	name	signature
    //   0	89	0	this	dp
    //   0	89	1	paramd	d
    //   0	89	2	paramArrayOfString	String[]
    //   3	80	3	localParcel1	Parcel
    //   7	71	4	localParcel2	Parcel
    //   75	12	5	localObject	Object
    // Exception table:
    //   from	to	target	type
    //   9	15	75	finally
    //   19	30	75	finally
    //   30	57	75	finally
    //   67	72	75	finally
  }
  
  /* Error */
  public final void f(d paramd)
  {
    // Byte code:
    //   0: invokestatic 21	android/os/Parcel:obtain	()Landroid/os/Parcel;
    //   3: astore_2
    //   4: invokestatic 21	android/os/Parcel:obtain	()Landroid/os/Parcel;
    //   7: astore_3
    //   8: aload_2
    //   9: ldc 23
    //   11: invokevirtual 27	android/os/Parcel:writeInterfaceToken	(Ljava/lang/String;)V
    //   14: aload_1
    //   15: ifnull +43 -> 58
    //   18: aload_2
    //   19: iconst_1
    //   20: invokevirtual 43	android/os/Parcel:writeInt	(I)V
    //   23: aload_1
    //   24: aload_2
    //   25: iconst_0
    //   26: invokevirtual 56	com/google/android/gms/common/data/d:writeToParcel	(Landroid/os/Parcel;I)V
    //   29: aload_0
    //   30: getfield 15	com/google/android/gms/internal/dp:a	Landroid/os/IBinder;
    //   33: sipush 5009
    //   36: aload_2
    //   37: aload_3
    //   38: iconst_0
    //   39: invokeinterface 33 5 0
    //   44: pop
    //   45: aload_3
    //   46: invokevirtual 36	android/os/Parcel:readException	()V
    //   49: aload_3
    //   50: invokevirtual 39	android/os/Parcel:recycle	()V
    //   53: aload_2
    //   54: invokevirtual 39	android/os/Parcel:recycle	()V
    //   57: return
    //   58: aload_2
    //   59: iconst_0
    //   60: invokevirtual 43	android/os/Parcel:writeInt	(I)V
    //   63: goto -34 -> 29
    //   66: astore 4
    //   68: aload_3
    //   69: invokevirtual 39	android/os/Parcel:recycle	()V
    //   72: aload_2
    //   73: invokevirtual 39	android/os/Parcel:recycle	()V
    //   76: aload 4
    //   78: athrow
    // Local variable table:
    //   start	length	slot	name	signature
    //   0	79	0	this	dp
    //   0	79	1	paramd	d
    //   3	70	2	localParcel1	Parcel
    //   7	62	3	localParcel2	Parcel
    //   66	11	4	localObject	Object
    // Exception table:
    //   from	to	target	type
    //   8	14	66	finally
    //   18	29	66	finally
    //   29	49	66	finally
    //   58	63	66	finally
  }
  
  /* Error */
  public final void f(d paramd, String[] paramArrayOfString)
  {
    // Byte code:
    //   0: invokestatic 21	android/os/Parcel:obtain	()Landroid/os/Parcel;
    //   3: astore_3
    //   4: invokestatic 21	android/os/Parcel:obtain	()Landroid/os/Parcel;
    //   7: astore 4
    //   9: aload_3
    //   10: ldc 23
    //   12: invokevirtual 27	android/os/Parcel:writeInterfaceToken	(Ljava/lang/String;)V
    //   15: aload_1
    //   16: ifnull +51 -> 67
    //   19: aload_3
    //   20: iconst_1
    //   21: invokevirtual 43	android/os/Parcel:writeInt	(I)V
    //   24: aload_1
    //   25: aload_3
    //   26: iconst_0
    //   27: invokevirtual 56	com/google/android/gms/common/data/d:writeToParcel	(Landroid/os/Parcel;I)V
    //   30: aload_3
    //   31: aload_2
    //   32: invokevirtual 62	android/os/Parcel:writeStringArray	([Ljava/lang/String;)V
    //   35: aload_0
    //   36: getfield 15	com/google/android/gms/internal/dp:a	Landroid/os/IBinder;
    //   39: sipush 5031
    //   42: aload_3
    //   43: aload 4
    //   45: iconst_0
    //   46: invokeinterface 33 5 0
    //   51: pop
    //   52: aload 4
    //   54: invokevirtual 36	android/os/Parcel:readException	()V
    //   57: aload 4
    //   59: invokevirtual 39	android/os/Parcel:recycle	()V
    //   62: aload_3
    //   63: invokevirtual 39	android/os/Parcel:recycle	()V
    //   66: return
    //   67: aload_3
    //   68: iconst_0
    //   69: invokevirtual 43	android/os/Parcel:writeInt	(I)V
    //   72: goto -42 -> 30
    //   75: astore 5
    //   77: aload 4
    //   79: invokevirtual 39	android/os/Parcel:recycle	()V
    //   82: aload_3
    //   83: invokevirtual 39	android/os/Parcel:recycle	()V
    //   86: aload 5
    //   88: athrow
    // Local variable table:
    //   start	length	slot	name	signature
    //   0	89	0	this	dp
    //   0	89	1	paramd	d
    //   0	89	2	paramArrayOfString	String[]
    //   3	80	3	localParcel1	Parcel
    //   7	71	4	localParcel2	Parcel
    //   75	12	5	localObject	Object
    // Exception table:
    //   from	to	target	type
    //   9	15	75	finally
    //   19	30	75	finally
    //   30	57	75	finally
    //   67	72	75	finally
  }
  
  /* Error */
  public final void g(d paramd)
  {
    // Byte code:
    //   0: invokestatic 21	android/os/Parcel:obtain	()Landroid/os/Parcel;
    //   3: astore_2
    //   4: invokestatic 21	android/os/Parcel:obtain	()Landroid/os/Parcel;
    //   7: astore_3
    //   8: aload_2
    //   9: ldc 23
    //   11: invokevirtual 27	android/os/Parcel:writeInterfaceToken	(Ljava/lang/String;)V
    //   14: aload_1
    //   15: ifnull +43 -> 58
    //   18: aload_2
    //   19: iconst_1
    //   20: invokevirtual 43	android/os/Parcel:writeInt	(I)V
    //   23: aload_1
    //   24: aload_2
    //   25: iconst_0
    //   26: invokevirtual 56	com/google/android/gms/common/data/d:writeToParcel	(Landroid/os/Parcel;I)V
    //   29: aload_0
    //   30: getfield 15	com/google/android/gms/internal/dp:a	Landroid/os/IBinder;
    //   33: sipush 5010
    //   36: aload_2
    //   37: aload_3
    //   38: iconst_0
    //   39: invokeinterface 33 5 0
    //   44: pop
    //   45: aload_3
    //   46: invokevirtual 36	android/os/Parcel:readException	()V
    //   49: aload_3
    //   50: invokevirtual 39	android/os/Parcel:recycle	()V
    //   53: aload_2
    //   54: invokevirtual 39	android/os/Parcel:recycle	()V
    //   57: return
    //   58: aload_2
    //   59: iconst_0
    //   60: invokevirtual 43	android/os/Parcel:writeInt	(I)V
    //   63: goto -34 -> 29
    //   66: astore 4
    //   68: aload_3
    //   69: invokevirtual 39	android/os/Parcel:recycle	()V
    //   72: aload_2
    //   73: invokevirtual 39	android/os/Parcel:recycle	()V
    //   76: aload 4
    //   78: athrow
    // Local variable table:
    //   start	length	slot	name	signature
    //   0	79	0	this	dp
    //   0	79	1	paramd	d
    //   3	70	2	localParcel1	Parcel
    //   7	62	3	localParcel2	Parcel
    //   66	11	4	localObject	Object
    // Exception table:
    //   from	to	target	type
    //   8	14	66	finally
    //   18	29	66	finally
    //   29	49	66	finally
    //   58	63	66	finally
  }
  
  /* Error */
  public final void h(d paramd)
  {
    // Byte code:
    //   0: invokestatic 21	android/os/Parcel:obtain	()Landroid/os/Parcel;
    //   3: astore_2
    //   4: invokestatic 21	android/os/Parcel:obtain	()Landroid/os/Parcel;
    //   7: astore_3
    //   8: aload_2
    //   9: ldc 23
    //   11: invokevirtual 27	android/os/Parcel:writeInterfaceToken	(Ljava/lang/String;)V
    //   14: aload_1
    //   15: ifnull +43 -> 58
    //   18: aload_2
    //   19: iconst_1
    //   20: invokevirtual 43	android/os/Parcel:writeInt	(I)V
    //   23: aload_1
    //   24: aload_2
    //   25: iconst_0
    //   26: invokevirtual 56	com/google/android/gms/common/data/d:writeToParcel	(Landroid/os/Parcel;I)V
    //   29: aload_0
    //   30: getfield 15	com/google/android/gms/internal/dp:a	Landroid/os/IBinder;
    //   33: sipush 5011
    //   36: aload_2
    //   37: aload_3
    //   38: iconst_0
    //   39: invokeinterface 33 5 0
    //   44: pop
    //   45: aload_3
    //   46: invokevirtual 36	android/os/Parcel:readException	()V
    //   49: aload_3
    //   50: invokevirtual 39	android/os/Parcel:recycle	()V
    //   53: aload_2
    //   54: invokevirtual 39	android/os/Parcel:recycle	()V
    //   57: return
    //   58: aload_2
    //   59: iconst_0
    //   60: invokevirtual 43	android/os/Parcel:writeInt	(I)V
    //   63: goto -34 -> 29
    //   66: astore 4
    //   68: aload_3
    //   69: invokevirtual 39	android/os/Parcel:recycle	()V
    //   72: aload_2
    //   73: invokevirtual 39	android/os/Parcel:recycle	()V
    //   76: aload 4
    //   78: athrow
    // Local variable table:
    //   start	length	slot	name	signature
    //   0	79	0	this	dp
    //   0	79	1	paramd	d
    //   3	70	2	localParcel1	Parcel
    //   7	62	3	localParcel2	Parcel
    //   66	11	4	localObject	Object
    // Exception table:
    //   from	to	target	type
    //   8	14	66	finally
    //   18	29	66	finally
    //   29	49	66	finally
    //   58	63	66	finally
  }
  
  /* Error */
  public final void i(d paramd)
  {
    // Byte code:
    //   0: invokestatic 21	android/os/Parcel:obtain	()Landroid/os/Parcel;
    //   3: astore_2
    //   4: invokestatic 21	android/os/Parcel:obtain	()Landroid/os/Parcel;
    //   7: astore_3
    //   8: aload_2
    //   9: ldc 23
    //   11: invokevirtual 27	android/os/Parcel:writeInterfaceToken	(Ljava/lang/String;)V
    //   14: aload_1
    //   15: ifnull +43 -> 58
    //   18: aload_2
    //   19: iconst_1
    //   20: invokevirtual 43	android/os/Parcel:writeInt	(I)V
    //   23: aload_1
    //   24: aload_2
    //   25: iconst_0
    //   26: invokevirtual 56	com/google/android/gms/common/data/d:writeToParcel	(Landroid/os/Parcel;I)V
    //   29: aload_0
    //   30: getfield 15	com/google/android/gms/internal/dp:a	Landroid/os/IBinder;
    //   33: sipush 5017
    //   36: aload_2
    //   37: aload_3
    //   38: iconst_0
    //   39: invokeinterface 33 5 0
    //   44: pop
    //   45: aload_3
    //   46: invokevirtual 36	android/os/Parcel:readException	()V
    //   49: aload_3
    //   50: invokevirtual 39	android/os/Parcel:recycle	()V
    //   53: aload_2
    //   54: invokevirtual 39	android/os/Parcel:recycle	()V
    //   57: return
    //   58: aload_2
    //   59: iconst_0
    //   60: invokevirtual 43	android/os/Parcel:writeInt	(I)V
    //   63: goto -34 -> 29
    //   66: astore 4
    //   68: aload_3
    //   69: invokevirtual 39	android/os/Parcel:recycle	()V
    //   72: aload_2
    //   73: invokevirtual 39	android/os/Parcel:recycle	()V
    //   76: aload 4
    //   78: athrow
    // Local variable table:
    //   start	length	slot	name	signature
    //   0	79	0	this	dp
    //   0	79	1	paramd	d
    //   3	70	2	localParcel1	Parcel
    //   7	62	3	localParcel2	Parcel
    //   66	11	4	localObject	Object
    // Exception table:
    //   from	to	target	type
    //   8	14	66	finally
    //   18	29	66	finally
    //   29	49	66	finally
    //   58	63	66	finally
  }
  
  /* Error */
  public final void j(d paramd)
  {
    // Byte code:
    //   0: invokestatic 21	android/os/Parcel:obtain	()Landroid/os/Parcel;
    //   3: astore_2
    //   4: invokestatic 21	android/os/Parcel:obtain	()Landroid/os/Parcel;
    //   7: astore_3
    //   8: aload_2
    //   9: ldc 23
    //   11: invokevirtual 27	android/os/Parcel:writeInterfaceToken	(Ljava/lang/String;)V
    //   14: aload_1
    //   15: ifnull +43 -> 58
    //   18: aload_2
    //   19: iconst_1
    //   20: invokevirtual 43	android/os/Parcel:writeInt	(I)V
    //   23: aload_1
    //   24: aload_2
    //   25: iconst_0
    //   26: invokevirtual 56	com/google/android/gms/common/data/d:writeToParcel	(Landroid/os/Parcel;I)V
    //   29: aload_0
    //   30: getfield 15	com/google/android/gms/internal/dp:a	Landroid/os/IBinder;
    //   33: sipush 5037
    //   36: aload_2
    //   37: aload_3
    //   38: iconst_0
    //   39: invokeinterface 33 5 0
    //   44: pop
    //   45: aload_3
    //   46: invokevirtual 36	android/os/Parcel:readException	()V
    //   49: aload_3
    //   50: invokevirtual 39	android/os/Parcel:recycle	()V
    //   53: aload_2
    //   54: invokevirtual 39	android/os/Parcel:recycle	()V
    //   57: return
    //   58: aload_2
    //   59: iconst_0
    //   60: invokevirtual 43	android/os/Parcel:writeInt	(I)V
    //   63: goto -34 -> 29
    //   66: astore 4
    //   68: aload_3
    //   69: invokevirtual 39	android/os/Parcel:recycle	()V
    //   72: aload_2
    //   73: invokevirtual 39	android/os/Parcel:recycle	()V
    //   76: aload 4
    //   78: athrow
    // Local variable table:
    //   start	length	slot	name	signature
    //   0	79	0	this	dp
    //   0	79	1	paramd	d
    //   3	70	2	localParcel1	Parcel
    //   7	62	3	localParcel2	Parcel
    //   66	11	4	localObject	Object
    // Exception table:
    //   from	to	target	type
    //   8	14	66	finally
    //   18	29	66	finally
    //   29	49	66	finally
    //   58	63	66	finally
  }
  
  /* Error */
  public final void k(d paramd)
  {
    // Byte code:
    //   0: invokestatic 21	android/os/Parcel:obtain	()Landroid/os/Parcel;
    //   3: astore_2
    //   4: invokestatic 21	android/os/Parcel:obtain	()Landroid/os/Parcel;
    //   7: astore_3
    //   8: aload_2
    //   9: ldc 23
    //   11: invokevirtual 27	android/os/Parcel:writeInterfaceToken	(Ljava/lang/String;)V
    //   14: aload_1
    //   15: ifnull +43 -> 58
    //   18: aload_2
    //   19: iconst_1
    //   20: invokevirtual 43	android/os/Parcel:writeInt	(I)V
    //   23: aload_1
    //   24: aload_2
    //   25: iconst_0
    //   26: invokevirtual 56	com/google/android/gms/common/data/d:writeToParcel	(Landroid/os/Parcel;I)V
    //   29: aload_0
    //   30: getfield 15	com/google/android/gms/internal/dp:a	Landroid/os/IBinder;
    //   33: sipush 5012
    //   36: aload_2
    //   37: aload_3
    //   38: iconst_0
    //   39: invokeinterface 33 5 0
    //   44: pop
    //   45: aload_3
    //   46: invokevirtual 36	android/os/Parcel:readException	()V
    //   49: aload_3
    //   50: invokevirtual 39	android/os/Parcel:recycle	()V
    //   53: aload_2
    //   54: invokevirtual 39	android/os/Parcel:recycle	()V
    //   57: return
    //   58: aload_2
    //   59: iconst_0
    //   60: invokevirtual 43	android/os/Parcel:writeInt	(I)V
    //   63: goto -34 -> 29
    //   66: astore 4
    //   68: aload_3
    //   69: invokevirtual 39	android/os/Parcel:recycle	()V
    //   72: aload_2
    //   73: invokevirtual 39	android/os/Parcel:recycle	()V
    //   76: aload 4
    //   78: athrow
    // Local variable table:
    //   start	length	slot	name	signature
    //   0	79	0	this	dp
    //   0	79	1	paramd	d
    //   3	70	2	localParcel1	Parcel
    //   7	62	3	localParcel2	Parcel
    //   66	11	4	localObject	Object
    // Exception table:
    //   from	to	target	type
    //   8	14	66	finally
    //   18	29	66	finally
    //   29	49	66	finally
    //   58	63	66	finally
  }
  
  /* Error */
  public final void l(d paramd)
  {
    // Byte code:
    //   0: invokestatic 21	android/os/Parcel:obtain	()Landroid/os/Parcel;
    //   3: astore_2
    //   4: invokestatic 21	android/os/Parcel:obtain	()Landroid/os/Parcel;
    //   7: astore_3
    //   8: aload_2
    //   9: ldc 23
    //   11: invokevirtual 27	android/os/Parcel:writeInterfaceToken	(Ljava/lang/String;)V
    //   14: aload_1
    //   15: ifnull +43 -> 58
    //   18: aload_2
    //   19: iconst_1
    //   20: invokevirtual 43	android/os/Parcel:writeInt	(I)V
    //   23: aload_1
    //   24: aload_2
    //   25: iconst_0
    //   26: invokevirtual 56	com/google/android/gms/common/data/d:writeToParcel	(Landroid/os/Parcel;I)V
    //   29: aload_0
    //   30: getfield 15	com/google/android/gms/internal/dp:a	Landroid/os/IBinder;
    //   33: sipush 5014
    //   36: aload_2
    //   37: aload_3
    //   38: iconst_0
    //   39: invokeinterface 33 5 0
    //   44: pop
    //   45: aload_3
    //   46: invokevirtual 36	android/os/Parcel:readException	()V
    //   49: aload_3
    //   50: invokevirtual 39	android/os/Parcel:recycle	()V
    //   53: aload_2
    //   54: invokevirtual 39	android/os/Parcel:recycle	()V
    //   57: return
    //   58: aload_2
    //   59: iconst_0
    //   60: invokevirtual 43	android/os/Parcel:writeInt	(I)V
    //   63: goto -34 -> 29
    //   66: astore 4
    //   68: aload_3
    //   69: invokevirtual 39	android/os/Parcel:recycle	()V
    //   72: aload_2
    //   73: invokevirtual 39	android/os/Parcel:recycle	()V
    //   76: aload 4
    //   78: athrow
    // Local variable table:
    //   start	length	slot	name	signature
    //   0	79	0	this	dp
    //   0	79	1	paramd	d
    //   3	70	2	localParcel1	Parcel
    //   7	62	3	localParcel2	Parcel
    //   66	11	4	localObject	Object
    // Exception table:
    //   from	to	target	type
    //   8	14	66	finally
    //   18	29	66	finally
    //   29	49	66	finally
    //   58	63	66	finally
  }
  
  /* Error */
  public final void m(d paramd)
  {
    // Byte code:
    //   0: invokestatic 21	android/os/Parcel:obtain	()Landroid/os/Parcel;
    //   3: astore_2
    //   4: invokestatic 21	android/os/Parcel:obtain	()Landroid/os/Parcel;
    //   7: astore_3
    //   8: aload_2
    //   9: ldc 23
    //   11: invokevirtual 27	android/os/Parcel:writeInterfaceToken	(Ljava/lang/String;)V
    //   14: aload_1
    //   15: ifnull +43 -> 58
    //   18: aload_2
    //   19: iconst_1
    //   20: invokevirtual 43	android/os/Parcel:writeInt	(I)V
    //   23: aload_1
    //   24: aload_2
    //   25: iconst_0
    //   26: invokevirtual 56	com/google/android/gms/common/data/d:writeToParcel	(Landroid/os/Parcel;I)V
    //   29: aload_0
    //   30: getfield 15	com/google/android/gms/internal/dp:a	Landroid/os/IBinder;
    //   33: sipush 5018
    //   36: aload_2
    //   37: aload_3
    //   38: iconst_0
    //   39: invokeinterface 33 5 0
    //   44: pop
    //   45: aload_3
    //   46: invokevirtual 36	android/os/Parcel:readException	()V
    //   49: aload_3
    //   50: invokevirtual 39	android/os/Parcel:recycle	()V
    //   53: aload_2
    //   54: invokevirtual 39	android/os/Parcel:recycle	()V
    //   57: return
    //   58: aload_2
    //   59: iconst_0
    //   60: invokevirtual 43	android/os/Parcel:writeInt	(I)V
    //   63: goto -34 -> 29
    //   66: astore 4
    //   68: aload_3
    //   69: invokevirtual 39	android/os/Parcel:recycle	()V
    //   72: aload_2
    //   73: invokevirtual 39	android/os/Parcel:recycle	()V
    //   76: aload 4
    //   78: athrow
    // Local variable table:
    //   start	length	slot	name	signature
    //   0	79	0	this	dp
    //   0	79	1	paramd	d
    //   3	70	2	localParcel1	Parcel
    //   7	62	3	localParcel2	Parcel
    //   66	11	4	localObject	Object
    // Exception table:
    //   from	to	target	type
    //   8	14	66	finally
    //   18	29	66	finally
    //   29	49	66	finally
    //   58	63	66	finally
  }
  
  /* Error */
  public final void n(d paramd)
  {
    // Byte code:
    //   0: invokestatic 21	android/os/Parcel:obtain	()Landroid/os/Parcel;
    //   3: astore_2
    //   4: invokestatic 21	android/os/Parcel:obtain	()Landroid/os/Parcel;
    //   7: astore_3
    //   8: aload_2
    //   9: ldc 23
    //   11: invokevirtual 27	android/os/Parcel:writeInterfaceToken	(Ljava/lang/String;)V
    //   14: aload_1
    //   15: ifnull +43 -> 58
    //   18: aload_2
    //   19: iconst_1
    //   20: invokevirtual 43	android/os/Parcel:writeInt	(I)V
    //   23: aload_1
    //   24: aload_2
    //   25: iconst_0
    //   26: invokevirtual 56	com/google/android/gms/common/data/d:writeToParcel	(Landroid/os/Parcel;I)V
    //   29: aload_0
    //   30: getfield 15	com/google/android/gms/internal/dp:a	Landroid/os/IBinder;
    //   33: sipush 5019
    //   36: aload_2
    //   37: aload_3
    //   38: iconst_0
    //   39: invokeinterface 33 5 0
    //   44: pop
    //   45: aload_3
    //   46: invokevirtual 36	android/os/Parcel:readException	()V
    //   49: aload_3
    //   50: invokevirtual 39	android/os/Parcel:recycle	()V
    //   53: aload_2
    //   54: invokevirtual 39	android/os/Parcel:recycle	()V
    //   57: return
    //   58: aload_2
    //   59: iconst_0
    //   60: invokevirtual 43	android/os/Parcel:writeInt	(I)V
    //   63: goto -34 -> 29
    //   66: astore 4
    //   68: aload_3
    //   69: invokevirtual 39	android/os/Parcel:recycle	()V
    //   72: aload_2
    //   73: invokevirtual 39	android/os/Parcel:recycle	()V
    //   76: aload 4
    //   78: athrow
    // Local variable table:
    //   start	length	slot	name	signature
    //   0	79	0	this	dp
    //   0	79	1	paramd	d
    //   3	70	2	localParcel1	Parcel
    //   7	62	3	localParcel2	Parcel
    //   66	11	4	localObject	Object
    // Exception table:
    //   from	to	target	type
    //   8	14	66	finally
    //   18	29	66	finally
    //   29	49	66	finally
    //   58	63	66	finally
  }
  
  /* Error */
  public final void o(d paramd)
  {
    // Byte code:
    //   0: invokestatic 21	android/os/Parcel:obtain	()Landroid/os/Parcel;
    //   3: astore_2
    //   4: invokestatic 21	android/os/Parcel:obtain	()Landroid/os/Parcel;
    //   7: astore_3
    //   8: aload_2
    //   9: ldc 23
    //   11: invokevirtual 27	android/os/Parcel:writeInterfaceToken	(Ljava/lang/String;)V
    //   14: aload_1
    //   15: ifnull +43 -> 58
    //   18: aload_2
    //   19: iconst_1
    //   20: invokevirtual 43	android/os/Parcel:writeInt	(I)V
    //   23: aload_1
    //   24: aload_2
    //   25: iconst_0
    //   26: invokevirtual 56	com/google/android/gms/common/data/d:writeToParcel	(Landroid/os/Parcel;I)V
    //   29: aload_0
    //   30: getfield 15	com/google/android/gms/internal/dp:a	Landroid/os/IBinder;
    //   33: sipush 5021
    //   36: aload_2
    //   37: aload_3
    //   38: iconst_0
    //   39: invokeinterface 33 5 0
    //   44: pop
    //   45: aload_3
    //   46: invokevirtual 36	android/os/Parcel:readException	()V
    //   49: aload_3
    //   50: invokevirtual 39	android/os/Parcel:recycle	()V
    //   53: aload_2
    //   54: invokevirtual 39	android/os/Parcel:recycle	()V
    //   57: return
    //   58: aload_2
    //   59: iconst_0
    //   60: invokevirtual 43	android/os/Parcel:writeInt	(I)V
    //   63: goto -34 -> 29
    //   66: astore 4
    //   68: aload_3
    //   69: invokevirtual 39	android/os/Parcel:recycle	()V
    //   72: aload_2
    //   73: invokevirtual 39	android/os/Parcel:recycle	()V
    //   76: aload 4
    //   78: athrow
    // Local variable table:
    //   start	length	slot	name	signature
    //   0	79	0	this	dp
    //   0	79	1	paramd	d
    //   3	70	2	localParcel1	Parcel
    //   7	62	3	localParcel2	Parcel
    //   66	11	4	localObject	Object
    // Exception table:
    //   from	to	target	type
    //   8	14	66	finally
    //   18	29	66	finally
    //   29	49	66	finally
    //   58	63	66	finally
  }
  
  /* Error */
  public final void p(d paramd)
  {
    // Byte code:
    //   0: invokestatic 21	android/os/Parcel:obtain	()Landroid/os/Parcel;
    //   3: astore_2
    //   4: invokestatic 21	android/os/Parcel:obtain	()Landroid/os/Parcel;
    //   7: astore_3
    //   8: aload_2
    //   9: ldc 23
    //   11: invokevirtual 27	android/os/Parcel:writeInterfaceToken	(Ljava/lang/String;)V
    //   14: aload_1
    //   15: ifnull +43 -> 58
    //   18: aload_2
    //   19: iconst_1
    //   20: invokevirtual 43	android/os/Parcel:writeInt	(I)V
    //   23: aload_1
    //   24: aload_2
    //   25: iconst_0
    //   26: invokevirtual 56	com/google/android/gms/common/data/d:writeToParcel	(Landroid/os/Parcel;I)V
    //   29: aload_0
    //   30: getfield 15	com/google/android/gms/internal/dp:a	Landroid/os/IBinder;
    //   33: sipush 5022
    //   36: aload_2
    //   37: aload_3
    //   38: iconst_0
    //   39: invokeinterface 33 5 0
    //   44: pop
    //   45: aload_3
    //   46: invokevirtual 36	android/os/Parcel:readException	()V
    //   49: aload_3
    //   50: invokevirtual 39	android/os/Parcel:recycle	()V
    //   53: aload_2
    //   54: invokevirtual 39	android/os/Parcel:recycle	()V
    //   57: return
    //   58: aload_2
    //   59: iconst_0
    //   60: invokevirtual 43	android/os/Parcel:writeInt	(I)V
    //   63: goto -34 -> 29
    //   66: astore 4
    //   68: aload_3
    //   69: invokevirtual 39	android/os/Parcel:recycle	()V
    //   72: aload_2
    //   73: invokevirtual 39	android/os/Parcel:recycle	()V
    //   76: aload 4
    //   78: athrow
    // Local variable table:
    //   start	length	slot	name	signature
    //   0	79	0	this	dp
    //   0	79	1	paramd	d
    //   3	70	2	localParcel1	Parcel
    //   7	62	3	localParcel2	Parcel
    //   66	11	4	localObject	Object
    // Exception table:
    //   from	to	target	type
    //   8	14	66	finally
    //   18	29	66	finally
    //   29	49	66	finally
    //   58	63	66	finally
  }
  
  /* Error */
  public final void q(d paramd)
  {
    // Byte code:
    //   0: invokestatic 21	android/os/Parcel:obtain	()Landroid/os/Parcel;
    //   3: astore_2
    //   4: invokestatic 21	android/os/Parcel:obtain	()Landroid/os/Parcel;
    //   7: astore_3
    //   8: aload_2
    //   9: ldc 23
    //   11: invokevirtual 27	android/os/Parcel:writeInterfaceToken	(Ljava/lang/String;)V
    //   14: aload_1
    //   15: ifnull +43 -> 58
    //   18: aload_2
    //   19: iconst_1
    //   20: invokevirtual 43	android/os/Parcel:writeInt	(I)V
    //   23: aload_1
    //   24: aload_2
    //   25: iconst_0
    //   26: invokevirtual 56	com/google/android/gms/common/data/d:writeToParcel	(Landroid/os/Parcel;I)V
    //   29: aload_0
    //   30: getfield 15	com/google/android/gms/internal/dp:a	Landroid/os/IBinder;
    //   33: sipush 5023
    //   36: aload_2
    //   37: aload_3
    //   38: iconst_0
    //   39: invokeinterface 33 5 0
    //   44: pop
    //   45: aload_3
    //   46: invokevirtual 36	android/os/Parcel:readException	()V
    //   49: aload_3
    //   50: invokevirtual 39	android/os/Parcel:recycle	()V
    //   53: aload_2
    //   54: invokevirtual 39	android/os/Parcel:recycle	()V
    //   57: return
    //   58: aload_2
    //   59: iconst_0
    //   60: invokevirtual 43	android/os/Parcel:writeInt	(I)V
    //   63: goto -34 -> 29
    //   66: astore 4
    //   68: aload_3
    //   69: invokevirtual 39	android/os/Parcel:recycle	()V
    //   72: aload_2
    //   73: invokevirtual 39	android/os/Parcel:recycle	()V
    //   76: aload 4
    //   78: athrow
    // Local variable table:
    //   start	length	slot	name	signature
    //   0	79	0	this	dp
    //   0	79	1	paramd	d
    //   3	70	2	localParcel1	Parcel
    //   7	62	3	localParcel2	Parcel
    //   66	11	4	localObject	Object
    // Exception table:
    //   from	to	target	type
    //   8	14	66	finally
    //   18	29	66	finally
    //   29	49	66	finally
    //   58	63	66	finally
  }
  
  /* Error */
  public final void r(d paramd)
  {
    // Byte code:
    //   0: invokestatic 21	android/os/Parcel:obtain	()Landroid/os/Parcel;
    //   3: astore_2
    //   4: invokestatic 21	android/os/Parcel:obtain	()Landroid/os/Parcel;
    //   7: astore_3
    //   8: aload_2
    //   9: ldc 23
    //   11: invokevirtual 27	android/os/Parcel:writeInterfaceToken	(Ljava/lang/String;)V
    //   14: aload_1
    //   15: ifnull +43 -> 58
    //   18: aload_2
    //   19: iconst_1
    //   20: invokevirtual 43	android/os/Parcel:writeInt	(I)V
    //   23: aload_1
    //   24: aload_2
    //   25: iconst_0
    //   26: invokevirtual 56	com/google/android/gms/common/data/d:writeToParcel	(Landroid/os/Parcel;I)V
    //   29: aload_0
    //   30: getfield 15	com/google/android/gms/internal/dp:a	Landroid/os/IBinder;
    //   33: sipush 5024
    //   36: aload_2
    //   37: aload_3
    //   38: iconst_0
    //   39: invokeinterface 33 5 0
    //   44: pop
    //   45: aload_3
    //   46: invokevirtual 36	android/os/Parcel:readException	()V
    //   49: aload_3
    //   50: invokevirtual 39	android/os/Parcel:recycle	()V
    //   53: aload_2
    //   54: invokevirtual 39	android/os/Parcel:recycle	()V
    //   57: return
    //   58: aload_2
    //   59: iconst_0
    //   60: invokevirtual 43	android/os/Parcel:writeInt	(I)V
    //   63: goto -34 -> 29
    //   66: astore 4
    //   68: aload_3
    //   69: invokevirtual 39	android/os/Parcel:recycle	()V
    //   72: aload_2
    //   73: invokevirtual 39	android/os/Parcel:recycle	()V
    //   76: aload 4
    //   78: athrow
    // Local variable table:
    //   start	length	slot	name	signature
    //   0	79	0	this	dp
    //   0	79	1	paramd	d
    //   3	70	2	localParcel1	Parcel
    //   7	62	3	localParcel2	Parcel
    //   66	11	4	localObject	Object
    // Exception table:
    //   from	to	target	type
    //   8	14	66	finally
    //   18	29	66	finally
    //   29	49	66	finally
    //   58	63	66	finally
  }
  
  /* Error */
  public final void s(d paramd)
  {
    // Byte code:
    //   0: invokestatic 21	android/os/Parcel:obtain	()Landroid/os/Parcel;
    //   3: astore_2
    //   4: invokestatic 21	android/os/Parcel:obtain	()Landroid/os/Parcel;
    //   7: astore_3
    //   8: aload_2
    //   9: ldc 23
    //   11: invokevirtual 27	android/os/Parcel:writeInterfaceToken	(Ljava/lang/String;)V
    //   14: aload_1
    //   15: ifnull +43 -> 58
    //   18: aload_2
    //   19: iconst_1
    //   20: invokevirtual 43	android/os/Parcel:writeInt	(I)V
    //   23: aload_1
    //   24: aload_2
    //   25: iconst_0
    //   26: invokevirtual 56	com/google/android/gms/common/data/d:writeToParcel	(Landroid/os/Parcel;I)V
    //   29: aload_0
    //   30: getfield 15	com/google/android/gms/internal/dp:a	Landroid/os/IBinder;
    //   33: sipush 5025
    //   36: aload_2
    //   37: aload_3
    //   38: iconst_0
    //   39: invokeinterface 33 5 0
    //   44: pop
    //   45: aload_3
    //   46: invokevirtual 36	android/os/Parcel:readException	()V
    //   49: aload_3
    //   50: invokevirtual 39	android/os/Parcel:recycle	()V
    //   53: aload_2
    //   54: invokevirtual 39	android/os/Parcel:recycle	()V
    //   57: return
    //   58: aload_2
    //   59: iconst_0
    //   60: invokevirtual 43	android/os/Parcel:writeInt	(I)V
    //   63: goto -34 -> 29
    //   66: astore 4
    //   68: aload_3
    //   69: invokevirtual 39	android/os/Parcel:recycle	()V
    //   72: aload_2
    //   73: invokevirtual 39	android/os/Parcel:recycle	()V
    //   76: aload 4
    //   78: athrow
    // Local variable table:
    //   start	length	slot	name	signature
    //   0	79	0	this	dp
    //   0	79	1	paramd	d
    //   3	70	2	localParcel1	Parcel
    //   7	62	3	localParcel2	Parcel
    //   66	11	4	localObject	Object
    // Exception table:
    //   from	to	target	type
    //   8	14	66	finally
    //   18	29	66	finally
    //   29	49	66	finally
    //   58	63	66	finally
  }
  
  /* Error */
  public final void t(d paramd)
  {
    // Byte code:
    //   0: invokestatic 21	android/os/Parcel:obtain	()Landroid/os/Parcel;
    //   3: astore_2
    //   4: invokestatic 21	android/os/Parcel:obtain	()Landroid/os/Parcel;
    //   7: astore_3
    //   8: aload_2
    //   9: ldc 23
    //   11: invokevirtual 27	android/os/Parcel:writeInterfaceToken	(Ljava/lang/String;)V
    //   14: aload_1
    //   15: ifnull +43 -> 58
    //   18: aload_2
    //   19: iconst_1
    //   20: invokevirtual 43	android/os/Parcel:writeInt	(I)V
    //   23: aload_1
    //   24: aload_2
    //   25: iconst_0
    //   26: invokevirtual 56	com/google/android/gms/common/data/d:writeToParcel	(Landroid/os/Parcel;I)V
    //   29: aload_0
    //   30: getfield 15	com/google/android/gms/internal/dp:a	Landroid/os/IBinder;
    //   33: sipush 5038
    //   36: aload_2
    //   37: aload_3
    //   38: iconst_0
    //   39: invokeinterface 33 5 0
    //   44: pop
    //   45: aload_3
    //   46: invokevirtual 36	android/os/Parcel:readException	()V
    //   49: aload_3
    //   50: invokevirtual 39	android/os/Parcel:recycle	()V
    //   53: aload_2
    //   54: invokevirtual 39	android/os/Parcel:recycle	()V
    //   57: return
    //   58: aload_2
    //   59: iconst_0
    //   60: invokevirtual 43	android/os/Parcel:writeInt	(I)V
    //   63: goto -34 -> 29
    //   66: astore 4
    //   68: aload_3
    //   69: invokevirtual 39	android/os/Parcel:recycle	()V
    //   72: aload_2
    //   73: invokevirtual 39	android/os/Parcel:recycle	()V
    //   76: aload 4
    //   78: athrow
    // Local variable table:
    //   start	length	slot	name	signature
    //   0	79	0	this	dp
    //   0	79	1	paramd	d
    //   3	70	2	localParcel1	Parcel
    //   7	62	3	localParcel2	Parcel
    //   66	11	4	localObject	Object
    // Exception table:
    //   from	to	target	type
    //   8	14	66	finally
    //   18	29	66	finally
    //   29	49	66	finally
    //   58	63	66	finally
  }
  
  /* Error */
  public final void u(d paramd)
  {
    // Byte code:
    //   0: invokestatic 21	android/os/Parcel:obtain	()Landroid/os/Parcel;
    //   3: astore_2
    //   4: invokestatic 21	android/os/Parcel:obtain	()Landroid/os/Parcel;
    //   7: astore_3
    //   8: aload_2
    //   9: ldc 23
    //   11: invokevirtual 27	android/os/Parcel:writeInterfaceToken	(Ljava/lang/String;)V
    //   14: aload_1
    //   15: ifnull +43 -> 58
    //   18: aload_2
    //   19: iconst_1
    //   20: invokevirtual 43	android/os/Parcel:writeInt	(I)V
    //   23: aload_1
    //   24: aload_2
    //   25: iconst_0
    //   26: invokevirtual 56	com/google/android/gms/common/data/d:writeToParcel	(Landroid/os/Parcel;I)V
    //   29: aload_0
    //   30: getfield 15	com/google/android/gms/internal/dp:a	Landroid/os/IBinder;
    //   33: sipush 5035
    //   36: aload_2
    //   37: aload_3
    //   38: iconst_0
    //   39: invokeinterface 33 5 0
    //   44: pop
    //   45: aload_3
    //   46: invokevirtual 36	android/os/Parcel:readException	()V
    //   49: aload_3
    //   50: invokevirtual 39	android/os/Parcel:recycle	()V
    //   53: aload_2
    //   54: invokevirtual 39	android/os/Parcel:recycle	()V
    //   57: return
    //   58: aload_2
    //   59: iconst_0
    //   60: invokevirtual 43	android/os/Parcel:writeInt	(I)V
    //   63: goto -34 -> 29
    //   66: astore 4
    //   68: aload_3
    //   69: invokevirtual 39	android/os/Parcel:recycle	()V
    //   72: aload_2
    //   73: invokevirtual 39	android/os/Parcel:recycle	()V
    //   76: aload 4
    //   78: athrow
    // Local variable table:
    //   start	length	slot	name	signature
    //   0	79	0	this	dp
    //   0	79	1	paramd	d
    //   3	70	2	localParcel1	Parcel
    //   7	62	3	localParcel2	Parcel
    //   66	11	4	localObject	Object
    // Exception table:
    //   from	to	target	type
    //   8	14	66	finally
    //   18	29	66	finally
    //   29	49	66	finally
    //   58	63	66	finally
  }
  
  /* Error */
  public final void v(d paramd)
  {
    // Byte code:
    //   0: invokestatic 21	android/os/Parcel:obtain	()Landroid/os/Parcel;
    //   3: astore_2
    //   4: invokestatic 21	android/os/Parcel:obtain	()Landroid/os/Parcel;
    //   7: astore_3
    //   8: aload_2
    //   9: ldc 23
    //   11: invokevirtual 27	android/os/Parcel:writeInterfaceToken	(Ljava/lang/String;)V
    //   14: aload_1
    //   15: ifnull +43 -> 58
    //   18: aload_2
    //   19: iconst_1
    //   20: invokevirtual 43	android/os/Parcel:writeInt	(I)V
    //   23: aload_1
    //   24: aload_2
    //   25: iconst_0
    //   26: invokevirtual 56	com/google/android/gms/common/data/d:writeToParcel	(Landroid/os/Parcel;I)V
    //   29: aload_0
    //   30: getfield 15	com/google/android/gms/internal/dp:a	Landroid/os/IBinder;
    //   33: sipush 5039
    //   36: aload_2
    //   37: aload_3
    //   38: iconst_0
    //   39: invokeinterface 33 5 0
    //   44: pop
    //   45: aload_3
    //   46: invokevirtual 36	android/os/Parcel:readException	()V
    //   49: aload_3
    //   50: invokevirtual 39	android/os/Parcel:recycle	()V
    //   53: aload_2
    //   54: invokevirtual 39	android/os/Parcel:recycle	()V
    //   57: return
    //   58: aload_2
    //   59: iconst_0
    //   60: invokevirtual 43	android/os/Parcel:writeInt	(I)V
    //   63: goto -34 -> 29
    //   66: astore 4
    //   68: aload_3
    //   69: invokevirtual 39	android/os/Parcel:recycle	()V
    //   72: aload_2
    //   73: invokevirtual 39	android/os/Parcel:recycle	()V
    //   76: aload 4
    //   78: athrow
    // Local variable table:
    //   start	length	slot	name	signature
    //   0	79	0	this	dp
    //   0	79	1	paramd	d
    //   3	70	2	localParcel1	Parcel
    //   7	62	3	localParcel2	Parcel
    //   66	11	4	localObject	Object
    // Exception table:
    //   from	to	target	type
    //   8	14	66	finally
    //   18	29	66	finally
    //   29	49	66	finally
    //   58	63	66	finally
  }
}


/* Location:           C:\Users\vishnu\Desktop\New folder (3)\classes_dex2jar.jar
 * Qualified Name:     com.google.android.gms.internal.dp
 * JD-Core Version:    0.7.0.1
 */