package com.chartboost.sdk.impl;

import android.app.Activity;
import android.os.Handler;
import com.chartboost.sdk.Chartboost;

class n$1
  implements Runnable
{
  n$1(n paramn, String paramString, Activity paramActivity) {}
  
  public void a(String paramString)
  {
    n.1.1 local1 = new n.1.1(this, paramString, this.c);
    if (this.c != null)
    {
      this.c.runOnUiThread(local1);
      return;
    }
    Chartboost.sharedChartboost().getHandler().post(local1);
  }
  
  /* Error */
  public void run()
  {
    // Byte code:
    //   0: aload_0
    //   1: getfield 18	com/chartboost/sdk/impl/n$1:b	Ljava/lang/String;
    //   4: astore_1
    //   5: invokestatic 60	com/chartboost/sdk/impl/m:a	()Z
    //   8: ifeq +82 -> 90
    //   11: aconst_null
    //   12: astore_3
    //   13: invokestatic 42	com/chartboost/sdk/Chartboost:sharedChartboost	()Lcom/chartboost/sdk/Chartboost;
    //   16: astore 7
    //   18: new 62	java/net/URL
    //   21: dup
    //   22: aload_0
    //   23: getfield 18	com/chartboost/sdk/impl/n$1:b	Ljava/lang/String;
    //   26: invokespecial 64	java/net/URL:<init>	(Ljava/lang/String;)V
    //   29: invokevirtual 68	java/net/URL:openConnection	()Ljava/net/URLConnection;
    //   32: checkcast 70	java/net/HttpURLConnection
    //   35: astore 6
    //   37: aload 6
    //   39: iconst_0
    //   40: invokevirtual 74	java/net/HttpURLConnection:setInstanceFollowRedirects	(Z)V
    //   43: aload 6
    //   45: aload 7
    //   47: invokevirtual 78	com/chartboost/sdk/Chartboost:getTimeout	()I
    //   50: invokevirtual 82	java/net/HttpURLConnection:setConnectTimeout	(I)V
    //   53: aload 6
    //   55: aload 7
    //   57: invokevirtual 78	com/chartboost/sdk/Chartboost:getTimeout	()I
    //   60: invokevirtual 85	java/net/HttpURLConnection:setReadTimeout	(I)V
    //   63: aload 6
    //   65: ldc 87
    //   67: invokevirtual 91	java/net/HttpURLConnection:getHeaderField	(Ljava/lang/String;)Ljava/lang/String;
    //   70: astore 10
    //   72: aload 10
    //   74: ifnull +6 -> 80
    //   77: aload 10
    //   79: astore_1
    //   80: aload 6
    //   82: ifnull +8 -> 90
    //   85: aload 6
    //   87: invokevirtual 94	java/net/HttpURLConnection:disconnect	()V
    //   90: aload_1
    //   91: astore_2
    //   92: aload_0
    //   93: aload_2
    //   94: invokevirtual 96	com/chartboost/sdk/impl/n$1:a	(Ljava/lang/String;)V
    //   97: return
    //   98: astore 5
    //   100: aconst_null
    //   101: astore 6
    //   103: aload 6
    //   105: ifnull -15 -> 90
    //   108: aload 6
    //   110: invokevirtual 94	java/net/HttpURLConnection:disconnect	()V
    //   113: aload_1
    //   114: astore_2
    //   115: goto -23 -> 92
    //   118: astore 4
    //   120: aload_3
    //   121: ifnull +7 -> 128
    //   124: aload_3
    //   125: invokevirtual 94	java/net/HttpURLConnection:disconnect	()V
    //   128: aload 4
    //   130: athrow
    //   131: astore 9
    //   133: aload 6
    //   135: astore_3
    //   136: aload 9
    //   138: astore 4
    //   140: goto -20 -> 120
    //   143: astore 8
    //   145: goto -42 -> 103
    // Local variable table:
    //   start	length	slot	name	signature
    //   0	148	0	this	1
    //   4	110	1	localObject1	Object
    //   91	24	2	localObject2	Object
    //   12	124	3	localObject3	Object
    //   118	11	4	localObject4	Object
    //   138	1	4	localObject5	Object
    //   98	1	5	localException1	java.lang.Exception
    //   35	99	6	localHttpURLConnection	java.net.HttpURLConnection
    //   16	40	7	localChartboost	Chartboost
    //   143	1	8	localException2	java.lang.Exception
    //   131	6	9	localObject6	Object
    //   70	8	10	str	String
    // Exception table:
    //   from	to	target	type
    //   13	37	98	java/lang/Exception
    //   13	37	118	finally
    //   37	72	131	finally
    //   37	72	143	java/lang/Exception
  }
}


/* Location:           C:\Users\vishnu\Desktop\New folder (3)\classes_dex2jar.jar
 * Qualified Name:     com.chartboost.sdk.impl.n.1
 * JD-Core Version:    0.7.0.1
 */