package com.chartboost.sdk.impl;

import android.os.Bundle;
import android.os.Handler;
import android.widget.ImageView;
import com.chartboost.sdk.Chartboost;
import com.chartboost.sdk.Libraries.a.a;
import java.lang.ref.WeakReference;

class o$a
  implements Runnable
{
  private String b;
  private final WeakReference<ImageView> c;
  private o.b d;
  private String e;
  private Bundle f;
  
  public o$a(o paramo, ImageView paramImageView, o.b paramb, String paramString1, Bundle paramBundle, String paramString2)
  {
    this.c = new WeakReference(paramImageView);
    o.c localc = new o.c(this);
    if (paramImageView != null) {
      paramImageView.setImageDrawable(localc);
    }
    this.e = paramString1;
    this.d = paramb;
    this.f = paramBundle;
    this.b = paramString2;
  }
  
  public void a(a.a parama)
  {
    Chartboost.sharedChartboost().getHandler().post(new o.a.1(this, parama));
  }
  
  /* Error */
  public void run()
  {
    // Byte code:
    //   0: aconst_null
    //   1: astore_1
    //   2: aload_0
    //   3: getfield 49	com/chartboost/sdk/impl/o$a:f	Landroid/os/Bundle;
    //   6: ifnull +65 -> 71
    //   9: aload_0
    //   10: getfield 49	com/chartboost/sdk/impl/o$a:f	Landroid/os/Bundle;
    //   13: ldc 89
    //   15: invokevirtual 95	android/os/Bundle:getBoolean	(Ljava/lang/String;)Z
    //   18: istore_2
    //   19: aload_0
    //   20: getfield 22	com/chartboost/sdk/impl/o$a:a	Lcom/chartboost/sdk/impl/o;
    //   23: aload_0
    //   24: getfield 45	com/chartboost/sdk/impl/o$a:e	Ljava/lang/String;
    //   27: invokevirtual 100	com/chartboost/sdk/impl/o:a	(Ljava/lang/String;)Lcom/chartboost/sdk/Libraries/a$a;
    //   30: astore 31
    //   32: aload 31
    //   34: astore 4
    //   36: aload 4
    //   38: ifnull +52 -> 90
    //   41: iload_2
    //   42: ifeq +34 -> 76
    //   45: iconst_0
    //   46: istore 32
    //   48: aload 4
    //   50: iload 32
    //   52: invokevirtual 105	com/chartboost/sdk/Libraries/a$a:a	(Z)V
    //   55: aload 4
    //   57: astore 5
    //   59: aload 5
    //   61: ifnull +36 -> 97
    //   64: aload_0
    //   65: aload 5
    //   67: invokevirtual 107	com/chartboost/sdk/impl/o$a:a	(Lcom/chartboost/sdk/Libraries/a$a;)V
    //   70: return
    //   71: iconst_0
    //   72: istore_2
    //   73: goto -54 -> 19
    //   76: iconst_1
    //   77: istore 32
    //   79: goto -31 -> 48
    //   82: astore_3
    //   83: aconst_null
    //   84: astore 4
    //   86: aload_3
    //   87: invokevirtual 110	java/lang/Exception:printStackTrace	()V
    //   90: aload 4
    //   92: astore 5
    //   94: goto -35 -> 59
    //   97: invokestatic 115	com/chartboost/sdk/impl/l:b	()Lorg/apache/http/client/HttpClient;
    //   100: astore 6
    //   102: new 117	org/apache/http/client/methods/HttpGet
    //   105: dup
    //   106: aload_0
    //   107: getfield 51	com/chartboost/sdk/impl/o$a:b	Ljava/lang/String;
    //   110: invokespecial 120	org/apache/http/client/methods/HttpGet:<init>	(Ljava/lang/String;)V
    //   113: astore 7
    //   115: aload 6
    //   117: aload 7
    //   119: invokeinterface 126 2 0
    //   124: astore 17
    //   126: aload 17
    //   128: astore 13
    //   130: aload 13
    //   132: invokeinterface 132 1 0
    //   137: invokeinterface 138 1 0
    //   142: istore 21
    //   144: iload 21
    //   146: sipush 200
    //   149: if_icmpeq +91 -> 240
    //   152: new 140	java/lang/StringBuilder
    //   155: dup
    //   156: ldc 142
    //   158: invokespecial 143	java/lang/StringBuilder:<init>	(Ljava/lang/String;)V
    //   161: iload 21
    //   163: invokevirtual 147	java/lang/StringBuilder:append	(I)Ljava/lang/StringBuilder;
    //   166: ldc 149
    //   168: invokevirtual 152	java/lang/StringBuilder:append	(Ljava/lang/String;)Ljava/lang/StringBuilder;
    //   171: aload_0
    //   172: getfield 51	com/chartboost/sdk/impl/o$a:b	Ljava/lang/String;
    //   175: invokevirtual 152	java/lang/StringBuilder:append	(Ljava/lang/String;)Ljava/lang/StringBuilder;
    //   178: invokevirtual 156	java/lang/StringBuilder:toString	()Ljava/lang/String;
    //   181: pop
    //   182: aload 13
    //   184: invokestatic 161	com/chartboost/sdk/Libraries/CBUtility:a	(Lorg/apache/http/HttpResponse;)V
    //   187: aload_0
    //   188: aconst_null
    //   189: invokevirtual 107	com/chartboost/sdk/impl/o$a:a	(Lcom/chartboost/sdk/Libraries/a$a;)V
    //   192: return
    //   193: astore 20
    //   195: aload 13
    //   197: astore 10
    //   199: aload 5
    //   201: astore 9
    //   203: aload 7
    //   205: invokevirtual 164	org/apache/http/client/methods/HttpGet:abort	()V
    //   208: aload 10
    //   210: invokestatic 161	com/chartboost/sdk/Libraries/CBUtility:a	(Lorg/apache/http/HttpResponse;)V
    //   213: new 140	java/lang/StringBuilder
    //   216: dup
    //   217: ldc 166
    //   219: invokespecial 143	java/lang/StringBuilder:<init>	(Ljava/lang/String;)V
    //   222: aload_0
    //   223: getfield 51	com/chartboost/sdk/impl/o$a:b	Ljava/lang/String;
    //   226: invokevirtual 152	java/lang/StringBuilder:append	(Ljava/lang/String;)Ljava/lang/StringBuilder;
    //   229: invokevirtual 156	java/lang/StringBuilder:toString	()Ljava/lang/String;
    //   232: pop
    //   233: aload_0
    //   234: aload 9
    //   236: invokevirtual 107	com/chartboost/sdk/impl/o$a:a	(Lcom/chartboost/sdk/Libraries/a$a;)V
    //   239: return
    //   240: aload 13
    //   242: invokeinterface 170 1 0
    //   247: astore 23
    //   249: aload 23
    //   251: ifnull +291 -> 542
    //   254: aload 23
    //   256: invokeinterface 176 1 0
    //   261: astore_1
    //   262: aload_0
    //   263: getfield 22	com/chartboost/sdk/impl/o$a:a	Lcom/chartboost/sdk/impl/o;
    //   266: aload_0
    //   267: getfield 45	com/chartboost/sdk/impl/o$a:e	Ljava/lang/String;
    //   270: new 178	com/chartboost/sdk/impl/o$e
    //   273: dup
    //   274: aload_1
    //   275: invokespecial 181	com/chartboost/sdk/impl/o$e:<init>	(Ljava/io/InputStream;)V
    //   278: invokevirtual 184	com/chartboost/sdk/impl/o:a	(Ljava/lang/String;Lcom/chartboost/sdk/impl/o$e;)Z
    //   281: pop
    //   282: aload_0
    //   283: getfield 22	com/chartboost/sdk/impl/o$a:a	Lcom/chartboost/sdk/impl/o;
    //   286: aload_0
    //   287: getfield 45	com/chartboost/sdk/impl/o$a:e	Ljava/lang/String;
    //   290: invokevirtual 100	com/chartboost/sdk/impl/o:a	(Ljava/lang/String;)Lcom/chartboost/sdk/Libraries/a$a;
    //   293: astore 5
    //   295: aload 5
    //   297: ifnull +238 -> 535
    //   300: iconst_0
    //   301: istore 30
    //   303: iload_2
    //   304: ifeq +54 -> 358
    //   307: aload 5
    //   309: iload 30
    //   311: invokevirtual 105	com/chartboost/sdk/Libraries/a$a:a	(Z)V
    //   314: iload_2
    //   315: ifne +220 -> 535
    //   318: aload_0
    //   319: getfield 22	com/chartboost/sdk/impl/o$a:a	Lcom/chartboost/sdk/impl/o;
    //   322: invokestatic 187	com/chartboost/sdk/impl/o:a	(Lcom/chartboost/sdk/impl/o;)Lcom/chartboost/sdk/Libraries/a;
    //   325: aload_0
    //   326: getfield 45	com/chartboost/sdk/impl/o$a:e	Ljava/lang/String;
    //   329: aload 5
    //   331: invokevirtual 192	com/chartboost/sdk/Libraries/a:a	(Ljava/lang/String;Lcom/chartboost/sdk/Libraries/a$a;)V
    //   334: aload 5
    //   336: astore 9
    //   338: aload_1
    //   339: ifnull +138 -> 477
    //   342: aload_1
    //   343: invokevirtual 197	java/io/InputStream:close	()V
    //   346: goto -113 -> 233
    //   349: astore 29
    //   351: aload 13
    //   353: astore 10
    //   355: goto -152 -> 203
    //   358: iconst_1
    //   359: istore 30
    //   361: goto -54 -> 307
    //   364: astore 26
    //   366: aload 26
    //   368: invokevirtual 110	java/lang/Exception:printStackTrace	()V
    //   371: aload 5
    //   373: astore 9
    //   375: goto -37 -> 338
    //   378: astore 24
    //   380: aload_1
    //   381: ifnull +49 -> 430
    //   384: aload_1
    //   385: invokevirtual 197	java/io/InputStream:close	()V
    //   388: aload 24
    //   390: athrow
    //   391: astore 19
    //   393: aload 5
    //   395: astore 9
    //   397: aload 7
    //   399: invokevirtual 164	org/apache/http/client/methods/HttpGet:abort	()V
    //   402: aload 13
    //   404: invokestatic 161	com/chartboost/sdk/Libraries/CBUtility:a	(Lorg/apache/http/HttpResponse;)V
    //   407: new 140	java/lang/StringBuilder
    //   410: dup
    //   411: ldc 199
    //   413: invokespecial 143	java/lang/StringBuilder:<init>	(Ljava/lang/String;)V
    //   416: aload_0
    //   417: getfield 51	com/chartboost/sdk/impl/o$a:b	Ljava/lang/String;
    //   420: invokevirtual 152	java/lang/StringBuilder:append	(Ljava/lang/String;)Ljava/lang/StringBuilder;
    //   423: invokevirtual 156	java/lang/StringBuilder:toString	()Ljava/lang/String;
    //   426: pop
    //   427: goto -194 -> 233
    //   430: aload 23
    //   432: invokestatic 202	com/chartboost/sdk/Libraries/CBUtility:a	(Lorg/apache/http/HttpEntity;)V
    //   435: goto -47 -> 388
    //   438: astore 18
    //   440: aload 5
    //   442: astore 9
    //   444: aload 7
    //   446: invokevirtual 164	org/apache/http/client/methods/HttpGet:abort	()V
    //   449: aload 13
    //   451: invokestatic 161	com/chartboost/sdk/Libraries/CBUtility:a	(Lorg/apache/http/HttpResponse;)V
    //   454: new 140	java/lang/StringBuilder
    //   457: dup
    //   458: ldc 204
    //   460: invokespecial 143	java/lang/StringBuilder:<init>	(Ljava/lang/String;)V
    //   463: aload_0
    //   464: getfield 51	com/chartboost/sdk/impl/o$a:b	Ljava/lang/String;
    //   467: invokevirtual 152	java/lang/StringBuilder:append	(Ljava/lang/String;)Ljava/lang/StringBuilder;
    //   470: invokevirtual 156	java/lang/StringBuilder:toString	()Ljava/lang/String;
    //   473: pop
    //   474: goto -241 -> 233
    //   477: aload 23
    //   479: invokestatic 202	com/chartboost/sdk/Libraries/CBUtility:a	(Lorg/apache/http/HttpEntity;)V
    //   482: goto -249 -> 233
    //   485: astore 28
    //   487: goto -90 -> 397
    //   490: astore 15
    //   492: aload 5
    //   494: astore 9
    //   496: aconst_null
    //   497: astore 13
    //   499: goto -55 -> 444
    //   502: astore 27
    //   504: goto -60 -> 444
    //   507: astore 12
    //   509: aload 5
    //   511: astore 9
    //   513: aconst_null
    //   514: astore 13
    //   516: goto -119 -> 397
    //   519: astore 8
    //   521: aload 5
    //   523: astore 9
    //   525: aconst_null
    //   526: astore 10
    //   528: goto -325 -> 203
    //   531: astore_3
    //   532: goto -446 -> 86
    //   535: aload 5
    //   537: astore 9
    //   539: goto -201 -> 338
    //   542: aload 5
    //   544: astore 9
    //   546: goto -313 -> 233
    // Local variable table:
    //   start	length	slot	name	signature
    //   0	549	0	this	a
    //   1	384	1	localInputStream	java.io.InputStream
    //   18	297	2	bool1	boolean
    //   82	5	3	localException1	java.lang.Exception
    //   531	1	3	localException2	java.lang.Exception
    //   34	57	4	locala1	a.a
    //   57	486	5	locala2	a.a
    //   100	16	6	localHttpClient	org.apache.http.client.HttpClient
    //   113	332	7	localHttpGet	org.apache.http.client.methods.HttpGet
    //   519	1	8	localIOException1	java.io.IOException
    //   201	344	9	locala3	a.a
    //   197	330	10	localHttpResponse1	org.apache.http.HttpResponse
    //   507	1	12	localIllegalStateException1	java.lang.IllegalStateException
    //   128	387	13	localHttpResponse2	org.apache.http.HttpResponse
    //   490	1	15	localThrowable1	java.lang.Throwable
    //   124	3	17	localHttpResponse3	org.apache.http.HttpResponse
    //   438	1	18	localThrowable2	java.lang.Throwable
    //   391	1	19	localIllegalStateException2	java.lang.IllegalStateException
    //   193	1	20	localIOException2	java.io.IOException
    //   142	20	21	i	int
    //   247	231	23	localHttpEntity	org.apache.http.HttpEntity
    //   378	11	24	localObject	Object
    //   364	3	26	localException3	java.lang.Exception
    //   502	1	27	localThrowable3	java.lang.Throwable
    //   485	1	28	localIllegalStateException3	java.lang.IllegalStateException
    //   349	1	29	localIOException3	java.io.IOException
    //   301	59	30	bool2	boolean
    //   30	3	31	locala4	a.a
    //   46	32	32	bool3	boolean
    // Exception table:
    //   from	to	target	type
    //   19	32	82	java/lang/Exception
    //   130	144	193	java/io/IOException
    //   152	192	193	java/io/IOException
    //   240	249	193	java/io/IOException
    //   384	388	193	java/io/IOException
    //   388	391	193	java/io/IOException
    //   430	435	193	java/io/IOException
    //   342	346	349	java/io/IOException
    //   477	482	349	java/io/IOException
    //   282	295	364	java/lang/Exception
    //   307	314	364	java/lang/Exception
    //   318	334	364	java/lang/Exception
    //   254	282	378	finally
    //   282	295	378	finally
    //   307	314	378	finally
    //   318	334	378	finally
    //   366	371	378	finally
    //   130	144	391	java/lang/IllegalStateException
    //   152	192	391	java/lang/IllegalStateException
    //   240	249	391	java/lang/IllegalStateException
    //   384	388	391	java/lang/IllegalStateException
    //   388	391	391	java/lang/IllegalStateException
    //   430	435	391	java/lang/IllegalStateException
    //   130	144	438	java/lang/Throwable
    //   152	192	438	java/lang/Throwable
    //   240	249	438	java/lang/Throwable
    //   384	388	438	java/lang/Throwable
    //   388	391	438	java/lang/Throwable
    //   430	435	438	java/lang/Throwable
    //   342	346	485	java/lang/IllegalStateException
    //   477	482	485	java/lang/IllegalStateException
    //   115	126	490	java/lang/Throwable
    //   342	346	502	java/lang/Throwable
    //   477	482	502	java/lang/Throwable
    //   115	126	507	java/lang/IllegalStateException
    //   115	126	519	java/io/IOException
    //   48	55	531	java/lang/Exception
  }
}


/* Location:           C:\Users\vishnu\Desktop\New folder (3)\classes_dex2jar.jar
 * Qualified Name:     com.chartboost.sdk.impl.o.a
 * JD-Core Version:    0.7.0.1
 */