package com.jirbo.adcolony;

import java.io.File;

final class aj
  extends an
  implements Runnable
{
  g a;
  am b;
  String c;
  File d;
  Object e;
  String f;
  String g;
  boolean h;
  boolean i;
  boolean j;
  int k;
  String l;
  
  aj(g paramg, String paramString, am paramam)
  {
    this(paramg, paramString, paramam, null);
  }
  
  aj(g paramg, String paramString1, am paramam, String paramString2)
  {
    super(paramg, false);
    this.c = paramString1;
    this.b = paramam;
    if (paramString2 != null) {
      this.d = new File(paramString2);
    }
  }
  
  final aj a(Object paramObject)
  {
    this.e = paramObject;
    return this;
  }
  
  final aj a(String paramString1, String paramString2)
  {
    this.f = paramString1;
    this.g = paramString2;
    return this;
  }
  
  final void a()
  {
    this.b.a(this);
  }
  
  public final void b()
  {
    ck.a(this);
  }
  
  /* Error */
  public final void run()
  {
    // Byte code:
    //   0: iconst_1
    //   1: istore_1
    //   2: iload_1
    //   3: iconst_3
    //   4: if_icmpgt +1401 -> 1405
    //   7: aload_0
    //   8: getfield 50	com/jirbo/adcolony/aj:f	Ljava/lang/String;
    //   11: ifnull +748 -> 759
    //   14: getstatic 77	com/jirbo/adcolony/aq:a	Lcom/jirbo/adcolony/aq;
    //   17: ldc 79
    //   19: invokevirtual 82	com/jirbo/adcolony/aq:b	(Ljava/lang/Object;)Lcom/jirbo/adcolony/aq;
    //   22: pop
    //   23: aload_0
    //   24: getfield 35	com/jirbo/adcolony/aj:c	Ljava/lang/String;
    //   27: astore 37
    //   29: aload_0
    //   30: getfield 35	com/jirbo/adcolony/aj:c	Ljava/lang/String;
    //   33: astore 38
    //   35: ldc 84
    //   37: astore 39
    //   39: aload_0
    //   40: getfield 35	com/jirbo/adcolony/aj:c	Ljava/lang/String;
    //   43: invokevirtual 90	java/lang/String:toLowerCase	()Ljava/lang/String;
    //   46: ldc 92
    //   48: invokevirtual 96	java/lang/String:startsWith	(Ljava/lang/String;)Z
    //   51: ifeq +16 -> 67
    //   54: aload_0
    //   55: aload_0
    //   56: getfield 35	com/jirbo/adcolony/aj:c	Ljava/lang/String;
    //   59: bipush 7
    //   61: invokevirtual 100	java/lang/String:substring	(I)Ljava/lang/String;
    //   64: putfield 35	com/jirbo/adcolony/aj:c	Ljava/lang/String;
    //   67: aload_0
    //   68: getfield 35	com/jirbo/adcolony/aj:c	Ljava/lang/String;
    //   71: bipush 47
    //   73: invokevirtual 104	java/lang/String:indexOf	(I)I
    //   76: istore 40
    //   78: iload 40
    //   80: iconst_m1
    //   81: if_icmpeq +26 -> 107
    //   84: aload_0
    //   85: getfield 35	com/jirbo/adcolony/aj:c	Ljava/lang/String;
    //   88: iload 40
    //   90: invokevirtual 100	java/lang/String:substring	(I)Ljava/lang/String;
    //   93: astore 39
    //   95: aload_0
    //   96: getfield 35	com/jirbo/adcolony/aj:c	Ljava/lang/String;
    //   99: iconst_0
    //   100: iload 40
    //   102: invokevirtual 107	java/lang/String:substring	(II)Ljava/lang/String;
    //   105: astore 38
    //   107: new 109	java/net/Socket
    //   110: dup
    //   111: aload 38
    //   113: bipush 80
    //   115: invokespecial 112	java/net/Socket:<init>	(Ljava/lang/String;I)V
    //   118: astore 41
    //   120: aload 41
    //   122: sipush 30000
    //   125: invokevirtual 116	java/net/Socket:setSoTimeout	(I)V
    //   128: new 118	java/io/PrintStream
    //   131: dup
    //   132: aload 41
    //   134: invokevirtual 122	java/net/Socket:getOutputStream	()Ljava/io/OutputStream;
    //   137: invokespecial 125	java/io/PrintStream:<init>	(Ljava/io/OutputStream;)V
    //   140: astore 42
    //   142: aload 41
    //   144: invokevirtual 129	java/net/Socket:getInputStream	()Ljava/io/InputStream;
    //   147: astore 43
    //   149: new 131	java/lang/StringBuilder
    //   152: dup
    //   153: invokespecial 133	java/lang/StringBuilder:<init>	()V
    //   156: astore 44
    //   158: aload 44
    //   160: ldc 135
    //   162: invokevirtual 139	java/lang/StringBuilder:append	(Ljava/lang/String;)Ljava/lang/StringBuilder;
    //   165: pop
    //   166: aload 44
    //   168: aload 39
    //   170: invokevirtual 139	java/lang/StringBuilder:append	(Ljava/lang/String;)Ljava/lang/StringBuilder;
    //   173: pop
    //   174: aload 44
    //   176: ldc 141
    //   178: invokevirtual 139	java/lang/StringBuilder:append	(Ljava/lang/String;)Ljava/lang/StringBuilder;
    //   181: pop
    //   182: aload 44
    //   184: ldc 143
    //   186: invokevirtual 139	java/lang/StringBuilder:append	(Ljava/lang/String;)Ljava/lang/StringBuilder;
    //   189: pop
    //   190: aload 44
    //   192: aload 38
    //   194: invokevirtual 139	java/lang/StringBuilder:append	(Ljava/lang/String;)Ljava/lang/StringBuilder;
    //   197: pop
    //   198: aload 44
    //   200: ldc 145
    //   202: invokevirtual 139	java/lang/StringBuilder:append	(Ljava/lang/String;)Ljava/lang/StringBuilder;
    //   205: pop
    //   206: aload 44
    //   208: ldc 147
    //   210: invokevirtual 139	java/lang/StringBuilder:append	(Ljava/lang/String;)Ljava/lang/StringBuilder;
    //   213: pop
    //   214: aload 44
    //   216: aload_0
    //   217: getfield 50	com/jirbo/adcolony/aj:f	Ljava/lang/String;
    //   220: invokevirtual 139	java/lang/StringBuilder:append	(Ljava/lang/String;)Ljava/lang/StringBuilder;
    //   223: pop
    //   224: aload 44
    //   226: ldc 145
    //   228: invokevirtual 139	java/lang/StringBuilder:append	(Ljava/lang/String;)Ljava/lang/StringBuilder;
    //   231: pop
    //   232: aload 44
    //   234: ldc 149
    //   236: invokevirtual 139	java/lang/StringBuilder:append	(Ljava/lang/String;)Ljava/lang/StringBuilder;
    //   239: pop
    //   240: aload 44
    //   242: iconst_4
    //   243: aload_0
    //   244: getfield 52	com/jirbo/adcolony/aj:g	Ljava/lang/String;
    //   247: invokevirtual 153	java/lang/String:length	()I
    //   250: iadd
    //   251: invokevirtual 156	java/lang/StringBuilder:append	(I)Ljava/lang/StringBuilder;
    //   254: pop
    //   255: aload 44
    //   257: ldc 158
    //   259: invokevirtual 139	java/lang/StringBuilder:append	(Ljava/lang/String;)Ljava/lang/StringBuilder;
    //   262: pop
    //   263: aload 44
    //   265: aload_0
    //   266: getfield 52	com/jirbo/adcolony/aj:g	Ljava/lang/String;
    //   269: invokevirtual 139	java/lang/StringBuilder:append	(Ljava/lang/String;)Ljava/lang/StringBuilder;
    //   272: pop
    //   273: aload 44
    //   275: ldc 158
    //   277: invokevirtual 139	java/lang/StringBuilder:append	(Ljava/lang/String;)Ljava/lang/StringBuilder;
    //   280: pop
    //   281: aload 44
    //   283: invokevirtual 161	java/lang/StringBuilder:toString	()Ljava/lang/String;
    //   286: astore 59
    //   288: aload 42
    //   290: aload 59
    //   292: invokevirtual 164	java/io/PrintStream:print	(Ljava/lang/String;)V
    //   295: aload 42
    //   297: invokevirtual 167	java/io/PrintStream:flush	()V
    //   300: getstatic 77	com/jirbo/adcolony/aq:a	Lcom/jirbo/adcolony/aq;
    //   303: ldc 169
    //   305: invokevirtual 82	com/jirbo/adcolony/aq:b	(Ljava/lang/Object;)Lcom/jirbo/adcolony/aq;
    //   308: aload 59
    //   310: invokevirtual 82	com/jirbo/adcolony/aq:b	(Ljava/lang/Object;)Lcom/jirbo/adcolony/aq;
    //   313: pop
    //   314: new 131	java/lang/StringBuilder
    //   317: dup
    //   318: invokespecial 133	java/lang/StringBuilder:<init>	()V
    //   321: astore 61
    //   323: aload 43
    //   325: invokevirtual 174	java/io/InputStream:read	()I
    //   328: istore 62
    //   330: iload 62
    //   332: iconst_m1
    //   333: if_icmpeq +49 -> 382
    //   336: aload 61
    //   338: iload 62
    //   340: i2c
    //   341: invokevirtual 177	java/lang/StringBuilder:append	(C)Ljava/lang/StringBuilder;
    //   344: pop
    //   345: aload 61
    //   347: invokevirtual 178	java/lang/StringBuilder:length	()I
    //   350: iconst_4
    //   351: if_icmplt +21 -> 372
    //   354: aload 61
    //   356: ldc 158
    //   358: bipush 252
    //   360: aload 61
    //   362: invokevirtual 178	java/lang/StringBuilder:length	()I
    //   365: iadd
    //   366: invokevirtual 181	java/lang/StringBuilder:indexOf	(Ljava/lang/String;I)I
    //   369: ifge +13 -> 382
    //   372: aload 43
    //   374: invokevirtual 174	java/io/InputStream:read	()I
    //   377: istore 62
    //   379: goto -49 -> 330
    //   382: aload 61
    //   384: invokevirtual 161	java/lang/StringBuilder:toString	()Ljava/lang/String;
    //   387: astore 64
    //   389: aload 64
    //   391: ldc 183
    //   393: invokevirtual 186	java/lang/String:indexOf	(Ljava/lang/String;)I
    //   396: istore 65
    //   398: iload 65
    //   400: iflt +162 -> 562
    //   403: iload 65
    //   405: ldc 183
    //   407: invokevirtual 153	java/lang/String:length	()I
    //   410: iadd
    //   411: istore 66
    //   413: aload 64
    //   415: iload 66
    //   417: aload 64
    //   419: ldc 145
    //   421: iload 66
    //   423: invokevirtual 187	java/lang/String:indexOf	(Ljava/lang/String;I)I
    //   426: invokevirtual 107	java/lang/String:substring	(II)Ljava/lang/String;
    //   429: astore 67
    //   431: aload 67
    //   433: iconst_0
    //   434: invokevirtual 191	java/lang/String:charAt	(I)C
    //   437: bipush 32
    //   439: if_icmpne +14 -> 453
    //   442: aload 67
    //   444: iconst_1
    //   445: invokevirtual 100	java/lang/String:substring	(I)Ljava/lang/String;
    //   448: astore 67
    //   450: goto -19 -> 431
    //   453: aload 67
    //   455: iconst_m1
    //   456: aload 67
    //   458: invokevirtual 153	java/lang/String:length	()I
    //   461: iadd
    //   462: invokevirtual 191	java/lang/String:charAt	(I)C
    //   465: bipush 32
    //   467: if_icmpne +21 -> 488
    //   470: aload 67
    //   472: iconst_0
    //   473: iconst_m1
    //   474: aload 67
    //   476: invokevirtual 153	java/lang/String:length	()I
    //   479: iadd
    //   480: invokevirtual 107	java/lang/String:substring	(II)Ljava/lang/String;
    //   483: astore 67
    //   485: goto -32 -> 453
    //   488: aload 67
    //   490: invokestatic 196	java/lang/Integer:parseInt	(Ljava/lang/String;)I
    //   493: istore 68
    //   495: new 131	java/lang/StringBuilder
    //   498: dup
    //   499: invokespecial 133	java/lang/StringBuilder:<init>	()V
    //   502: astore 69
    //   504: iload 68
    //   506: ifeq +188 -> 694
    //   509: aload 43
    //   511: invokevirtual 174	java/io/InputStream:read	()I
    //   514: istore 73
    //   516: iload 73
    //   518: iconst_m1
    //   519: if_icmpeq +175 -> 694
    //   522: aload 69
    //   524: iload 73
    //   526: i2c
    //   527: invokevirtual 177	java/lang/StringBuilder:append	(C)Ljava/lang/StringBuilder;
    //   530: pop
    //   531: iload 68
    //   533: ifle -29 -> 504
    //   536: iinc 68 255
    //   539: iload 68
    //   541: ifne -37 -> 504
    //   544: aload 43
    //   546: invokevirtual 199	java/io/InputStream:available	()I
    //   549: istore 75
    //   551: iload 75
    //   553: ifle -49 -> 504
    //   556: iconst_m1
    //   557: istore 68
    //   559: goto -55 -> 504
    //   562: new 131	java/lang/StringBuilder
    //   565: dup
    //   566: ldc 201
    //   568: invokespecial 202	java/lang/StringBuilder:<init>	(Ljava/lang/String;)V
    //   571: aload_0
    //   572: getfield 35	com/jirbo/adcolony/aj:c	Ljava/lang/String;
    //   575: invokevirtual 139	java/lang/StringBuilder:append	(Ljava/lang/String;)Ljava/lang/StringBuilder;
    //   578: ldc 204
    //   580: invokevirtual 139	java/lang/StringBuilder:append	(Ljava/lang/String;)Ljava/lang/StringBuilder;
    //   583: invokevirtual 161	java/lang/StringBuilder:toString	()Ljava/lang/String;
    //   586: pop
    //   587: iconst_m1
    //   588: istore 68
    //   590: invokestatic 208	com/jirbo/adcolony/a:i	()V
    //   593: goto -98 -> 495
    //   596: astore_2
    //   597: iconst_3
    //   598: istore_3
    //   599: new 131	java/lang/StringBuilder
    //   602: dup
    //   603: ldc 210
    //   605: invokespecial 202	java/lang/StringBuilder:<init>	(Ljava/lang/String;)V
    //   608: aload_0
    //   609: getfield 35	com/jirbo/adcolony/aj:c	Ljava/lang/String;
    //   612: invokevirtual 139	java/lang/StringBuilder:append	(Ljava/lang/String;)Ljava/lang/StringBuilder;
    //   615: ldc 212
    //   617: invokevirtual 139	java/lang/StringBuilder:append	(Ljava/lang/String;)Ljava/lang/StringBuilder;
    //   620: aload_2
    //   621: invokevirtual 213	java/io/IOException:toString	()Ljava/lang/String;
    //   624: invokevirtual 139	java/lang/StringBuilder:append	(Ljava/lang/String;)Ljava/lang/StringBuilder;
    //   627: invokevirtual 161	java/lang/StringBuilder:toString	()Ljava/lang/String;
    //   630: pop
    //   631: invokestatic 215	com/jirbo/adcolony/a:h	()V
    //   634: iload_3
    //   635: iconst_3
    //   636: if_icmpeq +769 -> 1405
    //   639: sipush 1000
    //   642: bipush 10
    //   644: iload_3
    //   645: iconst_1
    //   646: iadd
    //   647: imul
    //   648: imul
    //   649: i2l
    //   650: lstore 5
    //   652: lload 5
    //   654: invokestatic 221	java/lang/Thread:sleep	(J)V
    //   657: getstatic 223	com/jirbo/adcolony/aq:b	Lcom/jirbo/adcolony/aq;
    //   660: ldc 225
    //   662: invokevirtual 228	com/jirbo/adcolony/aq:a	(Ljava/lang/String;)Lcom/jirbo/adcolony/aq;
    //   665: iload_3
    //   666: iconst_1
    //   667: iadd
    //   668: invokevirtual 231	com/jirbo/adcolony/aq:a	(I)Lcom/jirbo/adcolony/aq;
    //   671: ldc 233
    //   673: invokevirtual 82	com/jirbo/adcolony/aq:b	(Ljava/lang/Object;)Lcom/jirbo/adcolony/aq;
    //   676: pop
    //   677: iload_3
    //   678: iconst_1
    //   679: iadd
    //   680: istore_1
    //   681: goto -679 -> 2
    //   684: astore 72
    //   686: iload 68
    //   688: ifle +6 -> 694
    //   691: aload 72
    //   693: athrow
    //   694: aload 41
    //   696: invokevirtual 236	java/net/Socket:close	()V
    //   699: aload_0
    //   700: aload 69
    //   702: invokevirtual 161	java/lang/StringBuilder:toString	()Ljava/lang/String;
    //   705: putfield 238	com/jirbo/adcolony/aj:l	Ljava/lang/String;
    //   708: aload_0
    //   709: aload_0
    //   710: getfield 238	com/jirbo/adcolony/aj:l	Ljava/lang/String;
    //   713: invokevirtual 153	java/lang/String:length	()I
    //   716: putfield 240	com/jirbo/adcolony/aj:k	I
    //   719: getstatic 77	com/jirbo/adcolony/aq:a	Lcom/jirbo/adcolony/aq;
    //   722: ldc 242
    //   724: invokevirtual 228	com/jirbo/adcolony/aq:a	(Ljava/lang/String;)Lcom/jirbo/adcolony/aq;
    //   727: aload 37
    //   729: invokevirtual 228	com/jirbo/adcolony/aq:a	(Ljava/lang/String;)Lcom/jirbo/adcolony/aq;
    //   732: ldc 244
    //   734: invokevirtual 82	com/jirbo/adcolony/aq:b	(Ljava/lang/Object;)Lcom/jirbo/adcolony/aq;
    //   737: pop
    //   738: getstatic 77	com/jirbo/adcolony/aq:a	Lcom/jirbo/adcolony/aq;
    //   741: aload_0
    //   742: getfield 238	com/jirbo/adcolony/aj:l	Ljava/lang/String;
    //   745: invokevirtual 82	com/jirbo/adcolony/aq:b	(Ljava/lang/Object;)Lcom/jirbo/adcolony/aq;
    //   748: pop
    //   749: aload_0
    //   750: iconst_1
    //   751: putfield 246	com/jirbo/adcolony/aj:i	Z
    //   754: aload_0
    //   755: invokestatic 249	com/jirbo/adcolony/a:a	(Lcom/jirbo/adcolony/an;)V
    //   758: return
    //   759: new 251	java/net/URL
    //   762: dup
    //   763: aload_0
    //   764: getfield 35	com/jirbo/adcolony/aj:c	Ljava/lang/String;
    //   767: invokespecial 252	java/net/URL:<init>	(Ljava/lang/String;)V
    //   770: invokevirtual 256	java/net/URL:openConnection	()Ljava/net/URLConnection;
    //   773: checkcast 258	java/net/HttpURLConnection
    //   776: astore 9
    //   778: aload 9
    //   780: sipush 30000
    //   783: invokevirtual 261	java/net/HttpURLConnection:setReadTimeout	(I)V
    //   786: aload_0
    //   787: getfield 263	com/jirbo/adcolony/aj:h	Z
    //   790: ifeq +9 -> 799
    //   793: aload 9
    //   795: iconst_0
    //   796: invokevirtual 267	java/net/HttpURLConnection:setInstanceFollowRedirects	(Z)V
    //   799: aload_0
    //   800: getfield 44	com/jirbo/adcolony/aj:d	Ljava/io/File;
    //   803: ifnull +184 -> 987
    //   806: aload_0
    //   807: getfield 269	com/jirbo/adcolony/aj:a	Lcom/jirbo/adcolony/g;
    //   810: ifnull +23 -> 833
    //   813: aload_0
    //   814: getfield 269	com/jirbo/adcolony/aj:a	Lcom/jirbo/adcolony/g;
    //   817: getfield 274	com/jirbo/adcolony/g:f	Lcom/jirbo/adcolony/cg;
    //   820: ifnull +13 -> 833
    //   823: aload_0
    //   824: getfield 269	com/jirbo/adcolony/aj:a	Lcom/jirbo/adcolony/g;
    //   827: getfield 274	com/jirbo/adcolony/g:f	Lcom/jirbo/adcolony/cg;
    //   830: invokevirtual 278	com/jirbo/adcolony/cg:a	()V
    //   833: aload_0
    //   834: getfield 44	com/jirbo/adcolony/aj:d	Ljava/io/File;
    //   837: invokevirtual 281	java/io/File:getAbsolutePath	()Ljava/lang/String;
    //   840: astore 29
    //   842: new 283	java/io/FileOutputStream
    //   845: dup
    //   846: aload 29
    //   848: invokespecial 284	java/io/FileOutputStream:<init>	(Ljava/lang/String;)V
    //   851: astore 30
    //   853: aload 9
    //   855: invokevirtual 285	java/net/HttpURLConnection:getInputStream	()Ljava/io/InputStream;
    //   858: astore 31
    //   860: aload 9
    //   862: invokevirtual 288	java/net/HttpURLConnection:getContentLength	()I
    //   865: istore 32
    //   867: aload_0
    //   868: iconst_0
    //   869: putfield 240	com/jirbo/adcolony/aj:k	I
    //   872: sipush 1024
    //   875: newarray byte
    //   877: astore 33
    //   879: aload 31
    //   881: aload 33
    //   883: iconst_0
    //   884: sipush 1024
    //   887: invokevirtual 291	java/io/InputStream:read	([BII)I
    //   890: istore 34
    //   892: goto +533 -> 1425
    //   895: aload_0
    //   896: iload 34
    //   898: aload_0
    //   899: getfield 240	com/jirbo/adcolony/aj:k	I
    //   902: iadd
    //   903: putfield 240	com/jirbo/adcolony/aj:k	I
    //   906: aload 30
    //   908: aload 33
    //   910: iconst_0
    //   911: iload 34
    //   913: invokevirtual 297	java/io/OutputStream:write	([BII)V
    //   916: aload 31
    //   918: aload 33
    //   920: iconst_0
    //   921: sipush 1024
    //   924: invokevirtual 291	java/io/InputStream:read	([BII)I
    //   927: istore 34
    //   929: iload 32
    //   931: ifne +494 -> 1425
    //   934: aload 31
    //   936: invokevirtual 298	java/io/InputStream:close	()V
    //   939: aload 30
    //   941: invokevirtual 299	java/io/OutputStream:flush	()V
    //   944: aload 30
    //   946: invokevirtual 300	java/io/OutputStream:close	()V
    //   949: getstatic 223	com/jirbo/adcolony/aq:b	Lcom/jirbo/adcolony/aq;
    //   952: ldc_w 302
    //   955: invokevirtual 228	com/jirbo/adcolony/aq:a	(Ljava/lang/String;)Lcom/jirbo/adcolony/aq;
    //   958: aload_0
    //   959: getfield 35	com/jirbo/adcolony/aj:c	Ljava/lang/String;
    //   962: invokevirtual 228	com/jirbo/adcolony/aq:a	(Ljava/lang/String;)Lcom/jirbo/adcolony/aq;
    //   965: ldc_w 304
    //   968: invokevirtual 228	com/jirbo/adcolony/aq:a	(Ljava/lang/String;)Lcom/jirbo/adcolony/aq;
    //   971: aload 29
    //   973: invokevirtual 82	com/jirbo/adcolony/aq:b	(Ljava/lang/Object;)Lcom/jirbo/adcolony/aq;
    //   976: pop
    //   977: aload_0
    //   978: iconst_1
    //   979: putfield 246	com/jirbo/adcolony/aj:i	Z
    //   982: aload_0
    //   983: invokestatic 249	com/jirbo/adcolony/a:a	(Lcom/jirbo/adcolony/an;)V
    //   986: return
    //   987: aload_0
    //   988: getfield 263	com/jirbo/adcolony/aj:h	Z
    //   991: ifeq +74 -> 1065
    //   994: aload 9
    //   996: invokevirtual 307	java/net/HttpURLConnection:getResponseCode	()I
    //   999: istore 26
    //   1001: iload 26
    //   1003: ifle +62 -> 1065
    //   1006: getstatic 77	com/jirbo/adcolony/aq:a	Lcom/jirbo/adcolony/aq;
    //   1009: ldc_w 309
    //   1012: invokevirtual 228	com/jirbo/adcolony/aq:a	(Ljava/lang/String;)Lcom/jirbo/adcolony/aq;
    //   1015: iload 26
    //   1017: invokevirtual 231	com/jirbo/adcolony/aq:a	(I)Lcom/jirbo/adcolony/aq;
    //   1020: ldc_w 311
    //   1023: invokevirtual 82	com/jirbo/adcolony/aq:b	(Ljava/lang/Object;)Lcom/jirbo/adcolony/aq;
    //   1026: pop
    //   1027: getstatic 223	com/jirbo/adcolony/aq:b	Lcom/jirbo/adcolony/aq;
    //   1030: ldc_w 302
    //   1033: invokevirtual 228	com/jirbo/adcolony/aq:a	(Ljava/lang/String;)Lcom/jirbo/adcolony/aq;
    //   1036: aload_0
    //   1037: getfield 35	com/jirbo/adcolony/aj:c	Ljava/lang/String;
    //   1040: invokevirtual 82	com/jirbo/adcolony/aq:b	(Ljava/lang/Object;)Lcom/jirbo/adcolony/aq;
    //   1043: pop
    //   1044: aload_0
    //   1045: ldc 84
    //   1047: putfield 238	com/jirbo/adcolony/aj:l	Ljava/lang/String;
    //   1050: aload_0
    //   1051: iconst_0
    //   1052: putfield 240	com/jirbo/adcolony/aj:k	I
    //   1055: aload_0
    //   1056: iconst_1
    //   1057: putfield 246	com/jirbo/adcolony/aj:i	Z
    //   1060: aload_0
    //   1061: invokestatic 249	com/jirbo/adcolony/a:a	(Lcom/jirbo/adcolony/an;)V
    //   1064: return
    //   1065: aload_0
    //   1066: getfield 35	com/jirbo/adcolony/aj:c	Ljava/lang/String;
    //   1069: ldc_w 313
    //   1072: invokevirtual 96	java/lang/String:startsWith	(Ljava/lang/String;)Z
    //   1075: ifeq +229 -> 1304
    //   1078: getstatic 318	android/os/Build$VERSION:SDK_INT	I
    //   1081: bipush 10
    //   1083: if_icmplt +221 -> 1304
    //   1086: new 251	java/net/URL
    //   1089: dup
    //   1090: aload_0
    //   1091: getfield 35	com/jirbo/adcolony/aj:c	Ljava/lang/String;
    //   1094: invokespecial 252	java/net/URL:<init>	(Ljava/lang/String;)V
    //   1097: invokevirtual 256	java/net/URL:openConnection	()Ljava/net/URLConnection;
    //   1100: checkcast 320	javax/net/ssl/HttpsURLConnection
    //   1103: astore 10
    //   1105: aload_0
    //   1106: iconst_1
    //   1107: putfield 322	com/jirbo/adcolony/aj:j	Z
    //   1110: getstatic 77	com/jirbo/adcolony/aq:a	Lcom/jirbo/adcolony/aq;
    //   1113: ldc_w 324
    //   1116: invokevirtual 82	com/jirbo/adcolony/aq:b	(Ljava/lang/Object;)Lcom/jirbo/adcolony/aq;
    //   1119: pop
    //   1120: aload 10
    //   1122: new 326	com/jirbo/adcolony/ak
    //   1125: dup
    //   1126: aload_0
    //   1127: invokespecial 328	com/jirbo/adcolony/ak:<init>	(Lcom/jirbo/adcolony/aj;)V
    //   1130: invokevirtual 332	javax/net/ssl/HttpsURLConnection:setHostnameVerifier	(Ljavax/net/ssl/HostnameVerifier;)V
    //   1133: ldc_w 334
    //   1136: invokestatic 340	javax/net/ssl/SSLContext:getInstance	(Ljava/lang/String;)Ljavax/net/ssl/SSLContext;
    //   1139: astore 24
    //   1141: iconst_1
    //   1142: anewarray 342	javax/net/ssl/TrustManager
    //   1145: astore 25
    //   1147: aload 25
    //   1149: iconst_0
    //   1150: new 344	com/jirbo/adcolony/al
    //   1153: dup
    //   1154: iconst_0
    //   1155: invokespecial 347	com/jirbo/adcolony/al:<init>	(B)V
    //   1158: aastore
    //   1159: aload 24
    //   1161: aconst_null
    //   1162: aload 25
    //   1164: new 349	java/security/SecureRandom
    //   1167: dup
    //   1168: invokespecial 350	java/security/SecureRandom:<init>	()V
    //   1171: invokevirtual 354	javax/net/ssl/SSLContext:init	([Ljavax/net/ssl/KeyManager;[Ljavax/net/ssl/TrustManager;Ljava/security/SecureRandom;)V
    //   1174: aload 24
    //   1176: invokestatic 358	javax/net/ssl/SSLContext:setDefault	(Ljavax/net/ssl/SSLContext;)V
    //   1179: aload 24
    //   1181: invokevirtual 362	javax/net/ssl/SSLContext:getSocketFactory	()Ljavax/net/ssl/SSLSocketFactory;
    //   1184: invokestatic 366	javax/net/ssl/HttpsURLConnection:setDefaultSSLSocketFactory	(Ljavax/net/ssl/SSLSocketFactory;)V
    //   1187: getstatic 77	com/jirbo/adcolony/aq:a	Lcom/jirbo/adcolony/aq;
    //   1190: ldc_w 368
    //   1193: invokevirtual 82	com/jirbo/adcolony/aq:b	(Ljava/lang/Object;)Lcom/jirbo/adcolony/aq;
    //   1196: pop
    //   1197: ldc2_w 369
    //   1200: invokestatic 221	java/lang/Thread:sleep	(J)V
    //   1203: getstatic 77	com/jirbo/adcolony/aq:a	Lcom/jirbo/adcolony/aq;
    //   1206: ldc_w 372
    //   1209: invokevirtual 82	com/jirbo/adcolony/aq:b	(Ljava/lang/Object;)Lcom/jirbo/adcolony/aq;
    //   1212: pop
    //   1213: aload_0
    //   1214: getfield 322	com/jirbo/adcolony/aj:j	Z
    //   1217: ifeq +98 -> 1315
    //   1220: aload 10
    //   1222: invokevirtual 373	javax/net/ssl/HttpsURLConnection:getInputStream	()Ljava/io/InputStream;
    //   1225: astore 14
    //   1227: new 131	java/lang/StringBuilder
    //   1230: dup
    //   1231: invokespecial 133	java/lang/StringBuilder:<init>	()V
    //   1234: astore 15
    //   1236: sipush 1024
    //   1239: newarray byte
    //   1241: astore 16
    //   1243: aload 14
    //   1245: aload 16
    //   1247: iconst_0
    //   1248: sipush 1024
    //   1251: invokevirtual 291	java/io/InputStream:read	([BII)I
    //   1254: istore 17
    //   1256: goto +207 -> 1463
    //   1259: iinc 19 1
    //   1262: iload 19
    //   1264: iload 17
    //   1266: if_icmpge +59 -> 1325
    //   1269: aload 15
    //   1271: aload 16
    //   1273: iload 19
    //   1275: baload
    //   1276: i2c
    //   1277: invokevirtual 177	java/lang/StringBuilder:append	(C)Ljava/lang/StringBuilder;
    //   1280: pop
    //   1281: goto -22 -> 1259
    //   1284: astore 22
    //   1286: getstatic 77	com/jirbo/adcolony/aq:a	Lcom/jirbo/adcolony/aq;
    //   1289: ldc_w 375
    //   1292: invokevirtual 82	com/jirbo/adcolony/aq:b	(Ljava/lang/Object;)Lcom/jirbo/adcolony/aq;
    //   1295: pop
    //   1296: aload 22
    //   1298: invokevirtual 378	java/lang/Exception:printStackTrace	()V
    //   1301: goto -114 -> 1187
    //   1304: aload_0
    //   1305: iconst_0
    //   1306: putfield 322	com/jirbo/adcolony/aj:j	Z
    //   1309: aconst_null
    //   1310: astore 10
    //   1312: goto -125 -> 1187
    //   1315: aload 9
    //   1317: invokevirtual 285	java/net/HttpURLConnection:getInputStream	()Ljava/io/InputStream;
    //   1320: astore 14
    //   1322: goto -95 -> 1227
    //   1325: aload 14
    //   1327: aload 16
    //   1329: iconst_0
    //   1330: sipush 1024
    //   1333: invokevirtual 291	java/io/InputStream:read	([BII)I
    //   1336: istore 17
    //   1338: goto +125 -> 1463
    //   1341: aload 14
    //   1343: invokevirtual 298	java/io/InputStream:close	()V
    //   1346: aload_0
    //   1347: aload 15
    //   1349: invokevirtual 161	java/lang/StringBuilder:toString	()Ljava/lang/String;
    //   1352: putfield 238	com/jirbo/adcolony/aj:l	Ljava/lang/String;
    //   1355: aload_0
    //   1356: aload_0
    //   1357: getfield 238	com/jirbo/adcolony/aj:l	Ljava/lang/String;
    //   1360: invokevirtual 153	java/lang/String:length	()I
    //   1363: putfield 240	com/jirbo/adcolony/aj:k	I
    //   1366: aload_0
    //   1367: getfield 35	com/jirbo/adcolony/aj:c	Ljava/lang/String;
    //   1370: ldc_w 380
    //   1373: invokevirtual 384	java/lang/String:contains	(Ljava/lang/CharSequence;)Z
    //   1376: ifeq +9 -> 1385
    //   1379: invokestatic 390	java/lang/System:currentTimeMillis	()J
    //   1382: putstatic 393	com/jirbo/adcolony/a:I	J
    //   1385: getstatic 223	com/jirbo/adcolony/aq:b	Lcom/jirbo/adcolony/aq;
    //   1388: ldc_w 302
    //   1391: invokevirtual 228	com/jirbo/adcolony/aq:a	(Ljava/lang/String;)Lcom/jirbo/adcolony/aq;
    //   1394: aload_0
    //   1395: getfield 35	com/jirbo/adcolony/aj:c	Ljava/lang/String;
    //   1398: invokevirtual 82	com/jirbo/adcolony/aq:b	(Ljava/lang/Object;)Lcom/jirbo/adcolony/aq;
    //   1401: pop
    //   1402: goto -425 -> 977
    //   1405: aload_0
    //   1406: iconst_0
    //   1407: putfield 246	com/jirbo/adcolony/aj:i	Z
    //   1410: aload_0
    //   1411: invokestatic 249	com/jirbo/adcolony/a:a	(Lcom/jirbo/adcolony/an;)V
    //   1414: return
    //   1415: astore 12
    //   1417: goto -214 -> 1203
    //   1420: astore 7
    //   1422: goto -765 -> 657
    //   1425: iload 34
    //   1427: iconst_m1
    //   1428: if_icmpeq -494 -> 934
    //   1431: iload 32
    //   1433: ifle -538 -> 895
    //   1436: iload 34
    //   1438: iload 32
    //   1440: if_icmple +7 -> 1447
    //   1443: iload 32
    //   1445: istore 34
    //   1447: iload 32
    //   1449: iload 34
    //   1451: isub
    //   1452: istore 32
    //   1454: goto -559 -> 895
    //   1457: astore_2
    //   1458: iload_1
    //   1459: istore_3
    //   1460: goto -861 -> 599
    //   1463: iload 17
    //   1465: iconst_m1
    //   1466: if_icmpeq -125 -> 1341
    //   1469: iconst_m1
    //   1470: istore 19
    //   1472: goto -213 -> 1259
    // Local variable table:
    //   start	length	slot	name	signature
    //   0	1475	0	this	aj
    //   1	1458	1	m	int
    //   596	25	2	localIOException1	java.io.IOException
    //   1457	1	2	localIOException2	java.io.IOException
    //   598	862	3	n	int
    //   650	3	5	l1	long
    //   1420	1	7	localInterruptedException	java.lang.InterruptedException
    //   776	540	9	localHttpURLConnection	java.net.HttpURLConnection
    //   1103	208	10	localHttpsURLConnection	javax.net.ssl.HttpsURLConnection
    //   1415	1	12	localException1	java.lang.Exception
    //   1225	117	14	localInputStream1	java.io.InputStream
    //   1234	114	15	localStringBuilder1	java.lang.StringBuilder
    //   1241	87	16	arrayOfByte1	byte[]
    //   1254	213	17	i1	int
    //   1259	212	19	i2	int
    //   1284	13	22	localException2	java.lang.Exception
    //   1139	41	24	localSSLContext	javax.net.ssl.SSLContext
    //   1145	18	25	arrayOfTrustManager	javax.net.ssl.TrustManager[]
    //   999	17	26	i3	int
    //   840	132	29	str1	String
    //   851	94	30	localFileOutputStream	java.io.FileOutputStream
    //   858	77	31	localInputStream2	java.io.InputStream
    //   865	588	32	i4	int
    //   877	42	33	arrayOfByte2	byte[]
    //   890	562	34	i5	int
    //   27	701	37	str2	String
    //   33	160	38	str3	String
    //   37	132	39	str4	String
    //   76	25	40	i6	int
    //   118	577	41	localSocket	java.net.Socket
    //   140	156	42	localPrintStream	java.io.PrintStream
    //   147	398	43	localInputStream3	java.io.InputStream
    //   156	126	44	localStringBuilder2	java.lang.StringBuilder
    //   286	23	59	str5	String
    //   321	62	61	localStringBuilder3	java.lang.StringBuilder
    //   328	50	62	i7	int
    //   387	31	64	str6	String
    //   396	15	65	i8	int
    //   411	11	66	i9	int
    //   429	60	67	str7	String
    //   493	194	68	i10	int
    //   502	199	69	localStringBuilder4	java.lang.StringBuilder
    //   684	8	72	localSocketTimeoutException	java.net.SocketTimeoutException
    //   514	11	73	i11	int
    //   549	3	75	i12	int
    // Exception table:
    //   from	to	target	type
    //   23	35	596	java/io/IOException
    //   39	67	596	java/io/IOException
    //   67	78	596	java/io/IOException
    //   84	107	596	java/io/IOException
    //   107	330	596	java/io/IOException
    //   336	372	596	java/io/IOException
    //   372	379	596	java/io/IOException
    //   382	398	596	java/io/IOException
    //   403	431	596	java/io/IOException
    //   431	450	596	java/io/IOException
    //   453	485	596	java/io/IOException
    //   488	495	596	java/io/IOException
    //   495	504	596	java/io/IOException
    //   509	516	596	java/io/IOException
    //   522	531	596	java/io/IOException
    //   544	551	596	java/io/IOException
    //   562	587	596	java/io/IOException
    //   590	593	596	java/io/IOException
    //   691	694	596	java/io/IOException
    //   694	758	596	java/io/IOException
    //   509	516	684	java/net/SocketTimeoutException
    //   522	531	684	java/net/SocketTimeoutException
    //   544	551	684	java/net/SocketTimeoutException
    //   1133	1187	1284	java/lang/Exception
    //   1197	1203	1415	java/lang/Exception
    //   652	657	1420	java/lang/InterruptedException
    //   7	23	1457	java/io/IOException
    //   759	799	1457	java/io/IOException
    //   799	833	1457	java/io/IOException
    //   833	892	1457	java/io/IOException
    //   895	929	1457	java/io/IOException
    //   934	977	1457	java/io/IOException
    //   977	986	1457	java/io/IOException
    //   987	1001	1457	java/io/IOException
    //   1006	1064	1457	java/io/IOException
    //   1065	1133	1457	java/io/IOException
    //   1133	1187	1457	java/io/IOException
    //   1187	1197	1457	java/io/IOException
    //   1197	1203	1457	java/io/IOException
    //   1203	1227	1457	java/io/IOException
    //   1227	1256	1457	java/io/IOException
    //   1269	1281	1457	java/io/IOException
    //   1286	1301	1457	java/io/IOException
    //   1304	1309	1457	java/io/IOException
    //   1315	1322	1457	java/io/IOException
    //   1325	1338	1457	java/io/IOException
    //   1341	1385	1457	java/io/IOException
    //   1385	1402	1457	java/io/IOException
  }
}


/* Location:           C:\Users\vishnu\Desktop\New folder (3)\classes_dex2jar.jar
 * Qualified Name:     com.jirbo.adcolony.aj
 * JD-Core Version:    0.7.0.1
 */